Workbook

Sheet Clients
A1: Client_ID | B1: Company_Name | C1: Industry | D1: Contract_Type | E1: Region | F1: City | G1: Onboarding_Date | H1: Satisfaction_Score | I1: Tenure_Years | J1: Annual_Contract_Value | K1: Account_Status
A2: CLI-0113 | B2: CloudNine Enterprises | C2: Healthcare | D2: Managed Services | E2: South | F2: Hyderabad | G2: 44281 | H2: 3.2 | I2: 4 | J2: 75000 | K2: Active
A3: CLI-0047 | B3: DigitalForge Services | C3: Government | D3: Managed Services | E3: East | F3: Kolkata | G3: 45171 | H3: 3.1 | I3: 1.6 | J3: 100000 | K3: Active
A4: CLI-0083 | B4: OmniSoft Digital | C4: Media | D4: Annual License | E4: East | F4: Kolkata | G4: 43835 | H4: 4.4 | I4: 5.2 | J4: 300000 | K4: Active
A5: CLI-0111 | B5: CloudNine Enterprises | C5: Banking | D5: Monthly SaaS | E5: West | F5: Ahmedabad | G5: 44775 | H5: 4.9 | I5: 2.7 | J5: 75000 | K5: Active
A6: CLI-0199 | B6: GreenPulse Technologies | C6: Banking | D6: Monthly SaaS | E6: West | F6: Ahmedabad | G6: 44538 | H6: 4.3 | I6: 3.3 | J6: 75000 | K6: Active
A7: CLI-0213 | B7: SwiftCode Solutions | C7: Logistics | D7: Monthly SaaS | E7: West | F7: Surat | G7: 44170 | H7: 3.8 | I7: 4.3 | J7: 500000 | K7: Active
A8: CLI-0042 | B8: NovaTech Group | C8: EdTech | D8: Annual License | E8: West | F8: Surat | G8: 43682 | H8: 3.4 | I8: 5.7 | J8: 750000 | K8: Churned
A9: CLI-0217 | B9: BlueOrbit Systems | C9: EdTech | D9: Multi-Year | E9: East | F9: Kolkata | G9: 43510 | H9: 4.3 | I9: 6.1 | J9: 100000 | K9: Churned
A10: CLI-0070 | B10: SilverEdge Labs | C10: Media | D10: Monthly SaaS | E10: North | F10: Lucknow | G10: 43494 | H10: 2.8 | I10: 6.2 | J10: 300000 | K10: Active
A11: CLI-0115 | B11: DataWeave Corp | C11: Healthcare | D11: Managed Services | E11: East | F11: Patna | G11: 45209 | H11: 4.3 | I11: 1.5 | J11: 100000 | K11: Churned
A12: CLI-0264 | B12: BrightPath Technologies | C12: Insurance | D12: Project-Based | E12: South | F12: Kochi | G12: 43474 | H12: 2.6 | I12: 6.2 | J12: 500000 | K12: Churned
A13: CLI-0219 | B13: OmniSoft Corp | C13: Manufacturing | D13: Managed Services | E13: South | F13: Kochi | G13: 44094 | H13: 3.2 | I13: 4.5 | J13: 100000 | K13: Churned
... A52: CLI-0164 | B52: SilverEdge Corp | C52: Media | D52: Project-Based | E52: West | F52: Pune | G52: 44858 | H52: 3.5 | I52: 2.4 | J52: 200000 | K52: Churned
A53: CLI-0274 | B53: Apex Technologies | C53: EdTech | D53: Project-Based | E53: South | F53: Chennai | G53: 45429 | I53: 0.9 | J53: 300000 | K53: Active
A54: CLI-0271 | B54: CrestLine Systems | C54: Media | D54: Annual License | E54: West | F54: Mumbai | G54: 44343 | H54: 3.2 | I54: 3.8 | J54: 100000 | K54: Active
A55: CLI-0025 | B55: InfraMax Solutions | C55: Retail | D55: Monthly SaaS | E55: West | F55: Pune | G55: 44012 | H55: 4.3 | I55: 4.8 | J55: 500000 | K55: At Risk
A56: CLI-0041 | B56: BrightPath Labs | C56: Logistics | D56: Multi-Year | E56: North | F56: Chandigarh | G56: 43674 | H56: 3.3 | I56: 5.7 | J56: 75000 | K56: Churned
A57: CLI-0029 | B57: InfraMax Corp | C57: Logistics | D57: Monthly SaaS | E57: South | F57: Unspecified | G57: 44327 | H57: 3.4 | I57: 3.9 | J57: 100000 | K57: Active
A58: CLI-0136 | B58: CoreLogic Corp | C58: Telecom | D58: Annual License | E58: North | F58: Chandigarh | G58: 44561 | H58: 4.6 | I58: 3.2 | J58: 50000 | K58: At Risk
A59: CLI-0050 | B59: InfraMax Services | C59: Government | D59: Managed Services | E59: North | F59: Delhi | G59: 45406 | H59: 4.1 | I59: 0.9 | J59: 200000 | K59: Active
A60: CLI-0032 | B60: TechVista Infotech | C60: Retail | D60: Annual License | E60: North | F60: Lucknow | G60: 43914 | H60: 4.9 | I60: 5 | J60: 1000000 | K60: Active
A61: CLI-0161 | B61: Pinnacle Group | C61: Banking | D61: Multi-Year | E61: South | F61: Kochi | G61: 44021 | I61: 4.7 | J61: 75000 | K61: Active
A62: CLI-0044 | B62: Apex Enterprises | C62: EdTech | D62: Multi-Year | E62: West | F62: Pune | G62: 44192 | H62: 3.4 | I62: 4.3 | J62: 200000 | K62: Active
A63: CLI-0085 | B63: OmniSoft Solutions | C63: Healthcare | D63: Monthly SaaS | E63: West | F63: Surat | G63: 44460 | H63: 3.5 | I63: 3.5 | J63: 150000 | K63: Churned
A64: CLI-0065 | B64: Zenith Infotech | C64: Insurance | D64: Monthly SaaS | E64: West | F64: Ahmedabad | G64: 44831 | I64: 2.5 | J64: 750000 | K64: At Risk
A65: CLI-0037 | B65: GreenPulse Labs | C65: Insurance | D65: Annual License | E65: West | F65: Ahmedabad | G65: 44835 | H65: 3.5 | I65: 2.5 | J65: 100000 | K65: Churned
A66: CLI-0172 | B66: InfraMax Group | C66: Banking | D66: Monthly SaaS | E66: North | F66: Delhi | G66: 45040 | H66: 4.2 | I66: 1.9 | J66: 100000 | K66: Active
A67: CLI-0112 | B67: Apex Systems | C67: Government | D67: Project-Based | E67: North | F67: Chandigarh | G67: 43603 | H67: 4.1 | I67: 5.9 | J67: 300000 | K67: Active
A68: CLI-0177 | B68: BrightPath Labs | C68: Logistics | D68: Annual License | E68: South | F68: Chennai | G68: 44036 | H68: 4.5 | I68: 4.7 | J68: 75000 | K68: Active
A69: CLI-0016 | B69: SwiftCode Technologies | C69: Banking | D69: Managed Services | E69: North | F69: Delhi | G69: 45363 | H69: 3.1 | I69: 1.1 | J69: 500000 | K69: Active
A70: CLI-0200 | B70: CrestLine Services | C70: Healthcare | D70: Managed Services | E70: North | F70: Chandigarh | G70: 44983 | H70: 2.6 | I70: 2.1 | J70: 50000 | K70: Active
A71: CLI-0153 | B71: DigitalForge Infotech | C71: EdTech | D71: Monthly SaaS | E71: North | F71: Chandigarh | G71: 45385 | H71: 4.4 | I71: 1 | J71: 750000 | K71: At Risk
A72: CLI-0292 | B72: SilverEdge Solutions | C72: Retail | D72: Managed Services | E72: South | F72: Chennai | G72: 44755 | H72: 4.7 | I72: 2.7 | J72: 100000 | K72: Active
A73: CLI-0082 | B73: BrightPath Group | C73: Manufacturing | D73: Multi-Year | E73: West | F73: Pune | G73: 45201 | H73: 4.6 | I73: 1.5 | J73: 300000 | K73: Active
A74: CLI-0165 | B74: Zenith Labs | C74: EdTech | D74: Monthly SaaS | E74: North | F74: Delhi | G74: 43476 | H74: 3.6 | I74: 6.2 | J74: 200000 | K74: Active
A75: CLI-0273 | B75: SwiftCode Group | C75: Logistics | D75: Annual License | E75: East | F75: Bhubaneswar | G75: 45275 | H75: 3.3 | I75: 1.3 | J75: 300000 | K75: Active
A76: CLI-0076 | B76: Pinnacle Solutions | C76: Retail | D76: Annual License | E76: East | F76: Bhubaneswar | G76: 44671 | H76: 2.9 | I76: 2.9 | J76: 50000 | K76: Active
... A80: CLI-0284 | B80: SilverEdge Infotech | C80: Logistics | D80: Monthly SaaS | E80: East | F80: Bhubaneswar | G80: 44857 | H80: 4.7 | I80: 2.4 | J80: 750000 | K80: Active
A81: CLI-0086 | B81: DigitalForge Group | C81: Telecom | D81: Annual License | E81: South | F81: Kochi | G81: 44693 | I81: 2.9 | J81: 150000 | K81: Active
A82: CLI-0120 | B82: BrightPath Services | C82: Manufacturing | D82: Managed Services | E82: West | F82: Mumbai | G82: 44485 | H82: 3.9 | I82: 3.5 | J82: 200000 | K82: Active
A83: CLI-0215 | B83: SilverEdge Digital | C83: Logistics | D83: Monthly SaaS | E83: South | F83: Chennai | G83: 43950 | H83: 4.5 | I83: 4.9 | J83: 300000 | K83: At Risk
A84: CLI-0193 | B84: Zenith Technologies | C84: Government | D84: Project-Based | E84: East | F84: Guwahati | G84: 44110 | H84: 3.1 | I84: 4.5 | J84: 75000 | K84: Active
A85: CLI-0250 | B85: Vertex Technologies | C85: Banking | D85: Annual License | E85: North | F85: Unspecified | G85: 44375 | H85: 3.9 | I85: 3.8 | J85: 750000 | K85: Churned
A86: CLI-0191 | B86: Apex Corp | C86: Healthcare | D86: Project-Based | E86: South | F86: Kochi | G86: 43611 | H86: 2.7 | I86: 5.8 | J86: 75000 | K86: Active
A87: CLI-0051 | B87: NetDynamic Digital | C87: Insurance | D87: Monthly SaaS | E87: North | F87: Chandigarh | G87: 44056 | H87: 4.3 | I87: 4.6 | J87: 750000 | K87: Active
A88: CLI-0007 | B88: Zenith Infotech | C88: Media | D88: Managed Services | E88: East | F88: Guwahati | G88: 45304 | H88: 3.4 | I88: 1.2 | J88: 100000 | K88: Active
A89: CLI-0073 | B89: DigitalForge Digital | C89: Logistics | D89: Monthly SaaS | E89: North | F89: Jaipur | G89: 43910 | H89: 4.9 | I89: 5 | J89: 300000 | K89: Active
A90: CLI-0114 | B90: GreenPulse Enterprises | C90: Manufacturing | D90: Managed Services | E90: East | F90: Guwahati | G90: 43875 | H90: 4.6 | I90: 5.1 | J90: 750000 | K90: Active
A91: CLI-0169 | B91: OmniSoft Systems | C91: Telecom | D91: Monthly SaaS | E91: South | F91: Kochi | G91: 44109 | H91: 3.5 | I91: 4.5 | J91: 300000 | K91: Active
A92: CLI-0039 | B92: InfraMax Services | C92: Healthcare | D92: Project-Based | E92: North | F92: Delhi | G92: 45415 | H92: 4.1 | I92: 0.9 | J92: 50000 | K92: Churned
A93: CLI-0063 | B93: SilverEdge Services | C93: Unspecified | D93: Annual License | E93: West | F93: Mumbai | G93: 45023 | H93: 4.7 | I93: 2 | J93: 750000 | K93: Active
... A100: CLI-0156 | B100: SwiftCode Corp | C100: Telecom | D100: Project-Based | E100: West | F100: Surat | G100: 43810 | H100: 3.4 | I100: 5.3 | J100: 100000 | K100: Churned
A101: CLI-0023 | B101: InfraMax Group | C101: Banking | D101: Annual License | E101: North | F101: Chandigarh | G101: 44583 | I101: 3.2 | J101: 300000 | K101: Active
A102: CLI-0186 | B102: SilverEdge Labs | C102: Insurance | D102: Multi-Year | E102: East | F102: Guwahati | G102: 44234 | H102: 4.1 | I102: 4.1 | J102: 75000 | K102: Active
A103: CLI-0143 | B103: NetDynamic Technologies | C103: Manufacturing | D103: Managed Services | E103: West | F103: Mumbai | G103: 45306 | H103: 4.5 | I103: 1.2 | J103: 750000 | K103: Active
A104: CLI-0220 | B104: BrightPath Solutions | C104: Retail | D104: Managed Services | E104: East | F104: Bhubaneswar | G104: 44775 | H104: 4.8 | I104: 2.7 | J104: 100000 | K104: Active
A105: CLI-0095 | B105: SwiftCode Labs | C105: Telecom | D105: Monthly SaaS | E105: South | F105: Hyderabad | G105: 43632 | H105: 2.9 | I105: 5.8 | J105: 300000 | K105: Active
A106: CLI-0279 | B106: NetDynamic Labs | C106: Logistics | D106: Annual License | E106: West | F106: Pune | G106: 44558 | H106: 4.4 | I106: 3.3 | J106: 1000000 | K106: Active
A107: CLI-0300 | B107: Pinnacle Infotech | C107: Insurance | D107: Multi-Year | E107: North | F107: Chandigarh | G107: 44507 | H107: 3.3 | I107: 3.4 | J107: 1000000 | K107: Active
A108: CLI-0291 | B108: Zenith Systems | C108: Retail | D108: Monthly SaaS | E108: North | F108: Chandigarh | G108: 44315 | H108: 4.3 | I108: 3.9 | J108: 750000 | K108: Active
A109: CLI-0290 | B109: SilverEdge Group | C109: Logistics | D109: Monthly SaaS | E109: East | F109: Guwahati | G109: 45089 | H109: 4 | I109: 1.8 | J109: 1000000 | K109: At Risk
A110: CLI-0110 | B110: GreenPulse Technologies | C110: Logistics | D110: Annual License | E110: West | F110: Pune | G110: 44583 | H110: 2.8 | I110: 3.2 | J110: 300000 | K110: Active
A111: CLI-0253 | B111: DigitalForge Systems | C111: Healthcare | D111: Managed Services | E111: North | F111: Delhi | G111: 45318 | H111: 3.1 | I111: 1.2 | J111: 200000 | K111: Active
A112: CLI-0167 | B112: SafeHaven Systems | C112: Logistics | D112: Multi-Year | E112: South | F112: Hyderabad | G112: 44082 | H112: 2.9 | I112: 4.6 | J112: 100000 | K112: Active
A113: CLI-0157 | B113: Unspecified | C113: Banking | D113: Annual License | E113: North | F113: Delhi | G113: 44310 | H113: 4.1 | I113: 3.9 | J113: 75000 | K113: Churned
... A147: CLI-0149 | B147: Vertex Systems | C147: Media | D147: Monthly SaaS | E147: South | F147: Hyderabad | G147: 44648 | H147: 4.2 | I147: 3 | J147: 300000 | K147: Active
A148: CLI-0245 | B148: CrestLine Technologies | C148: Insurance | D148: Monthly SaaS | E148: South | F148: Hyderabad | G148: 44765 | I148: 2.7 | J148: 750000 | K148: Active
A149: CLI-0054 | B149: BrightPath Digital | C149: Banking | D149: Monthly SaaS | E149: North | F149: Chandigarh | G149: 44429 | H149: 3.6 | I149: 3.6 | J149: 200000 | K149: Active
A150: CLI-0004 | B150: OmniSoft Corp | C150: Government | D150: Multi-Year | E150: North | F150: Delhi | G150: 44820 | H150: 3.2 | I150: 2.5 | J150: 75000 | K150: At Risk
A151: CLI-0232 | B151: BrightPath Digital | C151: Insurance | D151: Annual License | E151: South | F151: Hyderabad | G151: 44291 | H151: 4 | I151: 4 | J151: 500000 | K151: Active
A152: CLI-0231 | B152: InfraMax Technologies | C152: Logistics | D152: Multi-Year | E152: South | F152: Bangalore | G152: 45360 | H152: 4.4 | I152: 1.1 | J152: 200000 | K152: At Risk
A153: CLI-0187 | B153: DigitalForge Corp | C153: Government | D153: Annual License | E153: North | F153: Lucknow | G153: 44766 | H153: 3.4 | I153: 2.7 | J153: 75000 | K153: Churned
A154: CLI-0234 | B154: DataWeave Services | C154: Logistics | D154: Managed Services | E154: North | F154: Chandigarh | G154: 44370 | H154: 4.6 | I154: 3.8 | J154: 750000 | K154: Churned
A155: CLI-0210 | B155: BrightPath Digital | C155: Telecom | D155: Annual License | E155: North | F155: Delhi | G155: 43870 | H155: 3.6 | I155: 5.1 | J155: 100000 | K155: Active
A156: CLI-0295 | B156: Zenith Digital | C156: Healthcare | D156: Multi-Year | E156: West | F156: Mumbai | G156: 45263 | H156: 3.8 | I156: 1.3 | J156: 75000 | K156: Active
A157: CLI-0101 | B157: Pinnacle Services | C157: Healthcare | D157: Multi-Year | E157: East | F157: Guwahati | G157: 45320 | H157: 4.6 | I157: 1.2 | J157: 75000 | K157: At Risk
A158: CLI-0089 | B158: InfraMax Technologies | C158: Manufacturing | D158: Project-Based | E158: West | F158: Mumbai | G158: 44276 | H158: 4.4 | I158: 4 | J158: 150000 | K158: Active
A159: CLI-0223 | B159: Pinnacle Technologies | C159: EdTech | D159: Multi-Year | E159: West | F159: Pune | G159: 44965 | H159: 4.9 | I159: 2.1 | J159: 75000 | K159: Active
A160: CLI-0009 | B160: DataWeave Technologies | C160: Telecom | D160: Project-Based | E160: South | F160: Kochi | G160: 43472 | H160: 4.7 | I160: 6.2 | J160: 200000 | K160: At Risk
... A175: CLI-0188 | B175: DataWeave Services | C175: EdTech | D175: Managed Services | E175: South | F175: Unspecified | G175: 45080 | H175: 4.2 | I175: 1.8 | J175: 50000 | K175: Active
A176: CLI-0216 | B176: BrightPath Infotech | C176: Insurance | D176: Managed Services | E176: East | F176: Unspecified | G176: 44470 | I176: 3.5 | J176: 50000 | K176: Active
A177: CLI-0196 | B177: Vertex Solutions | C177: Logistics | D177: Managed Services | E177: East | F177: Guwahati | G177: 44333 | H177: 2.7 | I177: 3.9 | J177: 1000000 | K177: Active
A178: CLI-0096 | B178: NovaTech Services | C178: Media | D178: Project-Based | E178: East | F178: Unspecified | G178: 44838 | H178: 4.9 | I178: 2.5 | J178: 1000000 | K178: Active
A179: CLI-0249 | B179: SilverEdge Infotech | C179: Retail | D179: Multi-Year | E179: North | F179: Chandigarh | G179: 43718 | H179: 4.1 | I179: 5.6 | J179: 50000 | K179: Active
A180: CLI-0011 | B180: CoreLogic Infotech | C180: Banking | D180: Multi-Year | E180: North | F180: Delhi | G180: 44964 | H180: 2.7 | I180: 2.1 | J180: 1000000 | K180: Churned
A181: CLI-0139 | B181: OmniSoft Labs | C181: Unspecified | D181: Managed Services | E181: East | F181: Kolkata | G181: 44286 | H181: 3 | I181: 4 | J181: 100000 | K181: Active
A182: CLI-0002 | B182: Apex Group | C182: Manufacturing | D182: Managed Services | E182: West | F182: Pune | G182: 44385 | H182: 4.5 | I182: 3.7 | J182: 50000 | K182: Churned
A183: CLI-0158 | B183: OmniSoft Enterprises | C183: Insurance | D183: Annual License | E183: North | F183: Lucknow | G183: 43490 | I183: 6.2 | J183: 200000 | K183: Active
A184: CLI-0127 | B184: Zenith Corp | C184: Insurance | D184: Managed Services | E184: West | F184: Pune | G184: 44707 | H184: 2.8 | I184: 2.8 | J184: 300000 | K184: Active
A185: CLI-0170 | B185: TechVista Services | C185: Logistics | D185: Monthly SaaS | E185: North | F185: Chandigarh | G185: 44678 | H185: 2.9 | I185: 2.9 | J185: 1000000 | K185: Active
A186: CLI-0241 | B186: Apex Enterprises | C186: Telecom | D186: Monthly SaaS | E186: West | F186: Surat | G186: 44261 | H186: 4 | I186: 4.1 | J186: 150000 | K186: Active
A187: CLI-0021 | B187: CoreLogic Digital | C187: Media | D187: Annual License | E187: East | F187: Kolkata | G187: 45388 | H187: 3.2 | I187: 1 | J187: 75000 | K187: Churned
A188: CLI-0031 | B188: SilverEdge Services | C188: Manufacturing | D188: Multi-Year | E188: South | F188: Bangalore | G188: 43560 | H188: 3.7 | I188: 6 | J188: 75000 | K188: Active
A189: CLI-0028 | B189: Vertex Labs | C189: Banking | D189: Managed Services | E189: South | F189: Hyderabad | G189: 44349 | H189: 4.2 | I189: 3.8 | J189: 300000 | K189: Active
A190: CLI-0040 | B190: Zenith Enterprises | C190: Healthcare | D190: Managed Services | E190: South | F190: Kochi | G190: 44898 | H190: 3.4 | I190: 2.3 | J190: 75000 | K190: Churned
A191: CLI-0092 | B191: Vertex Solutions | C191: EdTech | D191: Monthly SaaS | E191: North | F191: Delhi | G191: 44725 | H191: 3.5 | I191: 2.8 | J191: 1000000 | K191: At Risk
A192: CLI-0159 | B192: CrestLine Technologies | C192: Healthcare | D192: Managed Services | E192: South | F192: Chennai | G192: 43859 | H192: 3.1 | I192: 5.2 | J192: 300000 | K192: Active
A193: CLI-0228 | B193: SwiftCode Solutions | C193: Logistics | D193: Managed Services | E193: West | F193: Surat | G193: 44638 | H193: 3.7 | I193: 3 | J193: 75000 | K193: Active
A194: CLI-0238 | B194: Apex Enterprises | C194: Retail | D194: Multi-Year | E194: North | F194: Chandigarh | G194: 43982 | H194: 4.9 | I194: 4.8 | J194: 200000 | K194: Active
...

Sheet Finance_Expenses
A1: Expense_ID | B1: Department | C1: Category | D1: Vendor | E1: Amount_INR | F1: Budget_Allocated_INR | G1: Recomputed_Variance_INR | H1: Old_Variance_INR | I1: Expense_Date | J1: Approval_Status | K1: Payment_Mode | L1: Fiscal_Year | M1: Remarks | N1: Amount_Type_Flag | O1: High_Value_Pending_Rejected_Flag
A2: EXP-00594 | B2: Unspecified | C2: Cloud Infrastructure | D2: Slack | E2: 209189 | F2: 170793.17 | G2: =IF(Table13[[#This Row],[Budget_Allocated_INR]]="","",Table13[[#This Row],[Amount_INR]]-Table13[[#This Row],[Budget_Allocated_INR]]) -> 38395.83 | H2: 38395.83 | I2: 45126 | J2: Pending | K2: Vendor Credit | L2: FY2023-2024 | M2: Under review | N2: Expense | O2: Flag: High-Value Pending
A3: EXP-00495 | B3: Operations | C3: Utilities | D3: HubSpot | E3: 6214 | F3: 7523.05 | G3: =IF(Table13[[#This Row],[Budget_Allocated_INR]]="","",Table13[[#This Row],[Amount_INR]]-Table13[[#This Row],[Budget_Allocated_INR]]) -> -1309.05 | H3: -1309.05 | I3: 45209 | J3: Approved | K3: Bank Transfer | L3: FY2023-2024 | M3: Recurring | N3: Expense
A4: EXP-00587 | B4: Sales | C4: Marketing Spend | D4: SAP | E4: 499533 | F4: 550589.56 | G4: =IF(Table13[[#This Row],[Budget_Allocated_INR]]="","",Table13[[#This Row],[Amount_INR]]-Table13[[#This Row],[Budget_Allocated_INR]]) -> -51056.56 | H4: -51056.56 | I4: 45310 | J4: Approved | K4: Bank Transfer | L4: FY2023-2024 | M4: Recurring | N4: Expense
A5: EXP-00178 | B5: Finance | C5: Utilities | D5: Infosys | E5: 403234 | F5: 426617.54 | G5: =IF(Table13[[#This Row],[Budget_Allocated_INR]]="","",Table13[[#This Row],[Amount_INR]]-Table13[[#This Row],[Budget_Allocated_INR]]) -> -23383.54 | H5: -23383.54 | I5: 45732 | J5: Approved | K5: Bank Transfer | L5: FY2024-2025 | N5: Expense
A6: EXP-00869 | B6: Unspecified | C6: Cloud Infrastructure | D6: TCS | E6: 187461 | F6: 156297.94 | G6: =IF(Table13[[#This Row],[Budget_Allocated_INR]]="","",Table13[[#This Row],[Amount_INR]]-Table13[[#This Row],[Budget_Allocated_INR]]) -> 31163.06 | H6: 31163.06 | I6: 44963 | J6: Approved | K6: Credit Card | L6: FY2022-2023 | N6: Expense
A7: EXP-00674 | B7: Sales | C7: Hardware | D7: TCS | E7: 352393 | F7: 449410.33 | G7: =IF(Table13[[#This Row],[Budget_Allocated_INR]]="","",Table13[[#This Row],[Amount_INR]]-Table13[[#This Row],[Budget_Allocated_INR]]) -> -97017.33 | H7: -97017.33 | I7: 45365 | J7: Approved | K7: Bank Transfer | L7: FY2023-2024 | N7: Expense
A8: EXP-00181 | B8: Engineering | C8: Hardware | D8: Slack | E8: 361946 | F8: 354476.37 | G8: =IF(Table13[[#This Row],[Budget_Allocated_INR]]="","",Table13[[#This Row],[Amount_INR]]-Table13[[#This Row],[Budget_Allocated_INR]]) -> 7469.63 | H8: 7469.63 | I8: 45152 | J8: Pending | K8: Vendor Credit | L8: FY2023-2024 | M8: Urgent | N8: Expense | O8: Flag: High-Value Pending
A9: EXP-00277 | B9: Support | C9: Office Supplies | D9: Wipro | E9: 398503 | F9: 438557.67 | G9: =IF(Table13[[#This Row],[Budget_Allocated_INR]]="","",Table13[[#This Row],[Amount_INR]]-Table13[[#This Row],[Budget_Allocated_INR]]) -> -40054.67 | H9: -40054.67 | I9: 45145 | J9: Approved | K9: Credit Card | L9: FY2023-2024 | N9: Expense
A10: EXP-00515 | B10: Support | C10: Consulting Fees | D10: Oracle | E10: 345565 | F10: 382355.25 | G10: =IF(Table13[[#This Row],[Budget_Allocated_INR]]="","",Table13[[#This Row],[Amount_INR]]-Table13[[#This Row],[Budget_Allocated_INR]]) -> -36790.25 | H10: -36790.25 | I10: 45437 | J10: Approved | K10: Vendor Credit | L10: FY2024-2025 | M10: Duplicate entry | N10: Expense
A11: EXP-00339 | B11: Engineering | C11: Hardware | D11: HubSpot | E11: 441930 | F11: 426169.24 | G11: =IF(Table13[[#This Row],[Budget_Allocated_INR]]="","",Table13[[#This Row],[Amount_INR]]-Table13[[#This Row],[Budget_Allocated_INR]]) -> 15760.76 | H11: 15760.76 | I11: 45740 | J11: Approved | K11: Credit Card | L11: FY2024-2025 | M11: Under review | N11: Expense
A12: EXP-00555 | B12: Unspecified | C12: Office Supplies | D12: SAP | E12: 304214 | F12: 345611.18 | G12: =IF(Table13[[#This Row],[Budget_Allocated_INR]]="","",Table13[[#This Row],[Amount_INR]]-Table13[[#This Row],[Budget_Allocated_INR]]) -> -41397.18 | H12: -41397.18 | I12: 45689 | J12: Approved | K12: Bank Transfer | L12: FY2024-2025 | M12: Recurring | N12: Expense
A13: EXP-00803 | B13: Support | C13: Travel | D13: Freshdesk | E13: 65791 | F13: 59739.7 | G13: =IF(Table13[[#This Row],[Budget_Allocated_INR]]="","",Table13[[#This Row],[Amount_INR]]-Table13[[#This Row],[Budget_Allocated_INR]]) -> 6051.3 | H13: 6051.3 | I13: 45346 | J13: Approved | K13: Petty Cash | L13: FY2023-2024 | M13: Under review | N13: Expense
A14: EXP-00875 | B14: Engineering | C14: Software Licenses | D14: Google Cloud | E14: 49237 | G14: =IF(Table13[[#This Row],[Budget_Allocated_INR]]="","",Table13[[#This Row],[Amount_INR]]-Table13[[#This Row],[Budget_Allocated_INR]]) | H14: 7036.11 | I14: 45457 | J14: Pending | K14: Petty Cash | L14: FY2024-2025 | M14: Duplicate entry | N14: Expense
A15: EXP-00691 | B15: HR | C15: Office Supplies | D15: TCS | E15: 365283 | F15: 359381.54 | G15: =IF(Table13[[#This Row],[Budget_Allocated_INR]]="","",Table13[[#This Row],[Amount_INR]]-Table13[[#This Row],[Budget_Allocated_INR]]) -> 5901.46 | H15: 5901.46 | I15: 45645 | J15: Approved | K15: Credit Card | L15: FY2024-2025 | N15: Expense
A16: EXP-00233 | B16: HR | C16: Consulting Fees | D16: Google Cloud | E16: 201346 | F16: 197464.53 | G16: =IF(Table13[[#This Row],[Budget_Allocated_INR]]="","",Table13[[#This Row],[Amount_INR]]-Table13[[#This Row],[Budget_Allocated_INR]]) -> 3881.47 | I16: 45719 | J16: Pending | K16: Bank Transfer | L16: FY2024-2025 | M16: Under review | N16: Expense | O16: Flag: High-Value Pending
A17: EXP-00071 | B17: Sales | C17: Hardware | D17: HubSpot | E17: 375484 | F17: 303740.88 | G17: =IF(Table13[[#This Row],[Budget_Allocated_INR]]="","",Table13[[#This Row],[Amount_INR]]-Table13[[#This Row],[Budget_Allocated_INR]]) -> 71743.12 | H17: 71743.12 | I17: 45454 | J17: Pending | K17: Bank Transfer | L17: FY2024-2025 | M17: One-time | N17: Expense | O17: Flag: High-Value Pending
A18: EXP-00860 | B18: Operations | C18: Cloud Infrastructure | D18: Wipro | E18: 91274 | F18: 117271.6 | G18: =IF(Table13[[#This Row],[Budget_Allocated_INR]]="","",Table13[[#This Row],[Amount_INR]]-Table13[[#This Row],[Budget_Allocated_INR]]) -> -25997.6 | H18: -25997.6 | I18: 45367 | J18: Approved | K18: Petty Cash | L18: FY2023-2024 | N18: Expense
A19: EXP-00607 | B19: Finance | C19: Hardware | D19: Jira | E19: 58546 | F19: 54790.73 | G19: =IF(Table13[[#This Row],[Budget_Allocated_INR]]="","",Table13[[#This Row],[Amount_INR]]-Table13[[#This Row],[Budget_Allocated_INR]]) -> 3755.27 | H19: 3755.27 | I19: 45324 | J19: Approved | K19: Petty Cash | L19: FY2023-2024 | M19: Under review | N19: Expense
A20: EXP-00651 | B20: Unspecified | C20: Marketing Spend | D20: SAP | E20: 10904 | F20: 13676.8 | G20: =IF(Table13[[#This Row],[Budget_Allocated_INR]]="","",Table13[[#This Row],[Amount_INR]]-Table13[[#This Row],[Budget_Allocated_INR]]) -> -2772.8 | H20: -2772.8 | I20: 44973 | J20: Approved | K20: Vendor Credit | L20: FY2022-2023 | M20: Duplicate entry | N20: Expense
A21: EXP-00652 | B21: Operations | C21: Utilities | D21: AWS | E21: 65481 | F21: 81303.61 | G21: =IF(Table13[[#This Row],[Budget_Allocated_INR]]="","",Table13[[#This Row],[Amount_INR]]-Table13[[#This Row],[Budget_Allocated_INR]]) -> -15822.61 | H21: -15822.61 | I21: 44962 | J21: Pending | K21: Vendor Credit | L21: FY2022-2023 | M21: Duplicate entry | N21: Expense
A22: EXP-00369 | B22: Marketing | C22: Marketing Spend | D22: HubSpot | E22: 66000 | F22: 78840.27 | G22: =IF(Table13[[#This Row],[Budget_Allocated_INR]]="","",Table13[[#This Row],[Amount_INR]]-Table13[[#This Row],[Budget_Allocated_INR]]) -> -12840.27 | H22: -12840.27 | I22: 45341 | J22: Approved | K22: Credit Card | L22: FY2023-2024 | M22: Under review | N22: Expense
A23: EXP-00721 | B23: Finance | C23: Office Supplies | D23: Slack | E23: 32147 | F23: 36235.03 | G23: =IF(Table13[[#This Row],[Budget_Allocated_INR]]="","",Table13[[#This Row],[Amount_INR]]-Table13[[#This Row],[Budget_Allocated_INR]]) -> -4088.03 | H23: -4088.03 | I23: 45247 | J23: Approved | K23: Credit Card | L23: FY2023-2024 | N23: Expense
A24: EXP-00390 | B24: Unspecified | C24: Consulting Fees | D24: Wipro | E24: 312310 | F24: 339411.41 | G24: =IF(Table13[[#This Row],[Budget_Allocated_INR]]="","",Table13[[#This Row],[Amount_INR]]-Table13[[#This Row],[Budget_Allocated_INR]]) -> -27101.41 | H24: -27101.41 | I24: 45270 | J24: Pending | K24: Bank Transfer | L24: FY2023-2024 | M24: Duplicate entry | N24: Expense | O24: Flag: High-Value Pending
A25: EXP-00520 | B25: HR | C25: Utilities | D25: Infosys | E25: 145866 | F25: 176369.11 | G25: =IF(Table13[[#This Row],[Budget_Allocated_INR]]="","",Table13[[#This Row],[Amount_INR]]-Table13[[#This Row],[Budget_Allocated_INR]]) -> -30503.11 | H25: -30503.11 | I25: 45589 | J25: Approved | K25: Petty Cash | L25: FY2024-2025 | M25: Recurring | N25: Expense
A26: EXP-00971 | B26: Finance | C26: Training | D26: Oracle | E26: -270391 | F26: 224861.48 | G26: =IF(Table13[[#This Row],[Budget_Allocated_INR]]="","",Table13[[#This Row],[Amount_INR]]-Table13[[#This Row],[Budget_Allocated_INR]]) -> -495252.48 | H26: 45529.52 | I26: 44992 | J26: Approved | K26: Credit Card | L26: FY2022-2023 | M26: Duplicate entry | N26: Credit/Refund
A27: EXP-00411 | B27: HR | C27: Hardware | D27: Microsoft Azure | E27: 410046 | F27: 483620.72 | G27: =IF(Table13[[#This Row],[Budget_Allocated_INR]]="","",Table13[[#This Row],[Amount_INR]]-Table13[[#This Row],[Budget_Allocated_INR]]) -> -73574.72 | H27: -73574.72 | I27: 45456 | J27: Approved | K27: Petty Cash | L27: FY2024-2025 | N27: Expense
A28: EXP-00354 | B28: Sales | C28: Salaries | D28: Oracle | E28: 406494 | G28: =IF(Table13[[#This Row],[Budget_Allocated_INR]]="","",Table13[[#This Row],[Amount_INR]]-Table13[[#This Row],[Budget_Allocated_INR]]) | H28: -13532 | I28: 45553 | J28: Approved | K28: Credit Card | L28: FY2024-2025 | M28: Recurring | N28: Expense
A29: EXP-00600 | B29: Engineering | C29: Travel | D29: Zoom | E29: 66859 | F29: 75521.94 | G29: =IF(Table13[[#This Row],[Budget_Allocated_INR]]="","",Table13[[#This Row],[Amount_INR]]-Table13[[#This Row],[Budget_Allocated_INR]]) -> -8662.94 | H29: -8662.94 | I29: 45442 | J29: Approved | K29: Petty Cash | L29: FY2024-2025 | N29: Expense
A30: EXP-00034 | B30: Support | C30: Consulting Fees | D30: Oracle | E30: 389612 | F30: 356713.15 | G30: =IF(Table13[[#This Row],[Budget_Allocated_INR]]="","",Table13[[#This Row],[Amount_INR]]-Table13[[#This Row],[Budget_Allocated_INR]]) -> 32898.85 | H30: 32898.85 | I30: 45486 | J30: Pending | K30: Petty Cash | L30: FY2024-2025 | N30: Expense | O30: Flag: High-Value Pending
A31: EXP-00200 | B31: Sales | C31: Salaries | D31: TCS | E31: 397643 | F31: 366588.32 | G31: =IF(Table13[[#This Row],[Budget_Allocated_INR]]="","",Table13[[#This Row],[Amount_INR]]-Table13[[#This Row],[Budget_Allocated_INR]]) -> 31054.68 | I31: 45309 | J31: Pending | K31: Petty Cash | L31: FY2023-2024 | N31: Expense | O31: Flag: High-Value Pending
A32: EXP-00925 | B32: Sales | C32: Software Licenses | D32: Google Cloud | E32: 367122 | F32: 465065.53 | G32: =IF(Table13[[#This Row],[Budget_Allocated_INR]]="","",Table13[[#This Row],[Amount_INR]]-Table13[[#This Row],[Budget_Allocated_INR]]) -> -97943.53 | H32: -97943.53 | I32: 45084 | J32: Pending | K32: Credit Card | L32: FY2023-2024 | M32: One-time | N32: Expense | O32: Flag: High-Value Pending
A33: EXP-00546 | B33: Marketing | C33: Travel | D33: Adobe | E33: 65667 | F33: 72499.12 | G33: =IF(Table13[[#This Row],[Budget_Allocated_INR]]="","",Table13[[#This Row],[Amount_INR]]-Table13[[#This Row],[Budget_Allocated_INR]]) -> -6832.12 | H33: -6832.12 | I33: 45077 | J33: Approved | K33: Petty Cash | L33: FY2023-2024 | N33: Expense
A34: EXP-00602 | B34: Unspecified | C34: Salaries | D34: Wipro | E34: 350446 | F34: 293167.5 | G34: =IF(Table13[[#This Row],[Budget_Allocated_INR]]="","",Table13[[#This Row],[Amount_INR]]-Table13[[#This Row],[Budget_Allocated_INR]]) -> 57278.5 | H34: 57278.5 | I34: 45395 | J34: Approved | K34: Vendor Credit | L34: FY2024-2025 | N34: Expense
A35: EXP-00083 | B35: Support | C35: Maintenance | D35: Wipro | E35: 215496 | F35: 269360.68 | G35: =IF(Table13[[#This Row],[Budget_Allocated_INR]]="","",Table13[[#This Row],[Amount_INR]]-Table13[[#This Row],[Budget_Allocated_INR]]) -> -53864.68 | I35: 45427 | J35: Rejected | K35: Petty Cash | L35: FY2024-2025 | M35: Duplicate entry | N35: Expense | O35: Flag: High-Value Pending
A36: EXP-00750 | B36: Sales | C36: Recruitment | D36: Freshdesk | E36: 7227 | F36: 9023.9 | G36: =IF(Table13[[#This Row],[Budget_Allocated_INR]]="","",Table13[[#This Row],[Amount_INR]]-Table13[[#This Row],[Budget_Allocated_INR]]) -> -1796.9 | H36: -1796.9 | I36: 45131 | J36: Approved | K36: Vendor Credit | L36: FY2023-2024 | N36: Expense
A37: EXP-00172 | B37: Operations | C37: Travel | D37: AWS | E37: 481644 | F37: 431586.58 | G37: =IF(Table13[[#This Row],[Budget_Allocated_INR]]="","",Table13[[#This Row],[Amount_INR]]-Table13[[#This Row],[Budget_Allocated_INR]]) -> 50057.42 | H37: 50057.42 | I37: 45338 | J37: Approved | K37: Vendor Credit | L37: FY2023-2024 | M37: Urgent | N37: Expense
A38: EXP-00531 | B38: Sales | C38: Recruitment | D38: AWS | E38: -214583 | F38: 220195.61 | G38: =IF(Table13[[#This Row],[Budget_Allocated_INR]]="","",Table13[[#This Row],[Amount_INR]]-Table13[[#This Row],[Budget_Allocated_INR]]) -> -434778.61 | H38: -5612.61 | I38: 45157 | J38: Approved | K38: Petty Cash | L38: FY2023-2024 | N38: Credit/Refund
A39: EXP-00337 | B39: Sales | C39: Utilities | D39: HubSpot | E39: 71717 | F39: 89231.77 | G39: =IF(Table13[[#This Row],[Budget_Allocated_INR]]="","",Table13[[#This Row],[Amount_INR]]-Table13[[#This Row],[Budget_Allocated_INR]]) -> -17514.77 | H39: -17514.77 | I39: 45573 | J39: Approved | K39: Credit Card | L39: FY2024-2025 | M39: Urgent | N39: Expense
A40: EXP-00832 | B40: Engineering | C40: Training | D40: Infosys | E40: 352092 | F40: 424330.22 | G40: =IF(Table13[[#This Row],[Budget_Allocated_INR]]="","",Table13[[#This Row],[Amount_INR]]-Table13[[#This Row],[Budget_Allocated_INR]]) -> -72238.22 | H40: -72238.22 | I40: 45540 | J40: Approved | K40: Bank Transfer | L40: FY2024-2025 | M40: One-time | N40: Expense
A41: EXP-00717 | B41: HR | C41: Office Supplies | D41: Internal | E41: 3606815 | F41: 3411626.7 | G41: =IF(Table13[[#This Row],[Budget_Allocated_INR]]="","",Table13[[#This Row],[Amount_INR]]-Table13[[#This Row],[Budget_Allocated_INR]]) -> 195188.28 | H41: 195188.28 | I41: 45464 | J41: Pending | K41: Bank Transfer | L41: FY2024-2025 | M41: Recurring | N41: Expense | O41: Flag: High-Value Pending
A42: EXP-00601 | B42: Sales | C42: Cloud Infrastructure | D42: Wipro | E42: 128850 | F42: 118183.64 | G42: =IF(Table13[[#This Row],[Budget_Allocated_INR]]="","",Table13[[#This Row],[Amount_INR]]-Table13[[#This Row],[Budget_Allocated_INR]]) -> 10666.36 | H42: 10666.36 | I42: 45143 | J42: Approved | K42: Vendor Credit | L42: FY2023-2024 | N42: Expense
A43: EXP-00275 | B43: Operations | C43: Utilities | D43: SAP | E43: 166769 | F43: 196065.31 | G43: =IF(Table13[[#This Row],[Budget_Allocated_INR]]="","",Table13[[#This Row],[Amount_INR]]-Table13[[#This Row],[Budget_Allocated_INR]]) -> -29296.31 | H43: -29296.31 | I43: 45175 | J43: Approved | K43: Credit Card | L43: FY2023-2024 | M43: Recurring | N43: Expense
A44: EXP-00466 | B44: Support | C44: Software Licenses | D44: Adobe | E44: 454117 | G44: =IF(Table13[[#This Row],[Budget_Allocated_INR]]="","",Table13[[#This Row],[Amount_INR]]-Table13[[#This Row],[Budget_Allocated_INR]]) | H44: -112004.76 | I44: 45077 | J44: Approved | K44: Vendor Credit | L44: FY2023-2024 | M44: Under review | N44: Expense
A45: EXP-00663 | B45: Sales | C45: Recruitment | D45: Google Cloud | E45: 225901 | F45: 254208.33 | G45: =IF(Table13[[#This Row],[Budget_Allocated_INR]]="","",Table13[[#This Row],[Amount_INR]]-Table13[[#This Row],[Budget_Allocated_INR]]) -> -28307.33 | H45: -28307.33 | I45: 45520 | J45: Approved | K45: Petty Cash | L45: FY2024-2025 | M45: Recurring | N45: Expense
A46: EXP-00954 | B46: Engineering | C46: Training | D46: AWS | E46: 173047 | F46: 149662.31 | G46: =IF(Table13[[#This Row],[Budget_Allocated_INR]]="","",Table13[[#This Row],[Amount_INR]]-Table13[[#This Row],[Budget_Allocated_INR]]) -> 23384.69 | I46: 45249 | J46: Approved | K46: Vendor Credit | L46: FY2023-2024 | M46: Under review | N46: Expense
A47: EXP-00024 | B47: Finance | C47: Maintenance | D47: Infosys | E47: 247370 | F47: 268703.57 | G47: =IF(Table13[[#This Row],[Budget_Allocated_INR]]="","",Table13[[#This Row],[Amount_INR]]-Table13[[#This Row],[Budget_Allocated_INR]]) -> -21333.57 | H47: -21333.57 | I47: 45554 | J47: Approved | K47: Bank Transfer | L47: FY2024-2025 | N47: Expense
A48: EXP-00430 | B48: Engineering | C48: Marketing Spend | D48: Wipro | E48: 295595 | F48: 333028.71 | G48: =IF(Table13[[#This Row],[Budget_Allocated_INR]]="","",Table13[[#This Row],[Amount_INR]]-Table13[[#This Row],[Budget_Allocated_INR]]) -> -37433.71 | H48: -37433.71 | I48: 45555 | J48: Pending | K48: Vendor Credit | L48: FY2024-2025 | M48: Urgent | N48: Expense | O48: Flag: High-Value Pending
A49: EXP-00219 | B49: Finance | C49: Training | D49: HubSpot | E49: 344780 | F49: 378391.66 | G49: =IF(Table13[[#This Row],[Budget_Allocated_INR]]="","",Table13[[#This Row],[Amount_INR]]-Table13[[#This Row],[Budget_Allocated_INR]]) -> -33611.66 | H49: -33611.66 | I49: 44976 | J49: Approved | K49: Bank Transfer | L49: FY2022-2023 | N49: Expense
A50: EXP-00318 | B50: Finance | C50: Training | D50: Slack | E50: 228003 | F50: 192790.08 | G50: =IF(Table13[[#This Row],[Budget_Allocated_INR]]="","",Table13[[#This Row],[Amount_INR]]-Table13[[#This Row],[Budget_Allocated_INR]]) -> 35212.92 | H50: 35212.92 | I50: 45366 | J50: Approved | K50: Credit Card | L50: FY2023-2024 | M50: Under review | N50: Expense
A51: EXP-00235 | B51: Support | C51: Training | D51: Internal | E51: 205500 | F51: 166546.9 | G51: =IF(Table13[[#This Row],[Budget_Allocated_INR]]="","",Table13[[#This Row],[Amount_INR]]-Table13[[#This Row],[Budget_Allocated_INR]]) -> 38953.1 | H51: 38953.1 | I51: 45180 | J51: Approved | K51: Vendor Credit | L51: FY2023-2024 | M51: Duplicate entry | N51: Expense
A52: EXP-00231 | B52: Sales | C52: Utilities | D52: Adobe | E52: 336583 | F52: 372109.92 | G52: =IF(Table13[[#This Row],[Budget_Allocated_INR]]="","",Table13[[#This Row],[Amount_INR]]-Table13[[#This Row],[Budget_Allocated_INR]]) -> -35526.92 | H52: -35526.92 | I52: 44983 | J52: Approved | K52: Credit Card | L52: FY2022-2023 | M52: Under review | N52: Expense
A53: EXP-00680 | B53: Support | C53: Recruitment | D53: Jira | E53: 76037 | F53: 88996.48 | G53: =IF(Table13[[#This Row],[Budget_Allocated_INR]]="","",Table13[[#This Row],[Amount_INR]]-Table13[[#This Row],[Budget_Allocated_INR]]) -> -12959.48 | H53: -12959.48 | I53: 45229 | J53: Approved | K53: Bank Transfer | L53: FY2023-2024 | N53: Expense
A54: EXP-00301 | B54: Support | C54: Hardware | D54: Internal | E54: 51292 | F54: 52199.26 | G54: =IF(Table13[[#This Row],[Budget_Allocated_INR]]="","",Table13[[#This Row],[Amount_INR]]-Table13[[#This Row],[Budget_Allocated_INR]]) -> -907.26 | H54: -907.26 | I54: 45250 | J54: Approved | K54: Petty Cash | L54: FY2023-2024 | M54: Urgent | N54: Expense
A55: EXP-00617 | B55: Support | C55: Training | D55: HubSpot | E55: -307191 | F55: 328740.27 | G55: =IF(Table13[[#This Row],[Budget_Allocated_INR]]="","",Table13[[#This Row],[Amount_INR]]-Table13[[#This Row],[Budget_Allocated_INR]]) -> -635931.27 | H55: -21549.27 | I55: 45684 | J55: Approved | K55: Bank Transfer | L55: FY2024-2025 | M55: Under review | N55: Credit/Refund
A56: EXP-00994 | B56: Operations | C56: Marketing Spend | D56: Infosys | E56: 333909 | F56: 401580.86 | G56: =IF(Table13[[#This Row],[Budget_Allocated_INR]]="","",Table13[[#This Row],[Amount_INR]]-Table13[[#This Row],[Budget_Allocated_INR]]) -> -67671.86 | H56: -67671.86 | I56: 45317 | J56: Rejected | K56: Bank Transfer | L56: FY2023-2024 | M56: Recurring | N56: Expense | O56: Flag: High-Value Pending
A57: EXP-00548 | B57: Finance | C57: Training | D57: SAP | E57: 325449 | F57: 392529.63 | G57: =IF(Table13[[#This Row],[Budget_Allocated_INR]]="","",Table13[[#This Row],[Amount_INR]]-Table13[[#This Row],[Budget_Allocated_INR]]) -> -67080.63 | H57: -67080.63 | I57: 45709 | J57: Approved | K57: Bank Transfer | L57: FY2024-2025 | M57: Urgent | N57: Expense
A58: EXP-00738 | B58: Operations | C58: Consulting Fees | D58: Wipro | E58: 10526 | F58: 9003.53 | G58: =IF(Table13[[#This Row],[Budget_Allocated_INR]]="","",Table13[[#This Row],[Amount_INR]]-Table13[[#This Row],[Budget_Allocated_INR]]) -> 1522.47 | H58: 1522.47 | I58: 45217 | J58: Approved | K58: Bank Transfer | L58: FY2023-2024 | M58: Under review | N58: Expense
A59: EXP-00490 | B59: Sales | C59: Uncategorized | D59: SAP | E59: 464884 | F59: 581075.86 | G59: =IF(Table13[[#This Row],[Budget_Allocated_INR]]="","",Table13[[#This Row],[Amount_INR]]-Table13[[#This Row],[Budget_Allocated_INR]]) -> -116191.86 | H59: -116191.86 | I59: 45636 | J59: Rejected | K59: Vendor Credit | L59: FY2024-2025 | M59: Duplicate entry | N59: Expense | O59: Flag: High-Value Pending
A60: EXP-00449 | B60: Sales | C60: Recruitment | D60: Adobe | E60: 265649 | F60: 235191.89 | G60: =IF(Table13[[#This Row],[Budget_Allocated_INR]]="","",Table13[[#This Row],[Amount_INR]]-Table13[[#This Row],[Budget_Allocated_INR]]) -> 30457.11 | H60: 30457.11 | I60: 45298 | J60: Approved | K60: Credit Card | L60: FY2023-2024 | N60: Expense
A61: EXP-00147 | B61: Finance | C61: Travel | D61: Adobe | E61: 32268 | F61: 26832.63 | G61: =IF(Table13[[#This Row],[Budget_Allocated_INR]]="","",Table13[[#This Row],[Amount_INR]]-Table13[[#This Row],[Budget_Allocated_INR]]) -> 5435.37 | H61: 5435.37 | I61: 45157 | J61: Approved | K61: Credit Card | L61: FY2023-2024 | M61: Under review | N61: Expense
A62: EXP-00348 | B62: Finance | C62: Hardware | D62: Wipro | E62: 79555 | F62: 101962.75 | G62: =IF(Table13[[#This Row],[Budget_Allocated_INR]]="","",Table13[[#This Row],[Amount_INR]]-Table13[[#This Row],[Budget_Allocated_INR]]) -> -22407.75 | H62: -22407.75 | I62: 44958 | J62: Approved | K62: Bank Transfer | L62: FY2022-2023 | N62: Expense
A63: EXP-00372 | B63: Sales | C63: Utilities | D63: Zoom | E63: 411030 | F63: 392369.5 | G63: =IF(Table13[[#This Row],[Budget_Allocated_INR]]="","",Table13[[#This Row],[Amount_INR]]-Table13[[#This Row],[Budget_Allocated_INR]]) -> 18660.5 | H63: 18660.5 | I63: 44966 | J63: Approved | K63: Vendor Credit | L63: FY2022-2023 | N63: Expense
A64: EXP-00397 | B64: Finance | C64: Cloud Infrastructure | D64: HubSpot | E64: 2583687 | F64: 2695007.7 | G64: =IF(Table13[[#This Row],[Budget_Allocated_INR]]="","",Table13[[#This Row],[Amount_INR]]-Table13[[#This Row],[Budget_Allocated_INR]]) -> -111320.68 | H64: -111320.68 | I64: 45655 | J64: Pending | K64: Vendor Credit | L64: FY2024-2025 | N64: Expense | O64: Flag: High-Value Pending
A65: EXP-00806 | B65: Sales | C65: Travel | D65: Zoom | E65: 99203 | F65: 111995.57 | G65: =IF(Table13[[#This Row],[Budget_Allocated_INR]]="","",Table13[[#This Row],[Amount_INR]]-Table13[[#This Row],[Budget_Allocated_INR]]) -> -12792.57 | H65: -12792.57 | I65: 45616 | J65: Approved | K65: Bank Transfer | L65: FY2024-2025 | N65: Expense
A66: EXP-00660 | B66: Support | C66: Training | D66: Adobe | E66: 413818 | F66: 475823.4 | G66: =IF(Table13[[#This Row],[Budget_Allocated_INR]]="","",Table13[[#This Row],[Amount_INR]]-Table13[[#This Row],[Budget_Allocated_INR]]) -> -62005.4 | H66: -62005.4 | I66: 45461 | J66: Pending | K66: Credit Card | L66: FY2024-2025 | N66: Expense | O66: Flag: High-Value Pending
A67: EXP-00207 | B67: HR | C67: Utilities | D67: Internal | E67: 277583 | F67: 262488.11 | G67: =IF(Table13[[#This Row],[Budget_Allocated_INR]]="","",Table13[[#This Row],[Amount_INR]]-Table13[[#This Row],[Budget_Allocated_INR]]) -> 15094.89 | H67: 15094.89 | I67: 45270 | J67: Pending | K67: Credit Card | L67: FY2023-2024 | M67: Urgent | N67: Expense | O67: Flag: High-Value Pending
A68: EXP-00085 | B68: Sales | C68: Training | D68: Salesforce | E68: 457651 | F68: 467629.28 | G68: =IF(Table13[[#This Row],[Budget_Allocated_INR]]="","",Table13[[#This Row],[Amount_INR]]-Table13[[#This Row],[Budget_Allocated_INR]]) -> -9978.28 | H68: -9978.28 | I68: 45307 | J68: Approved | K68: Vendor Credit | L68: FY2023-2024 | M68: Urgent | N68: Expense
A69: EXP-00209 | B69: Support | C69: Salaries | D69: Google Cloud | E69: 62205 | F69: 68491.3 | G69: =IF(Table13[[#This Row],[Budget_Allocated_INR]]="","",Table13[[#This Row],[Amount_INR]]-Table13[[#This Row],[Budget_Allocated_INR]]) -> -6286.3 | I69: 45306 | J69: Approved | K69: Petty Cash | L69: FY2023-2024 | M69: Recurring | N69: Expense
A70: EXP-00089 | B70: Support | C70: Utilities | D70: HubSpot | E70: 395114 | F70: 453184.31 | G70: =IF(Table13[[#This Row],[Budget_Allocated_INR]]="","",Table13[[#This Row],[Amount_INR]]-Table13[[#This Row],[Budget_Allocated_INR]]) -> -58070.31 | H70: -58070.31 | I70: 44998 | J70: Pending | K70: Petty Cash | L70: FY2022-2023 | M70: Urgent | N70: Expense | O70: Flag: High-Value Pending
A71: EXP-00889 | B71: Sales | C71: Office Supplies | D71: Microsoft Azure | E71: 97690 | F71: 91260.03 | G71: =IF(Table13[[#This Row],[Budget_Allocated_INR]]="","",Table13[[#This Row],[Amount_INR]]-Table13[[#This Row],[Budget_Allocated_INR]]) -> 6429.97 | H71: 6429.97 | I71: 45440 | J71: Approved | K71: Petty Cash | L71: FY2024-2025 | N71: Expense
A72: EXP-00899 | B72: Operations | C72: Recruitment | D72: Zoom | E72: 491563 | F72: 637066.96 | G72: =IF(Table13[[#This Row],[Budget_Allocated_INR]]="","",Table13[[#This Row],[Amount_INR]]-Table13[[#This Row],[Budget_Allocated_INR]]) -> -145503.96 | H72: -145503.96 | I72: 44937 | J72: Approved | K72: Vendor Credit | L72: FY2022-2023 | M72: Recurring | N72: Expense
A73: EXP-00470 | B73: Support | C73: Maintenance | D73: Oracle | E73: 417255 | F73: 398887.4 | G73: =IF(Table13[[#This Row],[Budget_Allocated_INR]]="","",Table13[[#This Row],[Amount_INR]]-Table13[[#This Row],[Budget_Allocated_INR]]) -> 18367.6 | H73: 18367.6 | I73: 45228 | J73: Approved | K73: Vendor Credit | L73: FY2023-2024 | M73: Duplicate entry | N73: Expense
A74: EXP-00720 | B74: Engineering | C74: Utilities | D74: HubSpot | E74: 388564 | F74: 433099.82 | G74: =IF(Table13[[#This Row],[Budget_Allocated_INR]]="","",Table13[[#This Row],[Amount_INR]]-Table13[[#This Row],[Budget_Allocated_INR]]) -> -44535.82 | H74: -44535.82 | I74: 45302 | J74: Approved | K74: Credit Card | L74: FY2023-2024 | M74: Urgent | N74: Expense
A75: EXP-00033 | B75: Sales | C75: Uncategorized | D75: Salesforce | E75: 476675 | F75: 601228.87 | G75: =IF(Table13[[#This Row],[Budget_Allocated_INR]]="","",Table13[[#This Row],[Amount_INR]]-Table13[[#This Row],[Budget_Allocated_INR]]) -> -124553.87 | H75: -124553.87 | I75: 45426 | J75: Approved | K75: Vendor Credit | L75: FY2024-2025 | M75: Duplicate entry | N75: Expense
A76: EXP-00636 | B76: Sales | C76: Software Licenses | D76: HubSpot | E76: 118973 | F76: 134000.41 | G76: =IF(Table13[[#This Row],[Budget_Allocated_INR]]="","",Table13[[#This Row],[Amount_INR]]-Table13[[#This Row],[Budget_Allocated_INR]]) -> -15027.41 | H76: -15027.41 | I76: 45671 | J76: Approved | K76: Vendor Credit | L76: FY2024-2025 | N76: Expense
A77: EXP-00382 | B77: Support | C77: Maintenance | D77: SAP | E77: 22538 | F77: 19899.53 | G77: =IF(Table13[[#This Row],[Budget_Allocated_INR]]="","",Table13[[#This Row],[Amount_INR]]-Table13[[#This Row],[Budget_Allocated_INR]]) -> 2638.47 | H77: 2638.47 | I77: 45425 | J77: Approved | K77: Vendor Credit | L77: FY2024-2025 | N77: Expense
A78: EXP-00550 | B78: Finance | C78: Office Supplies | D78: Zoom | E78: 443662 | G78: =IF(Table13[[#This Row],[Budget_Allocated_INR]]="","",Table13[[#This Row],[Amount_INR]]-Table13[[#This Row],[Budget_Allocated_INR]]) | H78: 85569.69 | I78: 45673 | J78: Pending | K78: Vendor Credit | L78: FY2024-2025 | M78: One-time | N78: Expense | O78: Flag: High-Value Pending
A79: EXP-00163 | B79: Support | C79: Travel | D79: Slack | E79: 353333 | F79: 458964.2 | G79: =IF(Table13[[#This Row],[Budget_Allocated_INR]]="","",Table13[[#This Row],[Amount_INR]]-Table13[[#This Row],[Budget_Allocated_INR]]) -> -105631.2 | H79: -105631.2 | I79: 45702 | J79: Approved | K79: Credit Card | L79: FY2024-2025 | M79: Urgent | N79: Expense
A80: EXP-00795 | B80: Marketing | C80: Recruitment | D80: Oracle | E80: 290249 | F80: 369613.63 | G80: =IF(Table13[[#This Row],[Budget_Allocated_INR]]="","",Table13[[#This Row],[Amount_INR]]-Table13[[#This Row],[Budget_Allocated_INR]]) -> -79364.63 | H80: -79364.63 | I80: 45299 | J80: Approved | K80: Petty Cash | L80: FY2023-2024 | M80: Under review | N80: Expense
A81: EXP-00727 | B81: Finance | C81: Travel | D81: HubSpot | E81: 309034 | F81: 273262.53 | G81: =IF(Table13[[#This Row],[Budget_Allocated_INR]]="","",Table13[[#This Row],[Amount_INR]]-Table13[[#This Row],[Budget_Allocated_INR]]) -> 35771.47 | H81: 35771.47 | I81: 45384 | J81: Pending | K81: Petty Cash | L81: FY2024-2025 | M81: Recurring | N81: Expense | O81: Flag: High-Value Pending
A82: EXP-00403 | B82: Engineering | C82: Travel | D82: Microsoft Azure | E82: 106902 | F82: 123641.31 | G82: =IF(Table13[[#This Row],[Budget_Allocated_INR]]="","",Table13[[#This Row],[Amount_INR]]-Table13[[#This Row],[Budget_Allocated_INR]]) -> -16739.31 | H82: -16739.31 | I82: 45022 | J82: Pending | K82: Credit Card | L82: FY2023-2024 | N82: Expense
A83: EXP-00569 | B83: Operations | C83: Travel | D83: Freshdesk | E83: 429973 | F83: 376365.53 | G83: =IF(Table13[[#This Row],[Budget_Allocated_INR]]="","",Table13[[#This Row],[Amount_INR]]-Table13[[#This Row],[Budget_Allocated_INR]]) -> 53607.47 | H83: 53607.47 | I83: 45230 | J83: Pending | K83: Vendor Credit | L83: FY2023-2024 | N83: Expense | O83: Flag: High-Value Pending
A84: EXP-00396 | B84: Operations | C84: Office Supplies | D84: AWS | E84: 206116 | F84: 229625.18 | G84: =IF(Table13[[#This Row],[Budget_Allocated_INR]]="","",Table13[[#This Row],[Amount_INR]]-Table13[[#This Row],[Budget_Allocated_INR]]) -> -23509.18 | H84: -23509.18 | I84: 45699 | J84: Pending | K84: Vendor Credit | L84: FY2024-2025 | N84: Expense | O84: Flag: High-Value Pending
A85: EXP-00865 | B85: Unspecified | C85: Travel | D85: Microsoft Azure | E85: 1422304 | F85: 1675743.1 | G85: =IF(Table13[[#This Row],[Budget_Allocated_INR]]="","",Table13[[#This Row],[Amount_INR]]-Table13[[#This Row],[Budget_Allocated_INR]]) -> -253439.07 | H85: -253439.07 | I85: 45310 | J85: Approved | K85: Bank Transfer | L85: FY2023-2024 | M85: Recurring | N85: Expense
A86: EXP-00271 | B86: Operations | C86: Software Licenses | D86: Adobe | E86: 495376 | F86: 532148.51 | G86: =IF(Table13[[#This Row],[Budget_Allocated_INR]]="","",Table13[[#This Row],[Amount_INR]]-Table13[[#This Row],[Budget_Allocated_INR]]) -> -36772.51 | H86: -36772.51 | I86: 45728 | J86: Pending | K86: Petty Cash | L86: FY2024-2025 | M86: Recurring | N86: Expense | O86: Flag: High-Value Pending
A87: EXP-00272 | B87: HR | C87: Cloud Infrastructure | D87: Zoom | E87: 374421 | F87: 472252.91 | G87: =IF(Table13[[#This Row],[Budget_Allocated_INR]]="","",Table13[[#This Row],[Amount_INR]]-Table13[[#This Row],[Budget_Allocated_INR]]) -> -97831.91 | H87: -97831.91 | I87: 45125 | J87: Approved | K87: Credit Card | L87: FY2023-2024 | N87: Expense
A88: EXP-00583 | B88: HR | C88: Office Supplies | D88: Slack | E88: 277952 | F88: 236373.9 | G88: =IF(Table13[[#This Row],[Budget_Allocated_INR]]="","",Table13[[#This Row],[Amount_INR]]-Table13[[#This Row],[Budget_Allocated_INR]]) -> 41578.1 | H88: 41578.1 | I88: 45665 | J88: Rejected | K88: Credit Card | L88: FY2024-2025 | N88: Expense | O88: Flag: High-Value Pending
A89: EXP-00533 | B89: Finance | C89: Maintenance | D89: Salesforce | E89: 314597 | F89: 405247.51 | G89: =IF(Table13[[#This Row],[Budget_Allocated_INR]]="","",Table13[[#This Row],[Amount_INR]]-Table13[[#This Row],[Budget_Allocated_INR]]) -> -90650.51 | H89: -90650.51 | I89: 45576 | J89: Pending | K89: Bank Transfer | L89: FY2024-2025 | M89: Recurring | N89: Expense | O89: Flag: High-Value Pending
A90: EXP-00371 | B90: Support | C90: Software Licenses | D90: Internal | E90: 109346 | F90: 139986.84 | G90: =IF(Table13[[#This Row],[Budget_Allocated_INR]]="","",Table13[[#This Row],[Amount_INR]]-Table13[[#This Row],[Budget_Allocated_INR]]) -> -30640.84 | H90: -30640.84 | I90: 45178 | J90: Pending | K90: Credit Card | L90: FY2023-2024 | M90: Recurring | N90: Expense
A91: EXP-00835 | B91: Sales | C91: Office Supplies | D91: Freshdesk | E91: -57182 | F91: 60104.14 | G91: =IF(Table13[[#This Row],[Budget_Allocated_INR]]="","",Table13[[#This Row],[Amount_INR]]-Table13[[#This Row],[Budget_Allocated_INR]]) -> -117286.14 | I91: 45051 | J91: Approved | K91: Bank Transfer | L91: FY2023-2024 | N91: Credit/Refund
A92: EXP-00923 | B92: HR | C92: Office Supplies | D92: SAP | E92: 429501 | F92: 466352.17 | G92: =IF(Table13[[#This Row],[Budget_Allocated_INR]]="","",Table13[[#This Row],[Amount_INR]]-Table13[[#This Row],[Budget_Allocated_INR]]) -> -36851.17 | H92: -36851.17 | I92: 45638 | J92: Pending | K92: Credit Card | L92: FY2024-2025 | M92: Recurring | N92: Expense | O92: Flag: High-Value Pending
A93: EXP-00169 | B93: Sales | C93: Travel | D93: Salesforce | E93: 478753 | F93: 566440.71 | G93: =IF(Table13[[#This Row],[Budget_Allocated_INR]]="","",Table13[[#This Row],[Amount_INR]]-Table13[[#This Row],[Budget_Allocated_INR]]) -> -87687.71 | H93: -87687.71 | I93: 45164 | J93: Pending | K93: Bank Transfer | L93: FY2023-2024 | M93: Recurring | N93: Expense | O93: Flag: High-Value Pending
A94: EXP-00683 | B94: Sales | C94: Training | D94: Slack | E94: 62031 | F94: 62498.04 | G94: =IF(Table13[[#This Row],[Budget_Allocated_INR]]="","",Table13[[#This Row],[Amount_INR]]-Table13[[#This Row],[Budget_Allocated_INR]]) -> -467.04 | H94: -467.04 | I94: 45178 | J94: Rejected | K94: Bank Transfer | L94: FY2023-2024 | N94: Expense
A95: EXP-00506 | B95: Marketing | C95: Marketing Spend | D95: Slack | E95: 288581 | F95: 353638.16 | G95: =IF(Table13[[#This Row],[Budget_Allocated_INR]]="","",Table13[[#This Row],[Amount_INR]]-Table13[[#This Row],[Budget_Allocated_INR]]) -> -65057.16 | H95: -65057.16 | I95: 45602 | J95: Approved | K95: Bank Transfer | L95: FY2024-2025 | M95: Duplicate entry | N95: Expense
A96: EXP-00540 | B96: Marketing | C96: Utilities | D96: Oracle | E96: 123062 | F96: 152975.35 | G96: =IF(Table13[[#This Row],[Budget_Allocated_INR]]="","",Table13[[#This Row],[Amount_INR]]-Table13[[#This Row],[Budget_Allocated_INR]]) -> -29913.35 | H96: -29913.35 | I96: 45200 | J96: Pending | K96: Vendor Credit | L96: FY2023-2024 | M96: Duplicate entry | N96: Expense
A97: EXP-00532 | B97: Marketing | C97: Consulting Fees | D97: Google Cloud | E97: 481569 | F97: 451100.97 | G97: =IF(Table13[[#This Row],[Budget_Allocated_INR]]="","",Table13[[#This Row],[Amount_INR]]-Table13[[#This Row],[Budget_Allocated_INR]]) -> 30468.03 | H97: 30468.03 | I97: 45078 | J97: Approved | K97: Petty Cash | L97: FY2023-2024 | N97: Expense
A98: EXP-00898 | B98: Sales | C98: Consulting Fees | D98: Salesforce | E98: 163410 | F98: 200577.85 | G98: =IF(Table13[[#This Row],[Budget_Allocated_INR]]="","",Table13[[#This Row],[Amount_INR]]-Table13[[#This Row],[Budget_Allocated_INR]]) -> -37167.85 | I98: 45458 | J98: Approved | K98: Bank Transfer | L98: FY2024-2025 | M98: Urgent | N98: Expense
A99: EXP-00179 | B99: HR | C99: Travel | D99: TCS | E99: 377326 | F99: 461081.99 | G99: =IF(Table13[[#This Row],[Budget_Allocated_INR]]="","",Table13[[#This Row],[Amount_INR]]-Table13[[#This Row],[Budget_Allocated_INR]]) -> -83755.99 | H99: -83755.99 | I99: 45255 | J99: Approved | K99: Vendor Credit | L99: FY2023-2024 | N99: Expense
A100: EXP-00321 | B100: Operations | C100: Marketing Spend | D100: TCS | E100: 79297 | F100: 66599.44 | G100: =IF(Table13[[#This Row],[Budget_Allocated_INR]]="","",Table13[[#This Row],[Amount_INR]]-Table13[[#This Row],[Budget_Allocated_INR]]) -> 12697.56 | H100: 12697.56 | I100: 45023 | J100: Approved | K100: Petty Cash | L100: FY2023-2024 | M100: Under review | N100: Expense
...

Sheet Marketing_Campaigns
A1: Campaign_ID | B1: Campaign_Name | C1: Channel | D1: Campaign_Type | E1: Start_Date | F1: End_Date | G1: Budget_INR | H1: Impressions | I1: Clicks | J1: MQLs | K1: SQLs | L1: Conversions | M1: CTR_Percent | N1: Cost_Per_Click | O1: Customer_Acquisition_Cost | P1: Target_Region | Q1: Target_Industry
A2: CAMP-0116 | B2: Q2-2023 SecureNet Suite Retargeting | C2: Google Ads | D2: Retargeting | E2: 45027 | F2: 45089 | G2: 751318 | H2: 125501 | I2: 8720 | J2: 2000 | K2: 453 | L2: 158 | M2: 6.95 | N2: 86.16 | O2: 4755.18 | P2: North | Q2: Telecom
A3: CAMP-0035 | B3: Q2-2023 AnalyticsEdge Retargeting | C3: Social Media | D3: Lead Generation | E3: 45470 | F3: 45529 | G3: 931769 | H3: 404277 | I3: 28305 | J3: 3218 | K3: 614 | L3: 177 | M3: 7 | N3: 32.92 | O3: 5264.23 | P3: West | Q3: Manufacturing
A4: CAMP-0127 | B4: Q4-2023 AnalyticsEdge Product Launch | C4: SEO | D4: Brand Awareness | E4: 45082 | F4: 45135 | G4: 1330883 | H4: 169252 | I4: 9199 | J4: 1321 | K4: 320 | L4: 124 | M4: 5.44 | N4: 144.68 | O4: 10732.93 | P4: All Regions | Q4: EdTech
A5: CAMP-0115 | B5: Q4-2024 AI Insights Module Retargeting | C5: Webinar | D5: Brand Awareness | E5: 45529 | F5: 45604 | G5: 1055991 | H5: 167737 | I5: 2658 | J5: 164 | K5: 24 | L5: 6 | M5: 1.58 | N5: 397.29 | O5: 175998.5 | P5: Unspecified | Q5: Retail
A6: CAMP-0111 | B6: Q1-2024 SecureNet Suite Retargeting | C6: Webinar | D6: Lead Generation | E6: 45244 | F6: 45296 | G6: 576586 | H6: 352957 | I6: 18568 | J6: 3933 | K6: 1690 | L6: 470 | M6: 5.26 | N6: 31.05 | O6: 1226.78 | P6: All Regions | Q6: Telecom
A7: CAMP-0123 | B7: Q1-2024 CloudShift Platform Event Promotion | C7: LinkedIn | D7: Brand Awareness | E7: 45317 | F7: 45405 | G7: 99142 | H7: 23806 | I7: 697 | J7: 96 | K7: 16 | L7: 3 | M7: 2.93 | N7: 142.24 | O7: 33047.33 | P7: East | Q7: Telecom
A8: CAMP-0086 | B8: Q2-2023 AnalyticsEdge Product Launch | C8: SEO | D8: Brand Awareness | E8: 45203 | F8: 45278 | G8: 1296128 | H8: 325772 | I8: 9541 | J8: 1855 | K8: 438 | L8: 153 | M8: 2.93 | N8: 135.85 | O8: 8471.42 | P8: West | Q8: Retail
A9: CAMP-0039 | B9: Q3-2025 DevOps Accelerator Event Promotion | C9: Social Media | D9: Lead Generation | E9: 45661 | F9: 45746 | G9: 1268589 | H9: 152974 | I9: 10540 | J9: 2346 | K9: 955 | L9: 280 | M9: 6.89 | N9: 120.36 | O9: 4530.68 | P9: West | Q9: Banking
A10: CAMP-0016 | B10: Q3-2023 DevOps Accelerator Brand Awareness | C10: LinkedIn | D10: Retargeting | E10: 45483 | F10: 45535 | G10: 616140 | H10: 384535 | I10: 19957 | J10: 3229 | K10: 1357 | L10: 235 | M10: 5.19 | N10: 30.87 | O10: 2621.87 | P10: North | Q10: All Industries
A11: CAMP-0043 | B11: Q4-2025 AI Insights Module Brand Awareness | C11: Content Marketing | D11: Event Promotion | E11: 45215 | F11: 45241 | G11: 1208048 | H11: 11982 | I11: 195 | J11: 24 | K11: 8 | L11: 1 | M11: 1.63 | N11: 6195.12 | O11: 1208048 | P11: All Regions | Q11: Healthcare
A12: CAMP-0124 | B12: Q2-2025 SecureNet Suite Brand Awareness | C12: Social Media | D12: Event Promotion | E12: 45505 | F12: 45530 | G12: 1362761 | H12: 48086 | I12: 2575 | J12: 481 | K12: 145 | L12: 51 | M12: 5.35 | N12: 529.23 | O12: 26720.8 | P12: All Regions | Q12: Government
A13: CAMP-0053 | B13: Q2-2025 AI Insights Module Product Launch | C13: Google Ads | D13: Lead Generation | E13: 45352 | F13: 45375 | G13: 487709 | H13: 284841 | I13: 10450 | J13: 1086 | K13: 426 | L13: 97 | M13: 3.67 | N13: 46.67 | O13: 5027.93 | P13: West | Q13: All Industries
... A26: CAMP-0099 | B26: Q2-2025 DevOps Accelerator Brand Awareness | C26: Content Marketing | D26: Lead Generation | E26: 45503 | F26: 45518 | G26: 909983 | H26: 246287 | I26: 13286 | J26: 2769 | K26: 1258 | L26: 134 | M26: 5.39 | N26: 68.49 | O26: 6790.92 | P26: All Regions | Q26: Media
A27: CAMP-0077 | B27: Q4-2024 DataVault Pro Brand Awareness | C27: Google Ads | D27: Brand Awareness | E27: 45130 | F27: 45145 | G27: 639700 | H27: 91607 | I27: =ROUND(Table14[[#This Row],[Impressions]]*(Table14[[#This Row],[CTR_Percent]]/100),0) -> 6110 | J27: 562 | K27: 244 | L27: 75 | M27: 6.67 | N27: 104.65 | O27: 8529.33 | P27: All Regions | Q27: Manufacturing
A28: CAMP-0054 | B28: Q1-2024 AnalyticsEdge Lead Generation | C28: LinkedIn | D28: Event Promotion | E28: 45655 | F28: 45672 | G28: 118248 | H28: 168771 | I28: 5692 | J28: 378 | K28: 98 | L28: 16 | M28: 3.37 | N28: 20.77 | O28: 7390.5 | P28: North | Q28: Government
A29: CAMP-0112 | B29: Q2-2025 SecureNet Suite Brand Awareness | C29: Content Marketing | D29: Lead Generation | E29: 45515 | F29: 45547 | G29: 1084235 | H29: 244228 | I29: 18533 | J29: 1202 | K29: 329 | L29: 117 | M29: 7.59 | N29: 58.5 | O29: 9266.97 | P29: South | Q29: Logistics
A30: CAMP-0032 | B30: Q2-2025 AnalyticsEdge Product Launch | C30: LinkedIn | D30: Product Launch | E30: 45233 | F30: 45314 | G30: 1256395 | H30: 170300 | I30: 1941 | J30: 98 | K30: 37 | L30: 7 | M30: 1.14 | N30: 647.29 | O30: 179485 | P30: All Regions | Q30: Logistics
A31: CAMP-0042 | B31: Q4-2025 CloudShift Platform Retargeting | C31: Email | D31: Brand Awareness | E31: 44981 | F31: 45056 | G31: 1454862 | H31: 34159 | I31: 392 | J31: 24 | K31: 5 | L31: 1 | M31: 1.15 | N31: 3711.38 | O31: 1454862 | P31: East | Q31: Unspecified
A32: CAMP-0080 | B32: Q3-2024 AnalyticsEdge Lead Generation | C32: Social Media | D32: Product Launch | E32: 45028 | F32: 45109 | G32: 880836 | H32: 82670 | I32: 1430 | J32: 232 | K32: 88 | L32: 31 | M32: 1.73 | N32: 615.97 | O32: 28414.06 | P32: West | Q32: Logistics
A33: CAMP-0084 | B33: Q1-2024 AI Insights Module Retargeting | C33: SEO | D33: Product Launch | E33: 44984 | F33: 45038 | G33: 1392111 | H33: 327634 | I33: 23553 | J33: 3422 | K33: 1332 | L33: 222 | M33: 7.19 | N33: 59.11 | O33: 6270.77 | P33: North | Q33: Unspecified
A34: CAMP-0089 | B34: Q1-2024 AI Insights Module Lead Generation | C34: LinkedIn | D34: Product Launch | E34: 45193 | F34: 45220 | G34: 527447 | H34: 280933 | I34: 6027 | J34: 1165 | K34: 553 | L34: 147 | M34: 2.15 | N34: 87.51 | O34: 3588.07 | P34: All Regions | Q34: Manufacturing
A35: CAMP-0146 | B35: Q1-2025 SecureNet Suite Lead Generation | C35: LinkedIn | D35: Product Launch | E35: 45324 | F35: 45387 | G35: 222732 | H35: 463669 | I35: 27503 | J35: 5863 | K35: 953 | L35: 228 | M35: 5.93 | N35: 8.1 | O35: 976.89 | P35: South | Q35: Unspecified
A36: CAMP-0092 | B36: Q1-2024 DevOps Accelerator Lead Generation | C36: LinkedIn | D36: Lead Generation | E36: 44975 | F36: 45065 | G36: 273094 | H36: 235281 | I36: 8812 | J36: 1911 | K36: 683 | L36: 134 | M36: 3.75 | N36: 30.99 | O36: 2038.01 | P36: East | Q36: Unspecified
A37: CAMP-0034 | B37: Q4-2023 DevOps Accelerator Event Promotion | C37: Social Media | D37: Product Launch | E37: 45379 | F37: 45448 | G37: 1009931 | H37: 236770 | I37: 9413 | J37: 2259 | K37: 934 | L37: 287 | M37: 3.98 | N37: 107.29 | O37: 3518.92 | P37: North | Q37: Government
A38: CAMP-0059 | B38: Q4-2025 SecureNet Suite Event Promotion | C38: Social Media | D38: Lead Generation | E38: 45227 | F38: 45259 | G38: 584326 | H38: 42908 | I38: 1663 | J38: 270 | K38: 88 | L38: 16 | M38: 3.88 | N38: 351.37 | O38: 36520.38 | P38: North | Q38: Logistics
A39: CAMP-0003 | B39: Q4-2023 SecureNet Suite Product Launch | C39: LinkedIn | D39: Lead Generation | E39: 45634 | F39: 45675 | G39: 1047835 | H39: 496775 | I39: 27684 | J39: 6540 | K39: 2450 | L39: 458 | M39: 5.57 | N39: 37.85 | O39: 2287.85 | P39: West | Q39: Manufacturing
A40: CAMP-0026 | B40: Q1-2024 CloudShift Platform Product Launch | C40: Google Ads | D40: Retargeting | E40: 45572 | F40: 45647 | G40: 90065 | H40: 309321 | I40: =ROUND(Table14[[#This Row],[Impressions]]*(Table14[[#This Row],[CTR_Percent]]/100),0) -> 4640 | J40: 470 | K40: 199 | L40: 76 | M40: 1.5 | N40: 19.35 | O40: 1185.07 | P40: East | Q40: Unspecified
A41: CAMP-0147 | B41: Q1-2024 AI Insights Module Brand Awareness | C41: Trade Show | D41: Brand Awareness | E41: 45173 | F41: 45213 | G41: 810049 | H41: 24326 | I41: 433 | J41: 56 | K41: 12 | L41: 1 | M41: 1.78 | N41: 1870.78 | O41: 810049 | P41: Unspecified | Q41: Government
A42: CAMP-0014 | B42: Q1-2023 DataVault Pro Brand Awareness | C42: Email | D42: Brand Awareness | E42: 45160 | F42: 45195 | G42: 120003 | H42: 302403 | I42: =ROUND(Table14[[#This Row],[Impressions]]*(Table14[[#This Row],[CTR_Percent]]/100),0) -> 13275 | J42: 1325 | K42: 547 | L42: 200 | M42: 4.39 | N42: 9.04 | O42: 600.01 | P42: West | Q42: Government
A43: CAMP-0067 | B43: Q3-2023 DevOps Accelerator Retargeting | C43: Social Media | D43: Brand Awareness | E43: 45592 | F43: 45677 | G43: 1094418 | H43: 487816 | I43: 8187 | J43: 1785 | K43: 839 | L43: 243 | M43: 1.68 | N43: 133.68 | O43: 4503.78 | P43: East | Q43: Banking
A44: CAMP-0107 | B44: Q4-2025 AI Insights Module Retargeting | C44: LinkedIn | D44: Product Launch | E44: 45585 | F44: 45641 | G44: 519512 | H44: 111222 | I44: 8595 | J44: 551 | K44: 207 | L44: 56 | M44: 7.73 | N44: 60.44 | O44: 9277 | P44: South | Q44: All Industries
A45: CAMP-0109 | B45: Q4-2023 CloudShift Platform Product Launch | C45: LinkedIn | D45: Brand Awareness | E45: 45260 | F45: 45303 | G45: 1125285 | H45: 480535 | I45: 26731 | J45: 6012 | K45: 2554 | L45: 403 | M45: 5.56 | N45: 42.1 | O45: 2792.27 | P45: All Regions | Q45: EdTech
A46: CAMP-0108 | B46: Q4-2025 CloudShift Platform Retargeting | C46: SEO | D46: Product Launch | E46: 45572 | F46: 45592 | G46: 348839 | H46: 69013 | I46: 4567 | J46: 960 | K46: 408 | L46: 61 | M46: 6.62 | N46: 76.38 | O46: 5718.67 | P46: All Regions | Q46: All Industries
A47: CAMP-0145 | B47: Q3-2023 CloudShift Platform Lead Generation | C47: Google Ads | D47: Lead Generation | E47: 45397 | F47: 45434 | G47: 729171 | H47: 43782 | I47: 1128 | J47: 252 | K47: 52 | L47: 8 | M47: 2.58 | N47: 646.43 | O47: 91146.38 | P47: North | Q47: All Industries
A48: CAMP-0070 | B48: Q3-2024 CloudShift Platform Brand Awareness | C48: Google Ads | D48: Lead Generation | E48: 45255 | F48: 45275 | G48: 298026 | H48: 479249 | I48: =ROUND(Table14[[#This Row],[Impressions]]*(Table14[[#This Row],[CTR_Percent]]/100),0) -> 25688 | J48: 6052 | K48: 1602 | L48: 396 | M48: 5.36 | N48: 11.6 | O48: 752.59 | P48: East | Q48: Media
A49: CAMP-0017 | B49: Q1-2023 DataVault Pro Retargeting | C49: Google Ads | D49: Product Launch | E49: 45515 | F49: 45563 | G49: 879818 | H49: 98631 | I49: 3100 | J49: 382 | K49: 98 | L49: 22 | M49: 3.14 | N49: 283.81 | O49: 39991.73 | P49: West | Q49: Unspecified
A50: CAMP-0074 | B50: Q4-2023 DevOps Accelerator Retargeting | C50: Webinar | D50: Lead Generation | E50: 45507 | F50: 45540 | G50: 1464288 | H50: 203793 | I50: 4579 | J50: 415 | K50: 69 | L50: 27 | M50: 2.25 | N50: 319.78 | O50: 54232.89 | P50: East | Q50: Logistics
A51: CAMP-0131 | B51: Q1-2025 DataVault Pro Event Promotion | C51: Trade Show | D51: Retargeting | E51: 45516 | F51: 45585 | G51: 733453 | H51: 239205 | I51: 5167 | J51: 265 | K51: 58 | L51: 9 | M51: 2.16 | N51: 141.95 | O51: 81494.78 | P51: Unspecified | Q51: Telecom
A52: CAMP-0126 | B52: Q3-2025 DataVault Pro Product Launch | C52: Google Ads | D52: Product Launch | E52: 45565 | F52: 45640 | G52: 1066127 | H52: 383129 | I52: 22179 | J52: 5433 | K52: 1427 | L52: 349 | M52: 5.79 | N52: 48.07 | O52: 3054.81 | P52: East | Q52: Banking
A53: CAMP-0135 | B53: Q1-2025 SecureNet Suite Brand Awareness | C53: Email | D53: Event Promotion | E53: 45524 | F53: 45608 | G53: 207823 | H53: 428431 | I53: 9557 | J53: 764 | K53: 323 | L53: 53 | M53: 2.23 | N53: 21.75 | O53: 3921.19 | P53: All Regions | Q53: EdTech
A54: CAMP-0020 | B54: Q4-2023 DataVault Pro Lead Generation | C54: LinkedIn | D54: Event Promotion | E54: 44997 | F54: 45066 | G54: 245661 | H54: 64710 | I54: 5127 | J54: 861 | K54: 230 | L54: 38 | M54: 7.92 | N54: 47.92 | O54: 6464.76 | P54: All Regions | Q54: Manufacturing
A55: CAMP-0023 | B55: Q4-2024 DevOps Accelerator Lead Generation | C55: Email | D55: Lead Generation | E55: 45388 | F55: 45422 | G55: 121735 | H55: 335791 | I55: 11480 | J55: 1833 | K55: 699 | L55: 196 | M55: 3.42 | N55: 10.6 | O55: 621.1 | P55: South | Q55: Unspecified
A56: CAMP-0106 | B56: Q1-2025 DevOps Accelerator Event Promotion | C56: Webinar | D56: Event Promotion | E56: 45298 | F56: 45369 | G56: 1242650 | H56: 90536 | I56: 4247 | J56: 551 | K56: 110 | L56: 30 | M56: 4.69 | N56: 292.59 | O56: 41421.67 | P56: North | Q56: EdTech
A57: CAMP-0068 | B57: Q3-2023 AI Insights Module Event Promotion | C57: Webinar | D57: Lead Generation | E57: 45701 | F57: 45715 | G57: 630183 | H57: 235755 | I57: 3380 | J57: 643 | K57: 166 | L57: 48 | M57: 1.43 | N57: 186.44 | O57: 13128.81 | P57: Unspecified | Q57: Media
A58: CAMP-0071 | B58: Q2-2025 DataVault Pro Event Promotion | C58: Trade Show | D58: Lead Generation | E58: 45382 | F58: 45416 | G58: 772415 | H58: 175011 | I58: 4490 | J58: 236 | K58: 92 | L58: 35 | M58: 2.57 | N58: 172.03 | O58: 22069 | P58: East | Q58: EdTech
A59: CAMP-0065 | B59: Q4-2025 DataVault Pro Retargeting | C59: Google Ads | D59: Brand Awareness | E59: 45307 | F59: 45364 | G59: 1348252 | H59: 194414 | I59: 13988 | J59: 2441 | K59: 637 | L59: 138 | M59: 7.19 | N59: 96.39 | O59: 9769.94 | P59: West | Q59: Logistics
A60: CAMP-0058 | B60: Q1-2024 SecureNet Suite Brand Awareness | C60: Content Marketing | D60: Brand Awareness | E60: 45693 | F60: 45758 | G60: 1085332 | H60: 424698 | I60: 22951 | J60: 3580 | K60: 612 | L60: 124 | M60: 5.4 | N60: 47.29 | O60: 8752.68 | P60: North | Q60: Healthcare
... A78: CAMP-0149 | B78: Q4-2024 SecureNet Suite Brand Awareness | C78: Webinar | D78: Event Promotion | E78: 44978 | F78: 45020 | G78: 855078 | H78: 128028 | I78: 7208 | J78: 1106 | K78: 534 | L78: 130 | M78: 5.63 | N78: 118.63 | O78: 6577.52 | P78: South | Q78: Healthcare
A79: CAMP-0101 | B79: Q1-2024 DevOps Accelerator Product Launch | C79: Webinar | D79: Product Launch | E79: 45621 | F79: 45679 | G79: 844621 | H79: 193646 | I79: =ROUND(Table14[[#This Row],[Impressions]]*(Table14[[#This Row],[CTR_Percent]]/100),0) -> 14969 | J79: 2695 | K79: 1341 | L79: 223 | M79: 7.73 | N79: 56.44 | O79: 3787.54 | P79: South | Q79: Telecom
A80: CAMP-0095 | B80: Q2-2024 AnalyticsEdge Product Launch | C80: Webinar | D80: Product Launch | E80: 45516 | F80: 45569 | G80: 1458178 | H80: 227001 | I80: 7647 | J80: 1785 | K80: 688 | L80: 257 | M80: 3.37 | N80: 190.69 | O80: 5673.84 | P80: North | Q80: Manufacturing
A81: CAMP-0012 | B81: Q1-2025 SecureNet Suite Product Launch | C81: Social Media | D81: Retargeting | E81: 45549 | F81: 45591 | G81: 879174 | H81: 164865 | I81: 9397 | J81: 812 | K81: 181 | L81: 49 | M81: 5.7 | N81: 93.56 | O81: 17942.33 | P81: West | Q81: Media
A82: CAMP-0038 | B82: Q4-2023 DataVault Pro Product Launch | C82: Content Marketing | D82: Brand Awareness | E82: 44930 | F82: 44986 | G82: 105332 | H82: 306376 | I82: 22333 | J82: 5368 | K82: 2271 | L82: 694 | M82: 7.29 | N82: 4.72 | O82: 151.78 | P82: South | Q82: Insurance
A83: CAMP-0049 | B83: Q3-2024 DataVault Pro Lead Generation | C83: Google Ads | D83: Brand Awareness | E83: 44945 | F83: 44995 | G83: 92336 | H83: 148345 | I83: 2288 | J83: 524 | K83: 162 | L83: 21 | M83: 1.54 | N83: 40.36 | O83: 4396.95 | P83: North | Q83: Telecom
A84: CAMP-0093 | B84: Q2-2025 AI Insights Module Retargeting | C84: Content Marketing | D84: Brand Awareness | E84: 44931 | F84: 44985 | G84: 429370 | H84: 440621 | I84: 26431 | J84: 3118 | K84: 1204 | L84: 326 | M84: 6 | N84: 16.24 | O84: 1317.09 | P84: West | Q84: Manufacturing
A85: CAMP-0140 | B85: Q1-2023 CloudShift Platform Retargeting | C85: LinkedIn | D85: Product Launch | E85: 45537 | F85: 45573 | G85: 478526 | H85: 379093 | I85: 14412 | J85: 1425 | K85: 699 | L85: 177 | M85: 3.8 | N85: 33.2 | O85: 2703.54 | P85: All Regions | Q85: Media
A86: CAMP-0139 | B86: Q4-2023 SecureNet Suite Lead Generation | C86: SEO | D86: Event Promotion | E86: 45234 | F86: 45257 | G86: 343960 | H86: 122332 | I86: 3955 | J86: 630 | K86: 214 | L86: 58 | M86: 3.23 | N86: 86.97 | O86: 5930.34 | P86: North | Q86: Media
A87: CAMP-0110 | B87: Q2-2025 DevOps Accelerator Retargeting | C87: Email | D87: Retargeting | E87: 45220 | F87: 45283 | G87: 442809 | H87: 103840 | I87: 3911 | J87: 598 | K87: 217 | L87: 42 | M87: 3.77 | N87: 113.22 | O87: 10543.07 | P87: North | Q87: EdTech
A88: CAMP-0050 | B88: Q3-2024 DevOps Accelerator Lead Generation | C88: Content Marketing | D88: Event Promotion | E88: 45332 | F88: 45374 | G88: 799951 | H88: 176645 | I88: 2136 | J88: 355 | K88: 99 | L88: 36 | M88: 1.21 | N88: 374.51 | O88: 22220.86 | P88: Unspecified | Q88: Healthcare
A89: CAMP-0030 | B89: Q2-2023 AI Insights Module Brand Awareness | C89: LinkedIn | D89: Event Promotion | E89: 45396 | F89: 45461 | G89: 1039457 | H89: 40361 | I89: 861 | J89: 95 | K89: 26 | L89: 5 | M89: 2.13 | N89: 1207.27 | O89: 207891.4 | P89: East | Q89: Telecom
A90: CAMP-0004 | B90: Q1-2025 AnalyticsEdge Event Promotion | C90: SEO | D90: Event Promotion | E90: 45627 | F90: 45682 | G90: 999735 | H90: 402005 | I90: 14593 | J90: 1055 | K90: 453 | L90: 116 | M90: 3.63 | N90: 68.51 | O90: 8618.41 | P90: North | Q90: All Industries
A91: CAMP-0011 | B91: Q4-2025 DataVault Pro Retargeting | C91: Content Marketing | D91: Lead Generation | E91: 45305 | F91: 45384 | G91: 1004925 | H91: 44343 | I91: 2360 | J91: 408 | K91: 81 | L91: 9 | M91: 5.32 | N91: 425.82 | O91: 111658.33 | P91: East | Q91: Retail
... A95: CAMP-0120 | B95: Q4-2023 AnalyticsEdge Product Launch | C95: Email | D95: Brand Awareness | E95: 44939 | F95: 44957 | G95: 1245125 | H95: 383832 | I95: 15667 | J95: 3601 | K95: 864 | L95: 297 | M95: 4.08 | N95: 79.47 | O95: 4192.34 | P95: All Regions | Q95: Banking
A96: CAMP-0144 | B96: Q4-2024 DevOps Accelerator Event Promotion | C96: LinkedIn | D96: Lead Generation | E96: 45472 | F96: 45526 | G96: 1331429 | H96: 435674 | I96: =ROUND(Table14[[#This Row],[Impressions]]*(Table14[[#This Row],[CTR_Percent]]/100),0) -> 9454 | J96: 1254 | K96: 198 | L96: 35 | M96: 2.17 | N96: 141.01 | O96: 38040.83 | P96: West | Q96: Insurance
A97: CAMP-0022 | B97: Q3-2024 AI Insights Module Product Launch | C97: Email | D97: Product Launch | E97: 45368 | F97: 45453 | G97: 616265 | H97: 498467 | I97: 21669 | J97: 1722 | K97: 788 | L97: 296 | M97: 4.35 | N97: 28.44 | O97: 2081.98 | P97: North | Q97: EdTech
A98: CAMP-0064 | B98: Q1-2023 DataVault Pro Brand Awareness | C98: Trade Show | D98: Retargeting | E98: 45059 | F98: 45080 | G98: 1165930 | H98: 123339 | I98: 4815 | J98: 956 | K98: 431 | L98: 112 | M98: 3.9 | N98: 242.15 | O98: 10410.09 | P98: South | Q98: Unspecified
A99: CAMP-0143 | B99: Q2-2023 CloudShift Platform Brand Awareness | C99: SEO | D99: Product Launch | E99: 45560 | F99: 45630 | G99: 698375 | H99: 213239 | I99: 2242 | J99: 137 | K99: 53 | L99: 6 | M99: 1.05 | N99: 311.5 | O99: 116395.83 | P99: North | Q99: Healthcare
A100: CAMP-0098 | B100: Q2-2025 AI Insights Module Product Launch | C100: Trade Show | D100: Retargeting | E100: 45464 | F100: 45532 | G100: 1096240 | H100: 373451 | I100: 20558 | J100: 2188 | K100: 869 | L100: 163 | M100: 5.5 | N100: 53.32 | O100: 6725.4 | P100: West | Q100: Retail
A101: CAMP-0128 | B101: Q1-2023 CloudShift Platform Brand Awareness | C101: SEO | D101: Brand Awareness | E101: 45144 | F101: 45191 | G101: 1356029 | H101: 447812 | I101: 8675 | J101: 685 | K101: 323 | L101: 79 | M101: 1.94 | N101: 156.31 | O101: 17164.92 | P101: West | Q101: EdTech
A102: CAMP-0118 | B102: Q3-2023 CloudShift Platform Retargeting | C102: Social Media | D102: Retargeting | E102: 45550 | F102: 45619 | G102: 1465017 | H102: 116289 | I102: 2008 | J102: 331 | K102: 82 | L102: 19 | M102: 1.73 | N102: 729.59 | O102: 77106.16 | P102: All Regions | Q102: Logistics
A103: CAMP-0096 | B103: Q4-2023 DataVault Pro Event Promotion | C103: Trade Show | D103: Event Promotion | E103: 45287 | F103: 45325 | G103: 1202247 | H103: 291796 | I103: 17648 | J103: 2094 | K103: 753 | L103: 278 | M103: 6.05 | N103: 68.12 | O103: 4324.63 | P103: West | Q103: Government
A104: CAMP-0069 | B104: Q2-2024 SecureNet Suite Event Promotion | C104: Google Ads | D104: Product Launch | E104: 45216 | F104: 45289 | G104: 1330523 | H104: 36706 | I104: 1999 | J104: 478 | K104: 196 | L104: 67 | M104: 5.45 | N104: 665.59 | O104: 19858.55 | P104: North | Q104: Banking
A105: CAMP-0045 | B105: Q4-2024 AI Insights Module Retargeting | C105: Content Marketing | D105: Brand Awareness | E105: 45149 | F105: 45236 | G105: 658344 | H105: 443634 | I105: 10302 | J105: 1907 | K105: 767 | L105: 158 | M105: 2.32 | N105: 63.9 | O105: 4166.73 | P105: East | Q105: Media
A106: CAMP-0056 | B106: Q3-2024 SecureNet Suite Lead Generation | C106: SEO | D106: Event Promotion | E106: 45196 | F106: 45274 | G106: 920383 | H106: 406818 | I106: 7190 | J106: 1407 | K106: 453 | L106: 161 | M106: 1.77 | N106: 128.01 | O106: 5716.66 | P106: North | Q106: Retail
A107: CAMP-0132 | B107: Q3-2025 DataVault Pro Event Promotion | C107: Content Marketing | D107: Lead Generation | E107: 45414 | F107: 45497 | G107: 383942 | H107: 282310 | I107: 10313 | J107: 1269 | K107: 344 | L107: 79 | M107: 3.65 | N107: 37.23 | O107: 4860.03 | P107: South | Q107: Unspecified
A108: CAMP-0078 | B108: Q2-2024 CloudShift Platform Product Launch | C108: Google Ads | D108: Lead Generation | E108: 45244 | F108: 45289 | G108: 1195610 | H108: 490723 | I108: 19867 | J108: 2501 | K108: 826 | L108: 198 | M108: 4.05 | N108: 60.18 | O108: 6038.43 | P108: West | Q108: Unspecified
... A151: CAMP-0129 | B151: Q3-2025 SecureNet Suite Product Launch | C151: Webinar | D151: Product Launch | E151: 45189 | F151: 45271 | G151: 431336 | H151: 57921 | I151: 1556 | J151: 274 | K151: 52 | L151: 10 | M151: 2.69 | N151: 277.21 | O151: 43133.6 | P151: East | Q151: Government

Sheet Sales_Deals
A1: Deal_ID | B1: Sales_Rep | C1: Client_ID | D1: Product | E1: Lead_Source | F1: Deal_Stage | G1: Deal_Value_INR | H1: Created_Date | I1: Close_Date | J1: Days_to_Close | K1: Discount_Percent | L1: Region | M1: Quarter | N1: Outlier_Flag
A2: DEAL-01440 | B2: Rohit Mehta | C2: CLI-0014 | D2: SecureNet Suite | E2: Referral | F2: Closed Lost | G2: 160271 | H2: 45263 | I2: 45406 | J2: 143 | K2: 3.7 | L2: West | M2: Q4-2023 | N2: Normal
A3: DEAL-02021 | B3: Amit Pillai | C3: CLI-0208 | D3: AI Insights Module | E3: Organic Search | F3: Prospecting | G3: 491510 | H3: 45030 | L3: South | M3: Q2-2023 | N3: Normal
A4: DEAL-00174 | B4: Amit Pillai | C4: CLI-0084 | D4: AI Insights Module | E4: Referral | F4: Proposal Sent | G4: 224184 | H4: 44956 | L4: West | M4: Q1-2023 | N4: Normal
A5: DEAL-02399 | B5: Vikram Patel | C5: CLI-0096 | D5: AnalyticsEdge | E5: Organic Search | F5: Closed Won | G5: 265745 | H5: 45590 | I5: 45650 | J5: 60 | K5: 17.8 | L5: South | M5: Q4-2024 | N5: Normal
A6: DEAL-00243 | B6: Siddharth Joshi | C6: CLI-0071 | D6: DataVault Pro | E6: Email Campaign | F6: Closed Won | G6: 255053 | H6: 45266 | I6: 45429 | J6: 163 | K6: 8.4 | L6: East | M6: Q4-2023 | N6: Normal
A7: DEAL-02410 | B7: Unassigned | C7: CLI-0238 | D7: DataVault Pro | E7: Organic Search | F7: Qualification | G7: 389913 | H7: 45276 | L7: South | M7: Q4-2023 | N7: Normal
A8: DEAL-02158 | B8: Amit Pillai | C8: CLI-0081 | D8: AI Insights Module | E8: Email Campaign | F8: Closed Won | G8: 393048 | H8: 45613 | I8: 45784 | J8: 171 | K8: 1.1 | L8: West | M8: Q4-2024 | N8: Normal
A9: DEAL-01161 | B9: Aditya Pillai | C9: CLI-0236 | D9: AI Insights Module | E9: Google Ads | F9: Closed Won | G9: 295502 | H9: 45696 | I9: 45821 | J9: 125 | K9: 15.8 | L9: East | M9: Q1-2025 | N9: Normal
A10: DEAL-00586 | B10: Meera Reddy | C10: CLI-0128 | D10: CloudShift Platform | E10: Organic Search | F10: Proposal Sent | G10: 172519 | H10: 45371 | K10: 14.2 | L10: South | M10: Q1-2024 | N10: Normal
A11: DEAL-00863 | B11: Aditya Pillai | C11: CLI-0147 | D11: DataVault Pro | E11: LinkedIn Campaign | F11: Closed Won | G11: 146890 | H11: 45356 | I11: 45414 | J11: 58 | K11: 8.5 | L11: West | M11: Q1-2024 | N11: Normal
A12: DEAL-01273 | B12: Ananya Sharma | C12: CLI-0237 | D12: AnalyticsEdge | E12: Webinar | F12: Closed Won | G12: 242460 | H12: 45346 | I12: 45463 | J12: 117 | K12: 23 | L12: East | M12: Q1-2024 | N12: Normal
A13: DEAL-01938 | B13: Siddharth Gupta | C13: CLI-0261 | D13: DataVault Pro | E13: LinkedIn Campaign | F13: Closed Won | G13: 396833 | H13: 45219 | I13: 45236 | J13: 17 | K13: 4.3 | L13: South | M13: Q4-2023 | N13: Normal
A14: DEAL-01122 | B14: Rahul Patel | C14: CLI-0070 | D14: AI Insights Module | E14: Webinar | F14: Closed Won | G14: 207588 | H14: 45335 | I14: 45486 | J14: 151 | K14: 4.3 | L14: East | M14: Q1-2024 | N14: Normal
A15: DEAL-01643 | B15: Riya Das | C15: CLI-0298 | D15: DevOps Accelerator | E15: Referral | F15: Closed Won | G15: 244787 | H15: 45210 | I15: 45327 | J15: 117 | K15: 7.8 | L15: East | M15: Q4-2023 | N15: Normal
A16: DEAL-00234 | B16: Ananya Sharma | C16: CLI-0286 | D16: SecureNet Suite | E16: Trade Show | F16: Closed Won | G16: 223320 | H16: 45623 | I16: 45770 | J16: 147 | K16: 9 | L16: North | M16: Q4-2024 | N16: Normal
A17: DEAL-01783 | B17: Vikram Iyer | C17: CLI-0050 | D17: AI Insights Module | E17: Cold Outreach | F17: Proposal Sent | G17: 341493 | H17: 45142 | L17: West | M17: Q3-2023 | N17: Normal
A18: DEAL-00305 | B18: Neha Pillai | C18: CLI-0035 | D18: AI Insights Module | E18: Google Ads | F18: Closed Lost | G18: 416867 | H18: 45426 | I18: 45541 | J18: 115 | K18: 12.2 | L18: South | M18: Q2-2024 | N18: Normal
A19: DEAL-00351 | B19: Arjun Rao | C19: CLI-0090 | D19: CloudShift Platform | E19: Trade Show | F19: Proposal Sent | G19: 67690 | H19: 45708 | K19: 12.5 | L19: South | M19: Q1-2025 | N19: Normal
A20: DEAL-02148 | B20: Aditya Pillai | C20: CLI-0202 | D20: CloudShift Platform | E20: Email Campaign | F20: Closed Won | G20: 453993 | H20: 45316 | I20: 45466 | J20: 150 | K20: 9.5 | L20: West | M20: Q1-2024 | N20: Normal
A21: DEAL-01377 | B21: Vikram Patel | C21: CLI-0102 | D21: AnalyticsEdge | E21: Trade Show | F21: Proposal Sent | G21: 404058 | H21: 45432 | K21: 5.3 | L21: South | M21: Q2-2024 | N21: Normal
A22: DEAL-01947 | B22: Arjun Rao | C22: CLI-0135 | D22: CloudShift Platform | E22: LinkedIn Campaign | F22: Qualification | G22: 117974 | H22: 44950 | K22: 11.5 | L22: East | M22: Q1-2023 | N22: Normal
A23: DEAL-02354 | B23: Meera Reddy | C23: CLI-0120 | D23: CloudShift Platform | E23: LinkedIn Campaign | F23: Proposal Sent | G23: 111938 | H23: 45725 | L23: South | M23: Q1-2025 | N23: Normal
A24: DEAL-01835 | B24: Rahul Patel | C24: CLI-0070 | D24: AI Insights Module | E24: Cold Outreach | F24: Closed Lost | G24: 133407 | H24: 45046 | I24: 45166 | J24: 120 | K24: 10.9 | L24: North | M24: Q2-2023 | N24: Normal
A25: DEAL-02057 | B25: Deepika Das | C25: CLI-0125 | D25: SecureNet Suite | E25: Unknown | F25: Negotiation | G25: 125962 | H25: 45347 | K25: 12.9 | L25: East | M25: Q1-2024 | N25: Normal
A26: DEAL-00631 | B26: Aditya Pillai | C26: CLI-0222 | D26: AnalyticsEdge | E26: Trade Show | F26: Closed Won | G26: 71017 | H26: 44994 | I26: 45095 | J26: 101 | K26: 3.5 | L26: West | M26: Q1-2023 | N26: Normal
A27: DEAL-02059 | B27: Vikram Iyer | C27: CLI-0191 | D27: AnalyticsEdge | E27: Cold Outreach | F27: Closed Won | G27: 80078 | H27: 45652 | I27: 45722 | J27: 70 | K27: 4.9 | L27: North | M27: Q4-2024 | N27: Normal
A28: DEAL-00946 | B28: Rahul Patel | C28: CLI-0158 | D28: SecureNet Suite | E28: Cold Outreach | F28: Negotiation | G28: 147459 | H28: 45026 | K28: 6.4 | L28: South | M28: Q2-2023 | N28: Normal
A29: DEAL-01560 | B29: Siddharth Gupta | C29: CLI-0219 | D29: AI Insights Module | E29: Webinar | F29: Closed Lost | G29: 59394 | H29: 45278 | I29: 45351 | J29: 73 | K29: 2.1 | L29: East | M29: Q4-2023 | N29: Normal
A30: DEAL-01779 | B30: Neha Pillai | C30: CLI-0266 | D30: CloudShift Platform | E30: LinkedIn Campaign | F30: Prospecting | G30: 490489 | H30: 45699 | L30: North | M30: Q1-2025 | N30: Normal
A31: DEAL-01223 | B31: Ananya Sharma | C31: CLI-0006 | D31: DevOps Accelerator | E31: Trade Show | F31: Proposal Sent | G31: 267116 | H31: 45475 | K31: 3 | L31: South | M31: Q3-2024 | N31: Normal
A32: DEAL-02345 | B32: Riya Das | C32: CLI-0060 | D32: DevOps Accelerator | E32: Trade Show | F32: Closed Lost | G32: 340697 | H32: 45094 | I32: 45174 | J32: 80 | K32: 6.7 | L32: North | M32: Q2-2023 | N32: Normal
A33: DEAL-00816 | B33: Aditya Pillai | C33: CLI-0278 | D33: CloudShift Platform | E33: Referral | F33: Negotiation | G33: 432247 | H33: 45729 | K33: 13.4 | L33: North | M33: Q1-2025 | N33: Normal
A34: DEAL-01909 | B34: Amit Pillai | C34: CLI-0063 | D34: AnalyticsEdge | E34: Email Campaign | F34: Closed Lost | G34: 449838 | H34: 45442 | I34: 45589 | J34: 147 | K34: 6.8 | L34: West | M34: Q2-2024 | N34: Normal
A35: DEAL-00184 | B35: Siddharth Gupta | C35: CLI-0080 | D35: AI Insights Module | E35: LinkedIn Campaign | F35: Negotiation | G35: 325774 | H35: 45335 | L35: West | M35: Q1-2024 | N35: Normal
A36: DEAL-00430 | B36: Siddharth Gupta | C36: CLI-0088 | D36: AnalyticsEdge | E36: Trade Show | F36: Closed Lost | G36: 251845 | H36: 45499 | I36: 45520 | J36: 21 | K36: 6.3 | L36: East | M36: Q3-2024 | N36: Normal
A37: DEAL-01657 | B37: Arjun Rao | C37: CLI-0154 | D37: CloudShift Platform | E37: Cold Outreach | F37: Proposal Sent | G37: 245814 | H37: 45017 | L37: North | M37: Q2-2023 | N37: Normal
A38: DEAL-01118 | B38: Rohit Mehta | C38: CLI-0086 | D38: AI Insights Module | E38: Webinar | F38: Qualification | G38: 128284 | H38: 45083 | K38: 1.5 | L38: South | M38: Q2-2023 | N38: Normal
A39: DEAL-00337 | B39: Meera Reddy | C39: CLI-0286 | D39: SecureNet Suite | E39: Unknown | F39: Proposal Sent | G39: 157092 | H39: 45655 | K39: 6.3 | L39: North | M39: Q4-2024 | N39: Normal
A40: DEAL-01051 | B40: Priya Kumar | C40: CLI-0284 | D40: DevOps Accelerator | E40: Trade Show | F40: Qualification | G40: 387930 | H40: 45587 | K40: 2.8 | L40: West | M40: Q4-2024 | N40: Normal
A41: DEAL-01916 | B41: Arjun Rao | C41: CLI-0288 | D41: DevOps Accelerator | E41: Webinar | F41: Negotiation | G41: 265994 | H41: 45744 | K41: 0.7 | L41: North | M41: Q1-2025 | N41: Normal
A42: DEAL-00718 | B42: Rohit Mehta | C42: CLI-0272 | D42: SecureNet Suite | E42: Webinar | F42: Closed Won | G42: 925816 | H42: 45449 | I42: 45467 | J42: 18 | K42: 16.6 | L42: North | M42: Q2-2024 | N42: High Outlier
A43: DEAL-02141 | B43: Siddharth Joshi | C43: CLI-0218 | D43: DataVault Pro | E43: LinkedIn Campaign | F43: Closed Won | G43: 57872 | H43: 45391 | I43: 45559 | J43: 168 | K43: 4.5 | L43: South | M43: Q2-2024 | N43: Normal
A44: DEAL-00488 | B44: Riya Das | C44: CLI-0221 | D44: AnalyticsEdge | E44: Trade Show | F44: Closed Won | G44: 25184 | H44: 45446 | I44: 45516 | J44: 70 | K44: 19.6 | L44: North | M44: Q2-2024 | N44: Normal
A45: DEAL-01718 | B45: Aditya Pillai | C45: CLI-0138 | D45: AI Insights Module | E45: Google Ads | F45: Qualification | G45: 46255 | H45: 45309 | L45: West | M45: Q1-2024 | N45: Normal
A46: DEAL-01359 | B46: Rahul Patel | C46: CLI-0162 | D46: AI Insights Module | E46: Organic Search | F46: Closed Won | G46: 34502 | H46: 45629 | I46: 45690 | J46: 61 | K46: 2.3 | L46: North | M46: Q4-2024 | N46: Normal
A47: DEAL-01902 | B47: Meera Reddy | C47: CLI-0007 | D47: SecureNet Suite | E47: Google Ads | F47: Closed Won | G47: 242893 | H47: 45265 | I47: 45286 | J47: 21 | K47: 14.4 | L47: West | M47: Q4-2023 | N47: Normal
A48: DEAL-00388 | B48: Riya Das | C48: CLI-0052 | D48: CloudShift Platform | E48: Unknown | F48: Closed Won | G48: 276108 | H48: 45601 | I48: 45683 | J48: 82 | K48: 22.6 | L48: West | M48: Q4-2024 | N48: Normal
A49: DEAL-02216 | B49: Deepika Das | C49: CLI-0278 | D49: AI Insights Module | E49: Organic Search | F49: Proposal Sent | G49: 225261 | H49: 45248 | K49: 12.7 | L49: North | M49: Q4-2023 | N49: Normal
A50: DEAL-00556 | B50: Siddharth Gupta | C50: CLI-0138 | D50: AI Insights Module | E50: Cold Outreach | F50: Negotiation | G50: 321651 | H50: 45070 | L50: South | M50: Q2-2023 | N50: Normal
A51: DEAL-01130 | B51: Vikram Iyer | C51: CLI-0216 | D51: AnalyticsEdge | E51: Referral | F51: Prospecting | G51: 495204 | H51: 45734 | L51: North | M51: Q1-2025 | N51: Normal
A52: DEAL-00938 | B52: Deepika Das | C52: CLI-0160 | D52: SecureNet Suite | E52: Google Ads | F52: Negotiation | G52: 130238 | H52: 45191 | L52: West | M52: Q3-2023 | N52: Normal
A53: DEAL-00794 | B53: Siddharth Gupta | C53: CLI-0135 | D53: AnalyticsEdge | E53: Cold Outreach | F53: Proposal Sent | G53: 115669 | H53: 45076 | K53: 3.1 | L53: South | M53: Q2-2023 | N53: Normal
A54: DEAL-00604 | B54: Aditya Pillai | C54: CLI-0043 | D54: DataVault Pro | E54: Email Campaign | F54: Qualification | G54: 154425 | H54: 44938 | K54: 9.6 | L54: North | M54: Q1-2023 | N54: Normal
A55: DEAL-00954 | B55: Riya Das | C55: CLI-0208 | D55: DevOps Accelerator | E55: Trade Show | F55: Proposal Sent | G55: 225199 | H55: 45735 | L55: East | M55: Q1-2025 | N55: Normal
A56: DEAL-01107 | B56: Rahul Patel | C56: CLI-0005 | D56: SecureNet Suite | E56: Cold Outreach | F56: Negotiation | G56: 487991 | H56: 45655 | L56: West | M56: Q4-2024 | N56: Normal
A57: DEAL-00597 | B57: Neha Pillai | C57: CLI-0230 | D57: DevOps Accelerator | E57: Email Campaign | F57: Closed Won | G57: 360231 | H57: 45708 | I57: 45855 | J57: 147 | K57: 19.5 | L57: West | M57: Q1-2025 | N57: Normal
A58: DEAL-01404 | B58: Deepika Das | C58: CLI-0286 | D58: AI Insights Module | E58: LinkedIn Campaign | F58: Closed Won | G58: 128919 | H58: 45739 | I58: 45836 | J58: 97 | K58: 5 | L58: West | M58: Q1-2025 | N58: Normal
A59: DEAL-02242 | B59: Aditya Pillai | C59: CLI-0002 | D59: DataVault Pro | E59: Referral | F59: Proposal Sent | G59: 422278 | H59: 45532 | K59: 13.7 | L59: East | M59: Q3-2024 | N59: Normal
A60: DEAL-02405 | B60: Rohit Mehta | C60: CLI-0077 | D60: SecureNet Suite | E60: Webinar | F60: Negotiation | G60: 36712 | H60: 45136 | K60: 5.8 | L60: South | M60: Q3-2023 | N60: Normal
A61: DEAL-00721 | B61: Arjun Rao | C61: CLI-0135 | D61: AnalyticsEdge | E61: Google Ads | F61: Qualification | G61: 390892 | H61: 45327 | K61: 6.7 | L61: South | M61: Q1-2024 | N61: Normal
A62: DEAL-00504 | B62: Siddharth Gupta | C62: CLI-0237 | D62: DataVault Pro | E62: Webinar | F62: Negotiation | G62: 12937 | H62: 45119 | L62: West | M62: Q3-2023 | N62: Normal
A63: DEAL-00937 | B63: Rahul Patel | C63: CLI-0060 | D63: AnalyticsEdge | E63: Cold Outreach | F63: Closed Won | G63: 324521 | H63: 45500 | I63: 45644 | J63: 144 | K63: 18.2 | L63: West | M63: Q3-2024 | N63: Normal
A64: DEAL-01769 | B64: Deepika Das | C64: CLI-0208 | D64: AI Insights Module | E64: Referral | F64: Proposal Sent | G64: 113876 | H64: 45744 | L64: South | M64: Q1-2025 | N64: Normal
A65: DEAL-01725 | B65: Aditya Pillai | C65: CLI-0197 | D65: CloudShift Platform | E65: Webinar | F65: Proposal Sent | G65: 499086 | H65: 44931 | K65: 4.9 | L65: East | M65: Q1-2023 | N65: Normal
A66: DEAL-00951 | B66: Ananya Sharma | C66: CLI-0063 | D66: CloudShift Platform | E66: Email Campaign | F66: Closed Lost | G66: 139182 | H66: 45317 | I66: 45343 | J66: 26 | L66: North | M66: Q1-2024 | N66: Normal
A67: DEAL-00313 | B67: Siddharth Joshi | C67: CLI-0063 | D67: DevOps Accelerator | E67: Webinar | F67: Prospecting | G67: 244478 | H67: 45052 | K67: 0.6 | L67: South | M67: Q2-2023 | N67: Normal
A68: DEAL-00726 | B68: Vikram Patel | C68: CLI-0251 | D68: DevOps Accelerator | E68: Trade Show | F68: Closed Won | G68: 108751 | H68: 45732 | I68: 45782 | J68: 50 | K68: 17.2 | L68: South | M68: Q1-2025 | N68: Normal
A69: DEAL-01062 | B69: Ananya Sharma | C69: CLI-0243 | D69: SecureNet Suite | E69: LinkedIn Campaign | F69: Proposal Sent | G69: 387686 | H69: 45006 | K69: 8.5 | L69: East | M69: Q1-2023 | N69: Normal
A70: DEAL-00072 | B70: Neha Pillai | C70: CLI-0228 | D70: SecureNet Suite | E70: Email Campaign | F70: Closed Won | G70: 42234 | H70: 45069 | I70: 45232 | J70: 163 | K70: 15.9 | L70: North | M70: Q2-2023 | N70: Normal
A71: DEAL-00593 | B71: Meera Reddy | C71: CLI-0084 | D71: DevOps Accelerator | E71: LinkedIn Campaign | F71: Qualification | G71: 141423 | H71: 45602 | K71: 4.5 | L71: West | M71: Q4-2024 | N71: Normal
A72: DEAL-00633 | B72: Rahul Patel | C72: CLI-0275 | D72: DataVault Pro | E72: Cold Outreach | F72: Closed Lost | G72: 233514 | H72: 45313 | I72: 45349 | J72: 36 | K72: 7.4 | L72: West | M72: Q1-2024 | N72: Normal
A73: DEAL-00241 | B73: Rohit Mehta | C73: CLI-0292 | D73: CloudShift Platform | E73: Google Ads | F73: Qualification | G73: 316458 | H73: 45594 | K73: 11.3 | L73: South | M73: Q4-2024 | N73: Normal
A74: DEAL-00879 | B74: Neha Pillai | C74: CLI-0031 | D74: CloudShift Platform | E74: Referral | F74: Closed Lost | G74: 274493 | H74: 45654 | I74: 45769 | J74: 115 | K74: 0.4 | L74: East | M74: Q4-2024 | N74: Normal
A75: DEAL-01532 | B75: Arjun Rao | C75: CLI-0109 | D75: CloudShift Platform | E75: Google Ads | F75: Negotiation | G75: 187167 | H75: 45073 | L75: South | M75: Q2-2023 | N75: Normal
A76: DEAL-02348 | B76: Meera Reddy | C76: CLI-0295 | D76: SecureNet Suite | E76: LinkedIn Campaign | F76: Closed Lost | G76: 263320 | H76: 45404 | I76: 45429 | J76: 25 | L76: North | M76: Q2-2024 | N76: Normal
A77: DEAL-01079 | B77: Amit Pillai | C77: CLI-0172 | D77: CloudShift Platform | E77: Referral | F77: Prospecting | G77: 168215 | H77: 45370 | K77: 12.7 | L77: North | M77: Q1-2024 | N77: Normal
A78: DEAL-01305 | B78: Amit Pillai | C78: CLI-0206 | D78: SecureNet Suite | E78: Google Ads | F78: Closed Won | G78: 20087 | H78: 45455 | I78: 45599 | J78: 144 | K78: 24.1 | L78: South | M78: Q2-2024 | N78: Normal
A79: DEAL-00187 | B79: Siddharth Gupta | C79: CLI-0180 | D79: AI Insights Module | E79: Referral | F79: Closed Won | G79: 384150 | H79: 45434 | I79: 45583 | J79: 149 | K79: 13.1 | L79: East | M79: Q2-2024 | N79: Normal
A80: DEAL-02217 | B80: Ananya Sharma | C80: CLI-0270 | D80: SecureNet Suite | E80: Referral | F80: Negotiation | G80: 354315 | H80: 44983 | K80: 10.3 | L80: East | M80: Q1-2023 | N80: Normal
A81: DEAL-00347 | B81: Siddharth Gupta | C81: CLI-0077 | D81: AI Insights Module | E81: Google Ads | F81: Closed Won | G81: 124965 | H81: 45213 | I81: 45273 | J81: 60 | K81: 0.4 | L81: North | M81: Q4-2023 | N81: Normal
A82: DEAL-00971 | B82: Aditya Pillai | C82: CLI-0087 | D82: AnalyticsEdge | E82: Webinar | F82: Closed Lost | G82: 410731 | H82: 44989 | I82: 45082 | J82: 93 | K82: 4.7 | L82: South | M82: Q1-2023 | N82: Normal
A83: DEAL-00709 | B83: Aditya Pillai | C83: CLI-0183 | D83: AI Insights Module | E83: Email Campaign | F83: Closed Lost | G83: 272141 | H83: 44958 | I83: 45038 | J83: 80 | K83: 12.9 | L83: North | M83: Q1-2023 | N83: Normal
A84: DEAL-00383 | B84: Ananya Sharma | C84: CLI-0138 | D84: AI Insights Module | E84: LinkedIn Campaign | F84: Prospecting | G84: 400965 | H84: 45357 | K84: 10.4 | L84: West | M84: Q1-2024 | N84: Normal
A85: DEAL-01809 | B85: Siddharth Joshi | C85: CLI-0103 | D85: CloudShift Platform | E85: Organic Search | F85: Negotiation | G85: 217920 | H85: 45628 | L85: West | M85: Q4-2024 | N85: Normal
A86: DEAL-00077 | B86: Rahul Patel | C86: CLI-0075 | D86: DataVault Pro | E86: Trade Show | F86: Closed Lost | G86: 478494 | H86: 45545 | I86: 45668 | J86: 123 | K86: 6.8 | L86: West | M86: Q3-2024 | N86: Normal
A87: DEAL-00423 | B87: Vikram Patel | C87: CLI-0146 | D87: AnalyticsEdge | E87: Webinar | F87: Proposal Sent | G87: 366026 | H87: 45266 | K87: 5.9 | L87: East | M87: Q4-2023 | N87: Normal
A88: DEAL-01237 | B88: Amit Pillai | C88: CLI-0033 | D88: AI Insights Module | E88: Email Campaign | F88: Closed Won | G88: 210971 | H88: 45503 | I88: 45562 | J88: 59 | K88: 19.3 | L88: West | M88: Q3-2024 | N88: Normal
A89: DEAL-01217 | B89: Amit Pillai | C89: CLI-0017 | D89: AnalyticsEdge | E89: Webinar | F89: Qualification | G89: 392720 | H89: 45444 | K89: 5.8 | L89: South | M89: Q2-2024 | N89: Normal
A90: DEAL-01724 | B90: Neha Pillai | C90: CLI-0090 | D90: AnalyticsEdge | E90: LinkedIn Campaign | F90: Negotiation | G90: 268444 | H90: 45424 | L90: East | M90: Q2-2024 | N90: Normal
A91: DEAL-00151 | B91: Siddharth Gupta | C91: CLI-0099 | D91: CloudShift Platform | E91: Google Ads | F91: Qualification | G91: 202104 | H91: 45686 | K91: 8.8 | L91: East | M91: Q1-2025 | N91: Normal
A92: DEAL-00418 | B92: Deepika Das | C92: CLI-0295 | D92: AI Insights Module | E92: Referral | F92: Qualification | G92: 367272 | H92: 45118 | K92: 5 | L92: North | M92: Q3-2023 | N92: Normal
A93: DEAL-01039 | B93: Priya Kumar | C93: CLI-0212 | D93: AI Insights Module | E93: Organic Search | F93: Closed Lost | G93: 199001 | H93: 45374 | I93: 45483 | J93: 109 | L93: West | M93: Q1-2024 | N93: Normal
A94: DEAL-01871 | B94: Siddharth Joshi | C94: CLI-0026 | D94: DevOps Accelerator | E94: Email Campaign | F94: Qualification | G94: 321550 | H94: 45119 | L94: East | M94: Q3-2023 | N94: Normal
A95: DEAL-01438 | B95: Ananya Sharma | C95: CLI-0259 | D95: SecureNet Suite | E95: Referral | F95: Negotiation | G95: 376342 | H95: 45344 | K95: 1.9 | L95: East | M95: Q1-2024 | N95: Normal
A96: DEAL-02064 | B96: Rohit Mehta | C96: CLI-0248 | D96: DevOps Accelerator | E96: Referral | F96: Closed Lost | G96: 119352 | H96: 45346 | I96: 45410 | J96: 64 | K96: 5.9 | L96: South | M96: Q1-2024 | N96: Normal
A97: DEAL-00140 | B97: Aditya Pillai | C97: CLI-0261 | D97: DevOps Accelerator | E97: LinkedIn Campaign | F97: Prospecting | G97: 313108 | H97: 45468 | L97: East | M97: Q2-2024 | N97: Normal
A98: DEAL-01175 | B98: Ananya Sharma | C98: CLI-0273 | D98: DataVault Pro | E98: Cold Outreach | F98: Negotiation | G98: 254116 | H98: 45674 | K98: 11 | L98: West | M98: Q1-2025 | N98: Normal
A99: DEAL-01177 | B99: Rahul Patel | C99: CLI-0122 | D99: CloudShift Platform | E99: LinkedIn Campaign | F99: Negotiation | G99: 336032 | H99: 45124 | K99: 4.6 | L99: North | M99: Q3-2023 | N99: Normal
A100: DEAL-02224 | B100: Deepika Das | C100: CLI-0166 | D100: DevOps Accelerator | E100: Google Ads | F100: Closed Won | G100: 345065 | H100: 45194 | I100: 45267 | J100: 73 | K100: 2.5 | L100: West | M100: Q3-2023 | N100: Normal
...

Sheet Support_Tickets
A1: Ticket_ID | B1: Client_ID | C1: Product | D1: Issue_Type | E1: Priority | F1: Created_Date | G1: Resolved_Date | H1: Resolution_Hours | I1: SLA_Target_Hours | J1: SLA_Met | K1: Status | L1: Assigned_Agent | M1: Contact_Channel | N1: Customer_Satisfaction
A2: TKT-01100 | B2: CLI-0182 | C2: DataVault Pro | D2: Access Permission Issue | E2: Low | F2: 45348 | G2: 45350 | H2: 54.6 | I2: 48 | J2: No | K2: Resolved | L2: Unassigned | M2: Email | N2: 4
A3: TKT-02536 | B3: CLI-0020 | C3: AI Insights Module | D3: Feature Request | E3: Medium | F3: 45520 | G3: 45521 | H3: 25.9 | I3: 24 | J3: No | K3: Resolved | L3: Ananya Joshi | M3: Chat | N3: 1
A4: TKT-00220 | B4: CLI-0156 | C4: AI Insights Module | D4: Feature Request | E4: Medium | F4: 45230 | G4: 45230 | H4: 10.1 | I4: 24 | J4: Yes | K4: Resolved | L4: Rahul Das | M4: Phone | N4: 3
A5: TKT-02139 | B5: CLI-0222 | C5: DevOps Accelerator | D5: Login Issue | E5: Medium | F5: 45149 | I5: 24 | J5: Yes | K5: Escalated | L5: Pooja Iyer | M5: Email
A6: TKT-01110 | B6: CLI-0247 | C6: CloudShift Platform | D6: Feature Request | E6: Critical | F6: 45394 | I6: 4 | J6: Yes | K6: In Progress | L6: Divya Reddy | M6: Chat
A7: TKT-03054 | B7: CLI-0169 | C7: CloudShift Platform | D7: Onboarding Support | E7: Critical | F7: 45319 | G7: 45319 | H7: 8.4 | I7: 4 | J7: No | K7: Resolved | L7: Pooja Patel | M7: Portal | N7: 3
A8: TKT-00333 | B8: CLI-0074 | C8: DevOps Accelerator | D8: Security Alert | E8: Low | F8: 45700 | G8: 45702 | H8: 54.5 | I8: 48 | J8: No | K8: Resolved | L8: Pooja Gupta | M8: Chat | N8: 3
A9: TKT-01472 | B9: CLI-0288 | C9: SecureNet Suite | D9: Security Alert | E9: Medium | F9: 45570 | I9: 24 | J9: No | K9: Escalated | L9: Manish Nair | M9: Phone
A10: TKT-01841 | B10: CLI-0206 | C10: AI Insights Module | D10: API Integration Failure | E10: Medium | F10: 45103 | G10: 45103 | H10: 2.6 | I10: 24 | J10: Yes | K10: Resolved | L10: Priya Nair | M10: Portal | N10: 3
A11: TKT-00445 | B11: CLI-0230 | C11: DevOps Accelerator | D11: Dashboard Bug | E11: High | F11: 45024 | I11: 8 | J11: Yes | K11: Open | L11: Divya Reddy | M11: Portal
A12: TKT-03379 | B12: CLI-0033 | C12: AnalyticsEdge | D12: Billing Query | E12: Low | F12: 44932 | I12: 48 | J12: No | K12: Open | L12: Priya Nair | M12: Portal
A13: TKT-01818 | B13: CLI-0029 | C13: DataVault Pro | D13: API Integration Failure | E13: Medium | F13: 45250 | G13: 45252 | H13: 50.4 | I13: 24 | J13: Unknown | K13: Resolved | L13: Manish Nair | M13: Portal | N13: 3
A14: TKT-00367 | B14: CLI-0184 | C14: CloudShift Platform | D14: Report Inaccuracy | E14: High | F14: 45029 | I14: 8 | J14: No | K14: Open | L14: Neha Gupta | M14: Portal
A15: TKT-03060 | B15: CLI-0057 | C15: DevOps Accelerator | D15: Performance Lag | E15: Medium | F15: 45490 | G15: 45492 | H15: 54.8 | I15: 24 | J15: No | K15: Resolved | L15: Deepika Mishra | M15: Email | N15: 4
A16: TKT-03487 | B16: CLI-0205 | C16: CloudShift Platform | D16: Data Sync Error | E16: Medium | F16: 44983 | I16: 24 | J16: No | K16: Escalated | L16: Manish Nair | M16: Email
A17: TKT-03741 | B17: CLI-0183 | C17: SecureNet Suite | D17: Onboarding Support | E17: Medium | F17: 45046 | I17: 24 | J17: Yes | K17: Open | L17: Manish Nair | M17: Email
A18: TKT-01257 | B18: CLI-0068 | C18: AnalyticsEdge | D18: Feature Request | E18: High | F18: 45076 | G18: 45076 | H18: 14 | I18: 8 | J18: No | K18: Resolved | L18: Nikhil Mehta | M18: Chat | N18: 5
A19: TKT-01790 | B19: CLI-0205 | C19: AI Insights Module | D19: Server Downtime | E19: Medium | F19: 45328 | I19: 24 | J19: Unknown | K19: Open | L19: Manish Nair | M19: Portal
A20: TKT-02799 | B20: CLI-0093 | C20: CloudShift Platform | D20: Access Permission Issue | E20: Low | F20: 44999 | I20: 48 | J20: No | K20: Open | L20: Kavya Iyer | M20: Email
A21: TKT-00635 | B21: CLI-0099 | C21: AnalyticsEdge | D21: Onboarding Support | E21: Medium | F21: 45284 | I21: 24 | J21: Yes | K21: Escalated | L21: Kavya Iyer | M21: Chat
A22: TKT-01805 | B22: CLI-0161 | C22: DataVault Pro | D22: Report Inaccuracy | E22: Low | F22: 45729 | G22: 45729 | H22: 11.8 | I22: 48 | J22: Yes | K22: Resolved | L22: Neha Gupta | M22: Chat | N22: 3
A23: TKT-03253 | B23: CLI-0121 | C23: SecureNet Suite | D23: Server Downtime | E23: Medium | F23: 45496 | G23: 45497 | H23: 39.3 | I23: 24 | J23: No | K23: Resolved | L23: Pooja Gupta | M23: Email | N23: 2
A24: TKT-00709 | B24: CLI-0017 | C24: AI Insights Module | D24: Data Sync Error | E24: Critical | F24: 45539 | I24: 4 | J24: No | K24: Open | L24: Unassigned | M24: Email
A25: TKT-00343 | B25: CLI-0127 | C25: CloudShift Platform | D25: Access Permission Issue | E25: Medium | F25: 45722 | G25: 45723 | H25: 31.4 | I25: 24 | J25: No | K25: Resolved | L25: Neha Gupta | M25: Chat | N25: 4
A26: TKT-03567 | B26: CLI-0107 | C26: AI Insights Module | D26: Server Downtime | E26: Critical | F26: 45176 | G26: 45176 | H26: 8.7 | I26: 4 | J26: No | K26: Resolved | L26: Unassigned | M26: Email | N26: 4
A27: TKT-02295 | B27: CLI-0158 | C27: SecureNet Suite | D27: Login Issue | E27: Low | F27: 45431 | I27: 48 | J27: Yes | K27: Open | L27: Priya Nair | M27: Portal
A28: TKT-02678 | B28: CLI-0279 | C28: AnalyticsEdge | D28: Data Sync Error | E28: Low | F28: 45541 | G28: 45543 | H28: 67.1 | I28: 48 | J28: No | K28: Resolved | L28: Siddharth Reddy | M28: Portal | N28: 4
A29: TKT-03086 | B29: CLI-0298 | C29: DataVault Pro | D29: Onboarding Support | E29: Low | F29: 45314 | G29: 45315 | H29: 32.4 | I29: 48 | J29: Yes | K29: Resolved | L29: Pooja Gupta | M29: Phone | N29: 4
A30: TKT-00950 | B30: CLI-0014 | C30: AI Insights Module | D30: Login Issue | E30: Low | F30: 45597 | G30: 45601 | H30: 105.1 | I30: 48 | J30: No | K30: Resolved | L30: Pooja Patel | M30: Phone | N30: 4
A31: TKT-02137 | B31: CLI-0088 | C31: CloudShift Platform | D31: Login Issue | E31: Low | F31: 45571 | I31: 48 | J31: Yes | K31: In Progress | L31: Kavya Iyer | M31: Phone
A32: TKT-03836 | B32: CLI-0080 | C32: CloudShift Platform | D32: Performance Lag | E32: Medium | F32: 45016 | I32: 24 | J32: Yes | K32: Escalated | L32: Kavya Iyer | M32: Portal
A33: TKT-03334 | B33: CLI-0165 | C33: AnalyticsEdge | D33: Login Issue | E33: Critical | F33: 45264 | G33: 45264 | H33: 2.5 | I33: 4 | J33: Yes | K33: Resolved | L33: Rahul Das | M33: Portal
A34: TKT-03902 | B34: CLI-0278 | C34: DevOps Accelerator | D34: Onboarding Support | E34: Low | F34: 45375 | G34: 45376 | H34: 40.3 | I34: 48 | J34: Yes | K34: Resolved | L34: Rahul Das | M34: Phone | N34: 5
A35: TKT-02387 | B35: CLI-0265 | C35: DevOps Accelerator | D35: Server Downtime | E35: Critical | F35: 45646 | G35: 45646 | H35: 7.5 | I35: 4 | J35: No | K35: Resolved | L35: Karan Gupta | M35: Portal | N35: 4
A36: TKT-03282 | B36: CLI-0089 | C36: AI Insights Module | D36: Onboarding Support | E36: Medium | F36: 45332 | I36: 24 | J36: Yes | K36: In Progress | L36: Manish Nair | M36: Email
A37: TKT-03494 | B37: CLI-0134 | C37: DevOps Accelerator | D37: Server Downtime | E37: Medium | F37: 45196 | I37: 24 | J37: No | K37: Escalated | L37: Arjun Mishra | M37: Phone
A38: TKT-02380 | B38: CLI-0131 | C38: AI Insights Module | D38: Performance Lag | E38: Medium | F38: 45330 | I38: 24 | J38: No | K38: In Progress | L38: Priya Patel | M38: Phone
A39: TKT-03553 | B39: CLI-0150 | C39: DevOps Accelerator | D39: Access Permission Issue | E39: Low | F39: 45079 | I39: 48 | J39: No | K39: Escalated | L39: Rahul Das | M39: Phone
A40: TKT-03523 | B40: CLI-0104 | C40: DevOps Accelerator | D40: Report Inaccuracy | E40: Medium | F40: 45530 | G40: 45531 | H40: 24.6 | I40: 24 | J40: No | K40: Resolved | L40: Neha Gupta | M40: Email | N40: 3
A41: TKT-03577 | B41: CLI-0086 | C41: DevOps Accelerator | D41: Billing Query | E41: Low | F41: 45449 | I41: 48 | J41: No | K41: In Progress | L41: Kavya Iyer | M41: Phone
A42: TKT-00070 | B42: CLI-0172 | C42: DataVault Pro | D42: Login Issue | E42: High | F42: 45739 | I42: 8 | J42: No | K42: Escalated | L42: Pooja Iyer | M42: Email
A43: TKT-02556 | B43: CLI-0206 | C43: DataVault Pro | D43: Billing Query | E43: High | F43: 44988 | G43: 44988 | H43: 9.1 | I43: 8 | J43: No | K43: Resolved | L43: Neha Gupta | M43: Email | N43: 2
A44: TKT-01161 | B44: CLI-0037 | C44: CloudShift Platform | D44: API Integration Failure | E44: Low | F44: 45077 | I44: 48 | J44: No | K44: Escalated | L44: Deepika Mishra | M44: Portal
A45: TKT-03580 | B45: CLI-0222 | C45: SecureNet Suite | D45: Feature Request | E45: High | F45: 45624 | I45: 8 | J45: Yes | K45: In Progress | L45: Deepika Mishra | M45: Email
A46: TKT-03327 | B46: CLI-0069 | C46: DevOps Accelerator | D46: Billing Query | E46: Medium | F46: 45324 | I46: 24 | J46: No | K46: Open | L46: Pooja Iyer | M46: Chat
A47: TKT-03342 | B47: CLI-0274 | C47: AnalyticsEdge | D47: Dashboard Bug | E47: Low | F47: 45739 | G47: 45739 | H47: 11.9 | I47: 48 | J47: Yes | K47: Resolved | L47: Siddharth Reddy | M47: Portal | N47: 5
A48: TKT-00112 | B48: CLI-0077 | C48: DevOps Accelerator | D48: Server Downtime | E48: Low | F48: 45551 | G48: 45552 | H48: 36.1 | I48: 48 | J48: Yes | K48: Resolved | L48: Rahul Das | M48: Email | N48: 3
A49: TKT-01800 | B49: CLI-0088 | C49: AI Insights Module | D49: API Integration Failure | E49: Medium | F49: 45341 | G49: 45341 | H49: 14.4 | I49: 24 | J49: Yes | K49: Resolved | L49: Rahul Das | M49: Phone | N49: 2
A50: TKT-02619 | B50: CLI-0087 | C50: AnalyticsEdge | D50: Access Permission Issue | E50: Low | F50: 45474 | I50: 48 | J50: No | K50: Open | L50: Karan Rao | M50: Portal
A51: TKT-03979 | B51: CLI-0283 | C51: SecureNet Suite | D51: Server Downtime | E51: High | F51: 45007 | I51: 8 | J51: No | K51: Open | L51: Ananya Joshi | M51: Portal
A52: TKT-00369 | B52: CLI-0112 | C52: DataVault Pro | D52: Server Downtime | E52: Critical | F52: 44978 | I52: 4 | J52: No | K52: In Progress | L52: Deepika Mishra | M52: Chat
A53: TKT-02046 | B53: CLI-0278 | C53: DataVault Pro | D53: Report Inaccuracy | E53: Medium | F53: 45618 | I53: 24 | J53: Yes | K53: In Progress | L53: Karan Rao | M53: Chat
A54: TKT-02983 | B54: CLI-0074 | C54: DataVault Pro | D54: Performance Lag | E54: Critical | F54: 45008 | I54: 4 | J54: No | K54: In Progress | L54: Siddharth Reddy | M54: Phone
A55: TKT-02680 | B55: CLI-0270 | C55: AnalyticsEdge | D55: Billing Query | E55: High | F55: 45387 | I55: 8 | J55: No | K55: Open | L55: Divya Verma | M55: Phone
A56: TKT-00221 | B56: CLI-0255 | C56: DataVault Pro | D56: Dashboard Bug | E56: High | F56: 45537 | G56: 45537 | H56: 1.8 | I56: 8 | J56: Yes | K56: Resolved | L56: Pooja Iyer | M56: Email | N56: 4
A57: TKT-01719 | B57: CLI-0121 | C57: DevOps Accelerator | D57: Server Downtime | E57: Medium | F57: 45370 | G57: 45371 | H57: 47.2 | I57: 24 | J57: No | K57: Resolved | L57: Priya Nair | M57: Phone | N57: 5
A58: TKT-02963 | B58: CLI-0279 | C58: DevOps Accelerator | D58: Access Permission Issue | E58: High | F58: 45118 | I58: 8 | J58: Yes | K58: Open | L58: Kavya Iyer | M58: Phone
A59: TKT-00253 | B59: CLI-0097 | C59: CloudShift Platform | D59: Dashboard Bug | E59: High | F59: 45035 | G59: 45035 | H59: 12.5 | I59: 8 | J59: No | K59: Resolved | L59: Manish Nair | M59: Email | N59: 5
A60: TKT-03096 | B60: CLI-0198 | C60: AnalyticsEdge | D60: Feature Request | E60: Medium | F60: 45330 | I60: 24 | J60: Yes | K60: In Progress | L60: Unassigned | M60: Email
A61: TKT-03957 | B61: CLI-0230 | C61: CloudShift Platform | D61: Security Alert | E61: Medium | F61: 45225 | G61: 45226 | H61: 41.2 | I61: 24 | J61: No | K61: Resolved | L61: Manish Nair | M61: Email
A62: TKT-01175 | B62: CLI-0097 | C62: AI Insights Module | D62: Feature Request | E62: Medium | F62: 45409 | G62: 45410 | H62: 27.4 | I62: 24 | J62: No | K62: Resolved | L62: Deepika Mishra | M62: Chat | N62: 5
A63: TKT-02787 | B63: CLI-0280 | C63: DevOps Accelerator | D63: Onboarding Support | E63: Low | F63: 45549 | I63: 48 | J63: No | K63: In Progress | L63: Priya Patel | M63: Portal
A64: TKT-02896 | B64: CLI-0143 | C64: AnalyticsEdge | D64: Server Downtime | E64: Medium | F64: 45403 | I64: 24 | J64: No | K64: Open | L64: Arjun Mishra | M64: Phone
A65: TKT-01696 | B65: CLI-0272 | C65: CloudShift Platform | D65: Report Inaccuracy | E65: Critical | F65: 45681 | I65: 4 | J65: No | K65: Open | L65: Divya Verma | M65: Email
A66: TKT-02414 | B66: CLI-0002 | C66: DevOps Accelerator | D66: Report Inaccuracy | E66: Low | F66: 45231 | I66: 48 | J66: No | K66: In Progress | L66: Priya Patel | M66: Portal
A67: TKT-01537 | B67: CLI-0106 | C67: DataVault Pro | D67: Access Permission Issue | E67: High | F67: 45052 | G67: 45052 | H67: 9.7 | I67: 8 | J67: No | K67: Resolved | L67: Divya Reddy | M67: Email | N67: 5
A68: TKT-03857 | B68: CLI-0047 | C68: DevOps Accelerator | D68: Onboarding Support | E68: High | F68: 45412 | G68: 45412 | H68: 3.8 | I68: 8 | J68: Yes | K68: Resolved | L68: Ananya Joshi | M68: Phone | N68: 3
A69: TKT-02796 | B69: CLI-0079 | C69: CloudShift Platform | D69: Data Sync Error | E69: Medium | F69: 45680 | G69: 45680 | H69: 19.1 | I69: 24 | J69: Yes | K69: Resolved | L69: Karan Gupta | M69: Email | N69: 2
A70: TKT-02458 | B70: CLI-0042 | C70: DataVault Pro | D70: Access Permission Issue | E70: Low | F70: 45127 | G70: 45127 | H70: 22.6 | I70: 48 | J70: Yes | K70: Resolved | L70: Divya Reddy | M70: Email | N70: 3
A71: TKT-00276 | B71: CLI-0241 | C71: AnalyticsEdge | D71: Billing Query | E71: High | F71: 45528 | I71: 8 | J71: No | K71: In Progress | L71: Neha Gupta | M71: Email
A72: TKT-03056 | B72: CLI-0064 | C72: CloudShift Platform | D72: Server Downtime | E72: Low | F72: 45734 | G72: 45736 | H72: 64.1 | I72: 48 | J72: No | K72: Resolved | L72: Rahul Das | M72: Portal
A73: TKT-03271 | B73: CLI-0028 | C73: CloudShift Platform | D73: Feature Request | E73: Medium | F73: 45379 | I73: 24 | J73: No | K73: Open | L73: Kavya Iyer | M73: Portal
A74: TKT-02121 | B74: CLI-0041 | C74: DevOps Accelerator | D74: Report Inaccuracy | E74: Medium | F74: 45035 | I74: 24 | J74: Yes | K74: In Progress | L74: Deepika Mishra | M74: Phone
A75: TKT-00076 | B75: CLI-0182 | C75: AI Insights Module | D75: Billing Query | E75: Medium | F75: 44966 | I75: 24 | J75: Yes | K75: In Progress | L75: Rahul Das | M75: Phone
A76: TKT-00203 | B76: CLI-0120 | C76: AnalyticsEdge | D76: Onboarding Support | E76: High | F76: 45174 | G76: 45174 | H76: 8.6 | I76: 8 | J76: Unknown | K76: Resolved | L76: Nikhil Mehta | M76: Phone | N76: 4
A77: TKT-02610 | B77: CLI-0270 | C77: AI Insights Module | D77: Onboarding Support | E77: Medium | F77: 45269 | G77: 45269 | H77: 16.5 | I77: 24 | J77: Yes | K77: Resolved | L77: Rahul Das | M77: Portal | N77: 2
A78: TKT-01336 | B78: CLI-0005 | C78: DataVault Pro | D78: Server Downtime | E78: High | F78: 45016 | I78: 8 | J78: Yes | K78: Open | L78: Pooja Gupta | M78: Email
A79: TKT-00752 | B79: CLI-0090 | C79: CloudShift Platform | D79: Dashboard Bug | E79: Medium | F79: 45501 | G79: 45502 | H79: 31 | I79: 24 | J79: No | K79: Resolved | L79: Nikhil Mehta | M79: Chat | N79: 4
A80: TKT-00441 | B80: CLI-0208 | C80: CloudShift Platform | D80: Server Downtime | E80: High | F80: 45703 | G80: 45703 | H80: 3 | I80: 8 | J80: Yes | K80: Resolved | L80: Pooja Patel | M80: Chat | N80: 4
A81: TKT-02567 | B81: CLI-0114 | C81: DataVault Pro | D81: API Integration Failure | E81: Medium | F81: 45170 | I81: 24 | J81: No | K81: In Progress | L81: Priya Nair | M81: Chat
A82: TKT-02982 | B82: CLI-0074 | C82: DevOps Accelerator | D82: Login Issue | E82: High | F82: 45123 | G82: 45123 | H82: 2.4 | I82: 8 | J82: Yes | K82: Resolved | L82: Kavya Iyer | M82: Email
A83: TKT-03650 | B83: CLI-0027 | C83: SecureNet Suite | D83: Onboarding Support | E83: Medium | F83: 45568 | G83: 45568 | H83: 5.1 | I83: 24 | J83: Yes | K83: Resolved | L83: Siddharth Reddy | M83: Email | N83: 5
A84: TKT-00929 | B84: CLI-0117 | C84: SecureNet Suite | D84: Login Issue | E84: High | F84: 45294 | I84: 8 | J84: No | K84: Escalated | L84: Pooja Patel | M84: Chat
A85: TKT-01508 | B85: CLI-0139 | C85: DataVault Pro | D85: Security Alert | E85: Low | F85: 45235 | G85: 45236 | H85: 37.9 | I85: 48 | J85: Unknown | K85: Resolved | L85: Priya Nair | M85: Phone
A86: TKT-02182 | B86: CLI-0184 | C86: SecureNet Suite | D86: Access Permission Issue | E86: Medium | F86: 45370 | G86: 45371 | H86: 33.3 | I86: 24 | J86: No | K86: Resolved | L86: Siddharth Reddy | M86: Email
A87: TKT-02062 | B87: CLI-0038 | C87: CloudShift Platform | D87: Data Sync Error | E87: Low | F87: 44987 | I87: 48 | J87: Yes | K87: Open | L87: Deepika Mishra | M87: Email
A88: TKT-00874 | B88: CLI-0162 | C88: CloudShift Platform | D88: Performance Lag | E88: Medium | F88: 45046 | G88: 45046 | H88: 2.7 | I88: 24 | J88: Yes | K88: Resolved | L88: Rahul Das | M88: Phone | N88: 3
A89: TKT-03430 | B89: CLI-0091 | C89: CloudShift Platform | D89: Access Permission Issue | E89: Medium | F89: 45647 | G89: 45648 | H89: 25.5 | I89: 24 | J89: Unknown | K89: Resolved | L89: Priya Patel | M89: Chat | N89: 3
A90: TKT-03132 | B90: CLI-0273 | C90: SecureNet Suite | D90: Billing Query | E90: Medium | F90: 45540 | G90: 45540 | H90: 12.3 | I90: 24 | J90: Yes | K90: Resolved | L90: Unassigned | M90: Chat
A91: TKT-01208 | B91: CLI-0154 | C91: CloudShift Platform | D91: Feature Request | E91: High | F91: 45625 | G91: 45625 | H91: 9.2 | I91: 8 | J91: No | K91: Resolved | L91: Karan Rao | M91: Chat | N91: 3
A92: TKT-03384 | B92: CLI-0132 | C92: DevOps Accelerator | D92: Billing Query | E92: Medium | F92: 45721 | I92: 24 | J92: No | K92: Escalated | L92: Arjun Mishra | M92: Phone
A93: TKT-00614 | B93: CLI-0072 | C93: DataVault Pro | D93: API Integration Failure | E93: Medium | F93: 45424 | I93: 24 | J93: Yes | K93: Open | L93: Deepika Mishra | M93: Phone
A94: TKT-01159 | B94: CLI-0218 | C94: DataVault Pro | D94: Server Downtime | E94: High | F94: 45255 | G94: 45255 | H94: 5 | I94: 8 | J94: Yes | K94: Resolved | L94: Siddharth Reddy | M94: Chat
A95: TKT-00467 | B95: CLI-0001 | C95: SecureNet Suite | D95: Billing Query | E95: Low | F95: 45249 | I95: 48 | J95: Yes | K95: Open | L95: Pooja Iyer | M95: Phone
A96: TKT-02005 | B96: CLI-0204 | C96: SecureNet Suite | D96: Report Inaccuracy | E96: Low | F96: 45214 | I96: 48 | J96: Yes | K96: Open | L96: Priya Patel | M96: Chat
A97: TKT-00202 | B97: CLI-0093 | C97: SecureNet Suite | D97: Performance Lag | E97: Low | F97: 45709 | I97: 48 | J97: No | K97: In Progress | L97: Rahul Das | M97: Portal
A98: TKT-02224 | B98: CLI-0191 | C98: AnalyticsEdge | D98: Onboarding Support | E98: Critical | F98: 45506 | I98: 4 | J98: Yes | K98: Escalated | L98: Divya Verma | M98: Phone
A99: TKT-00479 | B99: CLI-0040 | C99: CloudShift Platform | D99: Billing Query | E99: High | F99: 45220 | G99: 45220 | H99: 19.1 | I99: 8 | J99: No | K99: Resolved | L99: Priya Nair | M99: Portal | N99: 4
A100: TKT-02827 | B100: CLI-0069 | C100: DataVault Pro | D100: Access Permission Issue | E100: Critical | F100: 45205 | I100: 4 | J100: Yes | K100: Escalated | L100: Rahul Das | M100: Email
...

Sheet Q34_Win_Rate
A1: H1 - Digital vs Offline Lead Source: Win Rate(Chi-Square Test)
A2: H0: Win rate is independent of channel type (digital vs offline).
A3: H1: Win rate differs by channel type.
A5: Digital = Google Ads, LinkedIn Campaign, Email Campaign.
A6: Offline = Referral, Trade Show, Cold Outreach.
A7: (Organic Search, Webinar, Unknown excluded — not named in either group by the brief.)
A9: Observed Contigency Table
A10: Channel | B10: Closed Won | C10: Closed Lost | D10: Total
A11: Digital | B11: =COUNTIFS(Sales_Deals!$E$2:$E$2501,"Google Ads",Sales_Deals!$F$2:$F$2501,"Closed Won")+COUNTIFS(Sales_Deals!$E$2:$E$2501,"LinkedIn Campaign",Sales_Deals!$F$2:$F$2501,"Closed Won")+COUNTIFS(Sales_Deals!$E$2:$E$2501,"Email Campaign",Sales_Deals!$F$2:$F$2501,"Closed Won") -> 224 | C11: =COUNTIFS(Sales_Deals!$E$2:$E$2501,"Google Ads",Sales_Deals!$F$2:$F$2501,"Closed Lost")+COUNTIFS(Sales_Deals!$E$2:$E$2501,"LinkedIn Campaign",Sales_Deals!$F$2:$F$2501,"Closed Lost")+COUNTIFS(Sales_Deals!$E$2:$E$2501,"Email Campaign",Sales_Deals!$F$2:$F$2501,"Closed Lost") -> 129 | D11: =B11+C11 -> 353
A12: Offline | B12: =COUNTIFS(Sales_Deals!$E$2:$E$2501,"Referral",Sales_Deals!$F$2:$F$2501,"Closed Won")+COUNTIFS(Sales_Deals!$E$2:$E$2501,"Trade Show",Sales_Deals!$F$2:$F$2501,"Closed Won")+COUNTIFS(Sales_Deals!$E$2:$E$2501,"Cold Outreach",Sales_Deals!$F$2:$F$2501,"Closed Won") -> 245 | C12: =COUNTIFS(Sales_Deals!$E$2:$E$2501,"Referral",Sales_Deals!$F$2:$F$2501,"Closed Lost")+COUNTIFS(Sales_Deals!$E$2:$E$2501,"Trade Show",Sales_Deals!$F$2:$F$2501,"Closed Lost")+COUNTIFS(Sales_Deals!$E$2:$E$2501,"Cold Outreach",Sales_Deals!$F$2:$F$2501,"Closed Lost") -> 137 | D12: =B12+C12 -> 382
A13: Total | B13: =B11+B12 -> 469 | C13: =C11+C12 -> 266 | D13: =D11+D12 -> 735
A15: Expected Counts (if independent)
A16: Channel | B16: Closed Won | C16: Closed lost
A17: Digital | B17: =$D11*B$13/$D$13 -> 225.24762 | C17: =$D11*C$13/$D$13 -> 127.75238
A18: Offline | B18: =$D12*B$13/$D$13 -> 243.75238 | C18: =$D12*C$13/$D$13 -> 138.24762
A20: Test Results
A21: Chi-Square Statistic | B21: =SUM((B11-B17)^2/B17,(C11-C17)^2/C17,(B12-B18)^2/B18,(C12-C18)^2/C18) -> 0.036739519
A22: Degrees of Freedom | B22: =(COUNTA(A11:A12)-1)*(COUNTA(Table6[[#Headers],[Closed Won]:[Closed Lost]])-1) -> 1
A23: p-Value | B23: =_xlfn.CHISQ.DIST.RT(B21,B22) -> 0.84799635
A24: Digital win rate | B24: =B11/D11 -> 0.63456091
A25: Offline will rate | B25: =B12/D12 -> 0.64136126
A27: Conclusion (Alpha=0.05) | B27: =IF(B23<0.05,"Reject H0 - Significant difference in win rates","Fail to reject H0 - No significant difference in win rates") -> Fail to reject H0 - No significant difference in win rates

Sheet Q35_Closure_Time
A1: H2 — Deal Closure Time:
A2: Recent 6 Months vs Previous 6 Months (T-Test)
A4: H0: Mean days-to-close is the same in both periods.
A5: H1: Mean days-to-close has increased in the recent period.
A7: Periods defined by Close_Date, relative to the dataset’s latest full quarter-end (2025-03-31). Recent = 2024-10-01 to 2025-03-31. Previous = 2024-04-01 to 2024-09-30.
A9: Helper columns (Days_to_Close pulled into each period; blank if the deal falls outside it)
A10: Row No. | B10: Recent_6 _Months | C10: Previous_6_Months | I10: Periods by Close_Date: Recent = 2024-10-01 to 2025-03-31. Previous = 2024-04-01 to 2024-09-30.
A11: 1 | B11: =IF(Sales_Deals!I2<>"",IF(AND(Sales_Deals!I2>DATE(2024,9,30),Sales_Deals!I2<=DATE(2025,3,31)),Sales_Deals!J2,""),"") | C11: =IF(Sales_Deals!I2<>"",IF(AND(Sales_Deals!I2>DATE(2024,3,31),Sales_Deals!I2<=DATE(2024,9,30)),Sales_Deals!J2,""),"") -> 143 | I11: Months | J11: n | K11: Mean | L11: Std Dev
A12: 2 | B12: =IF(Sales_Deals!I3<>"",IF(AND(Sales_Deals!I3>DATE(2024,9,30),Sales_Deals!I3<=DATE(2025,3,31)),Sales_Deals!J3,""),"") | C12: =IF(Sales_Deals!I3<>"",IF(AND(Sales_Deals!I3>DATE(2024,3,31),Sales_Deals!I3<=DATE(2024,9,30)),Sales_Deals!J3,""),"") | I12: Recent 6 Months | J12: =COUNT(B11:B2510) -> 205 | K12: =AVERAGE(B11:B2510) -> 100.57561 | L12: =STDEV(B11:B2510) -> 50.325805
A13: 3 | B13: =IF(Sales_Deals!I4<>"",IF(AND(Sales_Deals!I4>DATE(2024,9,30),Sales_Deals!I4<=DATE(2025,3,31)),Sales_Deals!J4,""),"") | C13: =IF(Sales_Deals!I4<>"",IF(AND(Sales_Deals!I4>DATE(2024,3,31),Sales_Deals!I4<=DATE(2024,9,30)),Sales_Deals!J4,""),"") | I13: Previous 6 Months | J13: =COUNT(C11:C2510) -> 221 | K13: =AVERAGE(C11:C2510) -> 97.289593 | L13: =STDEV(C11:C2510) -> 50.230083
A14: 4 | B14: =IF(Sales_Deals!I5<>"",IF(AND(Sales_Deals!I5>DATE(2024,9,30),Sales_Deals!I5<=DATE(2025,3,31)),Sales_Deals!J5,""),"") -> 60 | C14: =IF(Sales_Deals!I5<>"",IF(AND(Sales_Deals!I5>DATE(2024,3,31),Sales_Deals!I5<=DATE(2024,9,30)),Sales_Deals!J5,""),"")
A15: 5 | B15: =IF(Sales_Deals!I6<>"",IF(AND(Sales_Deals!I6>DATE(2024,9,30),Sales_Deals!I6<=DATE(2025,3,31)),Sales_Deals!J6,""),"") | C15: =IF(Sales_Deals!I6<>"",IF(AND(Sales_Deals!I6>DATE(2024,3,31),Sales_Deals!I6<=DATE(2024,9,30)),Sales_Deals!J6,""),"") -> 163
A16: 6 | B16: =IF(Sales_Deals!I7<>"",IF(AND(Sales_Deals!I7>DATE(2024,9,30),Sales_Deals!I7<=DATE(2025,3,31)),Sales_Deals!J7,""),"") | C16: =IF(Sales_Deals!I7<>"",IF(AND(Sales_Deals!I7>DATE(2024,3,31),Sales_Deals!I7<=DATE(2024,9,30)),Sales_Deals!J7,""),"") | I16: Test Results
A17: 7 | B17: =IF(Sales_Deals!I8<>"",IF(AND(Sales_Deals!I8>DATE(2024,9,30),Sales_Deals!I8<=DATE(2025,3,31)),Sales_Deals!J8,""),"") | C17: =IF(Sales_Deals!I8<>"",IF(AND(Sales_Deals!I8>DATE(2024,3,31),Sales_Deals!I8<=DATE(2024,9,30)),Sales_Deals!J8,""),"") | I17: Mean difference (Recent - Previous) | J17: =K12-K13 -> 3.286017
A18: 8 | B18: =IF(Sales_Deals!I9<>"",IF(AND(Sales_Deals!I9>DATE(2024,9,30),Sales_Deals!I9<=DATE(2025,3,31)),Sales_Deals!J9,""),"") | C18: =IF(Sales_Deals!I9<>"",IF(AND(Sales_Deals!I9>DATE(2024,3,31),Sales_Deals!I9<=DATE(2024,9,30)),Sales_Deals!J9,""),"") | I18: p-value (two-tailed) | J18: =TTEST(B11:B2510,C11:C2510,2,3) -> 0.50069562
A19: 9 | B19: =IF(Sales_Deals!I10<>"",IF(AND(Sales_Deals!I10>DATE(2024,9,30),Sales_Deals!I10<=DATE(2025,3,31)),Sales_Deals!J10,""),"") | C19: =IF(Sales_Deals!I10<>"",IF(AND(Sales_Deals!I10>DATE(2024,3,31),Sales_Deals!I10<=DATE(2024,9,30)),Sales_Deals!J10,""),"")
A20: 10 | B20: =IF(Sales_Deals!I11<>"",IF(AND(Sales_Deals!I11>DATE(2024,9,30),Sales_Deals!I11<=DATE(2025,3,31)),Sales_Deals!J11,""),"") | C20: =IF(Sales_Deals!I11<>"",IF(AND(Sales_Deals!I11>DATE(2024,3,31),Sales_Deals!I11<=DATE(2024,9,30)),Sales_Deals!J11,""),"") -> 58 | I20: Conclusion | J20: =IF(J18<0.05,"Reject H0 - closure time has changed","Fail to reject H0 - no significant change") -> Fail to reject H0 - no significant change
A21: 11 | B21: =IF(Sales_Deals!I12<>"",IF(AND(Sales_Deals!I12>DATE(2024,9,30),Sales_Deals!I12<=DATE(2025,3,31)),Sales_Deals!J12,""),"") | C21: =IF(Sales_Deals!I12<>"",IF(AND(Sales_Deals!I12>DATE(2024,3,31),Sales_Deals!I12<=DATE(2024,9,30)),Sales_Deals!J12,""),"") -> 117
A22: 12 | B22: =IF(Sales_Deals!I13<>"",IF(AND(Sales_Deals!I13>DATE(2024,9,30),Sales_Deals!I13<=DATE(2025,3,31)),Sales_Deals!J13,""),"") | C22: =IF(Sales_Deals!I13<>"",IF(AND(Sales_Deals!I13>DATE(2024,3,31),Sales_Deals!I13<=DATE(2024,9,30)),Sales_Deals!J13,""),"")
A23: 13 | B23: =IF(Sales_Deals!I14<>"",IF(AND(Sales_Deals!I14>DATE(2024,9,30),Sales_Deals!I14<=DATE(2025,3,31)),Sales_Deals!J14,""),"") | C23: =IF(Sales_Deals!I14<>"",IF(AND(Sales_Deals!I14>DATE(2024,3,31),Sales_Deals!I14<=DATE(2024,9,30)),Sales_Deals!J14,""),"") -> 151
A24: 14 | B24: =IF(Sales_Deals!I15<>"",IF(AND(Sales_Deals!I15>DATE(2024,9,30),Sales_Deals!I15<=DATE(2025,3,31)),Sales_Deals!J15,""),"") | C24: =IF(Sales_Deals!I15<>"",IF(AND(Sales_Deals!I15>DATE(2024,3,31),Sales_Deals!I15<=DATE(2024,9,30)),Sales_Deals!J15,""),"")
A25: 15 | B25: =IF(Sales_Deals!I16<>"",IF(AND(Sales_Deals!I16>DATE(2024,9,30),Sales_Deals!I16<=DATE(2025,3,31)),Sales_Deals!J16,""),"") | C25: =IF(Sales_Deals!I16<>"",IF(AND(Sales_Deals!I16>DATE(2024,3,31),Sales_Deals!I16<=DATE(2024,9,30)),Sales_Deals!J16,""),"")
A26: 16 | B26: =IF(Sales_Deals!I17<>"",IF(AND(Sales_Deals!I17>DATE(2024,9,30),Sales_Deals!I17<=DATE(2025,3,31)),Sales_Deals!J17,""),"") | C26: =IF(Sales_Deals!I17<>"",IF(AND(Sales_Deals!I17>DATE(2024,3,31),Sales_Deals!I17<=DATE(2024,9,30)),Sales_Deals!J17,""),"")
A27: 17 | B27: =IF(Sales_Deals!I18<>"",IF(AND(Sales_Deals!I18>DATE(2024,9,30),Sales_Deals!I18<=DATE(2025,3,31)),Sales_Deals!J18,""),"") | C27: =IF(Sales_Deals!I18<>"",IF(AND(Sales_Deals!I18>DATE(2024,3,31),Sales_Deals!I18<=DATE(2024,9,30)),Sales_Deals!J18,""),"") -> 115
A28: 18 | B28: =IF(Sales_Deals!I19<>"",IF(AND(Sales_Deals!I19>DATE(2024,9,30),Sales_Deals!I19<=DATE(2025,3,31)),Sales_Deals!J19,""),"") | C28: =IF(Sales_Deals!I19<>"",IF(AND(Sales_Deals!I19>DATE(2024,3,31),Sales_Deals!I19<=DATE(2024,9,30)),Sales_Deals!J19,""),"")
A29: 19 | B29: =IF(Sales_Deals!I20<>"",IF(AND(Sales_Deals!I20>DATE(2024,9,30),Sales_Deals!I20<=DATE(2025,3,31)),Sales_Deals!J20,""),"") | C29: =IF(Sales_Deals!I20<>"",IF(AND(Sales_Deals!I20>DATE(2024,3,31),Sales_Deals!I20<=DATE(2024,9,30)),Sales_Deals!J20,""),"") -> 150
A30: 20 | B30: =IF(Sales_Deals!I21<>"",IF(AND(Sales_Deals!I21>DATE(2024,9,30),Sales_Deals!I21<=DATE(2025,3,31)),Sales_Deals!J21,""),"") | C30: =IF(Sales_Deals!I21<>"",IF(AND(Sales_Deals!I21>DATE(2024,3,31),Sales_Deals!I21<=DATE(2024,9,30)),Sales_Deals!J21,""),"")
A31: 21 | B31: =IF(Sales_Deals!I22<>"",IF(AND(Sales_Deals!I22>DATE(2024,9,30),Sales_Deals!I22<=DATE(2025,3,31)),Sales_Deals!J22,""),"") | C31: =IF(Sales_Deals!I22<>"",IF(AND(Sales_Deals!I22>DATE(2024,3,31),Sales_Deals!I22<=DATE(2024,9,30)),Sales_Deals!J22,""),"")
A32: 22 | B32: =IF(Sales_Deals!I23<>"",IF(AND(Sales_Deals!I23>DATE(2024,9,30),Sales_Deals!I23<=DATE(2025,3,31)),Sales_Deals!J23,""),"") | C32: =IF(Sales_Deals!I23<>"",IF(AND(Sales_Deals!I23>DATE(2024,3,31),Sales_Deals!I23<=DATE(2024,9,30)),Sales_Deals!J23,""),"")
... A2510: 2500 | B2510: =IF(Sales_Deals!I2501<>"",IF(AND(Sales_Deals!I2501>DATE(2024,9,30),Sales_Deals!I2501<=DATE(2025,3,31)),Sales_Deals!J2501,""),"") | C2510: =IF(Sales_Deals!I2501<>"",IF(AND(Sales_Deals!I2501>DATE(2024,3,31),Sales_Deals!I2501<=DATE(2024,9,30)),Sales_Deals!J2501,""),"")

Sheet Q36_Correlation
A1: H3 — Client Satisfaction Score vs. SLA Breach Count (Correlation)
A3: H0: No linear relationship between satisfaction score and SLA breach count.
A4: H1: A significant correlation exists.
A6: Aggregated to one row per client. Breach Count = number of that client’s support tickets where SLA_Met = "No".
A8: Client_ID | B8: Satisfaction_Score | C8: SLA_Breach_Count | G8: Test Results
A9: =Clients!A2 -> CLI-0113 | B9: =IF(Clients!H2="","",Clients!H2) -> 3.2 | C9: =COUNTIFS(Support_Tickets!$B$2:$B$4001,A9,Support_Tickets!$J$2:$J$4001,"No") -> 10 | G9: n (Clients with a satisfaction score) | H9: =COUNT(B9:B308) -> 286
A10: =Clients!A3 -> CLI-0047 | B10: =IF(Clients!H3="","",Clients!H3) -> 3.1 | C10: =COUNTIFS(Support_Tickets!$B$2:$B$4001,A10,Support_Tickets!$J$2:$J$4001,"No") -> 10 | G10: Pearson r | H10: =PEARSON(B9:B308,C9:C308) -> 0.046973468
A11: =Clients!A4 -> CLI-0083 | B11: =IF(Clients!H4="","",Clients!H4) -> 4.4 | C11: =COUNTIFS(Support_Tickets!$B$2:$B$4001,A11,Support_Tickets!$J$2:$J$4001,"No") -> 4 | G11: t-statistic | H11: =H10*SQRT(H9-2)/SQRT(1-H10^2) -> 0.79248575
A12: =Clients!A5 -> CLI-0111 | B12: =IF(Clients!H5="","",Clients!H5) -> 4.9 | C12: =COUNTIFS(Support_Tickets!$B$2:$B$4001,A12,Support_Tickets!$J$2:$J$4001,"No") -> 9 | G12: Degrees of freedom | H12: =H9-2 -> 284
A13: =Clients!A6 -> CLI-0199 | B13: =IF(Clients!H6="","",Clients!H6) -> 4.3 | C13: =COUNTIFS(Support_Tickets!$B$2:$B$4001,A13,Support_Tickets!$J$2:$J$4001,"No") -> 6 | G13: p-value | H13: =TDIST(ABS(H11),H12,2) -> 0.42873898
A14: =Clients!A7 -> CLI-0213 | B14: =IF(Clients!H7="","",Clients!H7) -> 3.8 | C14: =COUNTIFS(Support_Tickets!$B$2:$B$4001,A14,Support_Tickets!$J$2:$J$4001,"No") -> 8
A15: =Clients!A8 -> CLI-0042 | B15: =IF(Clients!H8="","",Clients!H8) -> 3.4 | C15: =COUNTIFS(Support_Tickets!$B$2:$B$4001,A15,Support_Tickets!$J$2:$J$4001,"No") -> 7 | G15: Conclusion | H15: =IF(H13<0.05,"Reject H0 - significant correlation found","Fail to reject H0 - no significant correlation") -> Fail to reject H0 - no significant correlation
A16: =Clients!A9 -> CLI-0217 | B16: =IF(Clients!H9="","",Clients!H9) -> 4.3 | C16: =COUNTIFS(Support_Tickets!$B$2:$B$4001,A16,Support_Tickets!$J$2:$J$4001,"No") -> 7
A17: =Clients!A10 -> CLI-0070 | B17: =IF(Clients!H10="","",Clients!H10) -> 2.8 | C17: =COUNTIFS(Support_Tickets!$B$2:$B$4001,A17,Support_Tickets!$J$2:$J$4001,"No") -> 5
A18: =Clients!A11 -> CLI-0115 | B18: =IF(Clients!H11="","",Clients!H11) -> 4.3 | C18: =COUNTIFS(Support_Tickets!$B$2:$B$4001,A18,Support_Tickets!$J$2:$J$4001,"No") -> 8
A19: =Clients!A12 -> CLI-0264 | B19: =IF(Clients!H12="","",Clients!H12) -> 2.6 | C19: =COUNTIFS(Support_Tickets!$B$2:$B$4001,A19,Support_Tickets!$J$2:$J$4001,"No") -> 6
A20: =Clients!A13 -> CLI-0219 | B20: =IF(Clients!H13="","",Clients!H13) -> 3.2 | C20: =COUNTIFS(Support_Tickets!$B$2:$B$4001,A20,Support_Tickets!$J$2:$J$4001,"No") -> 8
A21: =Clients!A14 -> CLI-0269 | B21: =IF(Clients!H14="","",Clients!H14) -> 4.8 | C21: =COUNTIFS(Support_Tickets!$B$2:$B$4001,A21,Support_Tickets!$J$2:$J$4001,"No") -> 4
A22: =Clients!A15 -> CLI-0152 | B22: =IF(Clients!H15="","",Clients!H15) -> 4 | C22: =COUNTIFS(Support_Tickets!$B$2:$B$4001,A22,Support_Tickets!$J$2:$J$4001,"No") -> 4
A23: =Clients!A16 -> CLI-0150 | B23: =IF(Clients!H16="","",Clients!H16) -> 4.9 | C23: =COUNTIFS(Support_Tickets!$B$2:$B$4001,A23,Support_Tickets!$J$2:$J$4001,"No") -> 9
A24: =Clients!A17 -> CLI-0078 | B24: =IF(Clients!H17="","",Clients!H17) -> 2.7 | C24: =COUNTIFS(Support_Tickets!$B$2:$B$4001,A24,Support_Tickets!$J$2:$J$4001,"No") -> 9
A25: =Clients!A18 -> CLI-0297 | B25: =IF(Clients!H18="","",Clients!H18) -> 3.9 | C25: =COUNTIFS(Support_Tickets!$B$2:$B$4001,A25,Support_Tickets!$J$2:$J$4001,"No") -> 14
A26: =Clients!A19 -> CLI-0107 | B26: =IF(Clients!H19="","",Clients!H19) -> 3.7 | C26: =COUNTIFS(Support_Tickets!$B$2:$B$4001,A26,Support_Tickets!$J$2:$J$4001,"No") -> 9
A27: =Clients!A20 -> CLI-0195 | B27: =IF(Clients!H20="","",Clients!H20) -> 2.9 | C27: =COUNTIFS(Support_Tickets!$B$2:$B$4001,A27,Support_Tickets!$J$2:$J$4001,"No") -> 7
... A308: =Clients!A301 -> CLI-0030 | B308: =IF(Clients!H301="","",Clients!H301) -> 3.8 | C308: =COUNTIFS(Support_Tickets!$B$2:$B$4001,A308,Support_Tickets!$J$2:$J$4001,"No") -> 4

Sheet Q37_Trend_Analysis
A1: H4 — Quarterly Marketing Spend vs. Conversion Rate (Trend Analysis)
A3: H0: No linear trend over time.
A4: H1: Spend has increased while conversion rate has not.
A6: Quarter | B6: Period_Index | C6: Total_Spend (INR) | D6: Total_MQLs | E6: Total_Conversions | F6: Conversion_Rate
A7: 2023Q1 | B7: 1 | C7: =SUMIFS(Marketing_Campaigns!$G$2:$G$151,Marketing_Campaigns!$E$2:$E$151,">="&DATE(2023,1,1),Marketing_Campaigns!$E$2:$E$151,"<"&DATE(2023,4,1)) -> 13751382 | D7: =SUMIFS(Marketing_Campaigns!$J$2:$J$151,Marketing_Campaigns!$E$2:$E$151,">="&DATE(2023,1,1),Marketing_Campaigns!$E$2:$E$151,"<"&DATE(2023,4,1)) -> 36025 | E7: =SUMIFS(Marketing_Campaigns!$L$2:$L$151,Marketing_Campaigns!$E$2:$E$151,">="&DATE(2023,1,1),Marketing_Campaigns!$E$2:$E$151,"<"&DATE(2023,4,1)) -> 3371 | F7: =E7/D7 -> 0.093573907
A8: 2023Q2 | B8: 2 | C8: =SUMIFS(Marketing_Campaigns!$G$2:$G$151,Marketing_Campaigns!$E$2:$E$151,">="&DATE(2023,4,1),Marketing_Campaigns!$E$2:$E$151,"<"&DATE(2023,7,1)) -> 8650941 | D8: =SUMIFS(Marketing_Campaigns!$J$2:$J$151,Marketing_Campaigns!$E$2:$E$151,">="&DATE(2023,4,1),Marketing_Campaigns!$E$2:$E$151,"<"&DATE(2023,7,1)) -> 14806 | E8: =SUMIFS(Marketing_Campaigns!$L$2:$L$151,Marketing_Campaigns!$E$2:$E$151,">="&DATE(2023,4,1),Marketing_Campaigns!$E$2:$E$151,"<"&DATE(2023,7,1)) -> 1266 | F8: =E8/D8 -> 0.085505876
A9: 2023Q3 | B9: 3 | C9: =SUMIFS(Marketing_Campaigns!$G$2:$G$151,Marketing_Campaigns!$E$2:$E$151,">="&DATE(2023,7,1),Marketing_Campaigns!$E$2:$E$151,"<"&DATE(2023,10,1)) -> 10702434 | D9: =SUMIFS(Marketing_Campaigns!$J$2:$J$151,Marketing_Campaigns!$E$2:$E$151,">="&DATE(2023,7,1),Marketing_Campaigns!$E$2:$E$151,"<"&DATE(2023,10,1)) -> 21615 | E9: =SUMIFS(Marketing_Campaigns!$L$2:$L$151,Marketing_Campaigns!$E$2:$E$151,">="&DATE(2023,7,1),Marketing_Campaigns!$E$2:$E$151,"<"&DATE(2023,10,1)) -> 2255 | F9: =E9/D9 -> 0.1043257
A10: 2023Q4 | B10: 4 | C10: =SUMIFS(Marketing_Campaigns!$G$2:$G$151,Marketing_Campaigns!$E$2:$E$151,">="&DATE(2023,10,1),Marketing_Campaigns!$E$2:$E$151,"<"&DATE(2024,1,1)) -> 16358958 | D10: =SUMIFS(Marketing_Campaigns!$J$2:$J$151,Marketing_Campaigns!$E$2:$E$151,">="&DATE(2023,10,1),Marketing_Campaigns!$E$2:$E$151,"<"&DATE(2024,1,1)) -> 31737 | E10: =SUMIFS(Marketing_Campaigns!$L$2:$L$151,Marketing_Campaigns!$E$2:$E$151,">="&DATE(2023,10,1),Marketing_Campaigns!$E$2:$E$151,"<"&DATE(2024,1,1)) -> 2752 | F10: =E10/D10 -> 0.08671267
A11: 2024Q1 | B11: 5 | C11: =SUMIFS(Marketing_Campaigns!$G$2:$G$151,Marketing_Campaigns!$E$2:$E$151,">="&DATE(2024,1,1),Marketing_Campaigns!$E$2:$E$151,"<"&DATE(2024,4,1)) -> 17568102 | D11: =SUMIFS(Marketing_Campaigns!$J$2:$J$151,Marketing_Campaigns!$E$2:$E$151,">="&DATE(2024,1,1),Marketing_Campaigns!$E$2:$E$151,"<"&DATE(2024,4,1)) -> 35424 | E11: =SUMIFS(Marketing_Campaigns!$L$2:$L$151,Marketing_Campaigns!$E$2:$E$151,">="&DATE(2024,1,1),Marketing_Campaigns!$E$2:$E$151,"<"&DATE(2024,4,1)) -> 2801 | F11: =E11/D11 -> 0.079070687
A12: 2024Q2 | B12: 6 | C12: =SUMIFS(Marketing_Campaigns!$G$2:$G$151,Marketing_Campaigns!$E$2:$E$151,">="&DATE(2024,4,1),Marketing_Campaigns!$E$2:$E$151,"<"&DATE(2024,7,1)) -> 12762706 | D12: =SUMIFS(Marketing_Campaigns!$J$2:$J$151,Marketing_Campaigns!$E$2:$E$151,">="&DATE(2024,4,1),Marketing_Campaigns!$E$2:$E$151,"<"&DATE(2024,7,1)) -> 35699 | E12: =SUMIFS(Marketing_Campaigns!$L$2:$L$151,Marketing_Campaigns!$E$2:$E$151,">="&DATE(2024,4,1),Marketing_Campaigns!$E$2:$E$151,"<"&DATE(2024,7,1)) -> 2970 | F12: =E12/D12 -> 0.083195608
A13: 2024Q3 | B13: 7 | C13: =SUMIFS(Marketing_Campaigns!$G$2:$G$151,Marketing_Campaigns!$E$2:$E$151,">="&DATE(2024,7,1),Marketing_Campaigns!$E$2:$E$151,"<"&DATE(2024,10,1)) -> 22057177 | D13: =SUMIFS(Marketing_Campaigns!$J$2:$J$151,Marketing_Campaigns!$E$2:$E$151,">="&DATE(2024,7,1),Marketing_Campaigns!$E$2:$E$151,"<"&DATE(2024,10,1)) -> 33435 | E13: =SUMIFS(Marketing_Campaigns!$L$2:$L$151,Marketing_Campaigns!$E$2:$E$151,">="&DATE(2024,7,1),Marketing_Campaigns!$E$2:$E$151,"<"&DATE(2024,10,1)) -> 2604 | F13: =E13/D13 -> 0.077882459
A14: 2024Q4 | B14: 8 | C14: =SUMIFS(Marketing_Campaigns!$G$2:$G$151,Marketing_Campaigns!$E$2:$E$151,">="&DATE(2024,10,1),Marketing_Campaigns!$E$2:$E$151,"<"&DATE(2025,1,1)) -> 11642560 | D14: =SUMIFS(Marketing_Campaigns!$J$2:$J$151,Marketing_Campaigns!$E$2:$E$151,">="&DATE(2024,10,1),Marketing_Campaigns!$E$2:$E$151,"<"&DATE(2025,1,1)) -> 34862 | E14: =SUMIFS(Marketing_Campaigns!$L$2:$L$151,Marketing_Campaigns!$E$2:$E$151,">="&DATE(2024,10,1),Marketing_Campaigns!$E$2:$E$151,"<"&DATE(2025,1,1)) -> 2896 | F14: =E14/D14 -> 0.083070392
A15: 2025Q1 | B15: 9 | C15: =SUMIFS(Marketing_Campaigns!$G$2:$G$151,Marketing_Campaigns!$E$2:$E$151,">="&DATE(2025,1,1),Marketing_Campaigns!$E$2:$E$151,"<"&DATE(2025,4,1)) -> 5756255 | D15: =SUMIFS(Marketing_Campaigns!$J$2:$J$151,Marketing_Campaigns!$E$2:$E$151,">="&DATE(2025,1,1),Marketing_Campaigns!$E$2:$E$151,"<"&DATE(2025,4,1)) -> 14737 | E15: =SUMIFS(Marketing_Campaigns!$L$2:$L$151,Marketing_Campaigns!$E$2:$E$151,">="&DATE(2025,1,1),Marketing_Campaigns!$E$2:$E$151,"<"&DATE(2025,4,1)) -> 1185 | F15: =E15/D15 -> 0.080409853
A17: Trend Test- Total Spend vs. Period Index
A18: Slope | B18: =SLOPE(C7:C15,B7:B15) -> -64873.617
A19: Correlation with time | B19: =CORREL(B7:B15,C7:C15) -> -0.036194986
A20: t-statistic | B20: =B19*SQRT(7)/SQRT(1-B19^2) -> -0.09582572
A21: p-value | B21: =TDIST(ABS(B20),7,2) -> 0.92634463
A23: Trend Test- Conversion Rate vs. Period Index
A24: Slope | B24: =SLOPE(F7:F15,B7:B15) -> -0.0019394369
A25: Correlation with time | B25: =CORREL(B7:B15,F7:F15) -> -0.63736884
A26: t-statistic | B26: =B25*SQRT(7)/SQRT(1-B25^2) -> -2.1884369
A27: p-value | B27: =TDIST(ABS(B26),7,2) -> 0.064828194
A29: Conclusion (alpha=0.05) | B29: =IF(AND(B21<0.05,B19>0,B27>=0.05),"Confirms H4 - spend rising, conversion rate flat","Does not confirm H4 as stated - see narrative") -> Does not confirm H4 as stated - see narrative

Sheet Q38_Descriptive_Stats
A1: 38- Descriptive Statistics
A3: Variable | B3: n | C3: Mean | D3: Median | E3: Std Dev | F3: Skewness
A4: Deal_Value_INR (Sales_Deals) | B4: =COUNT(Sales_Deals!G2:G2501) -> 2500 | C4: =AVERAGE(Sales_Deals!G2:G2501) -> 278456.13 | D4: =MEDIAN(Sales_Deals!G2:G2501) -> 262675.5 | E4: =STDEV(Sales_Deals!G2:G2501) -> 211155.77 | F4: =SKEW(Sales_Deals!G2:G2501) -> 3.4053572
A5: Resolution_Hours (Support_Tickets) | B5: =COUNT(Support_Tickets!H2:H4001 ) -> 2393 | C5: =AVERAGE(Support_Tickets!H2:H4001 ) -> 29.23715 | D5: =MEDIAN(Support_Tickets!H2:H4001 ) -> 18.3 | E5: =STDEV(Support_Tickets!H2:H4001) -> 27.82665 | F5: =SKEW(Support_Tickets!H2:H4001 ) -> 1.3106835
A6: Budget_INR (Marketing_Campaigns) | B6: =COUNT(Marketing_Campaigns!G2:G151) -> 150 | C6: =AVERAGE(Marketing_Campaigns!G2:G151) -> 795003.43 | D6: =MEDIAN(Marketing_Campaigns!G2:G151) -> 833091.5 | E6: =STDEV(Marketing_Campaigns!G2:G151) -> 411316.4 | F6: =SKEW(Marketing_Campaigns!G2:G151) -> -0.085725727
A8: Skewness reference: |skew| < 0.5 roughly symmetric; 0.5-1 moderately skewed; >1 highly skewed.

Sheet Q39_Distribution
A1: 39- Distribution Fit: Deal_Value_INR | Q1: LN(Deal_Value_INR) helper
Q2: =LN(Sales_Deals!G2) -> 11.984621
Q3: =LN(Sales_Deals!G3) -> 13.105238
A4: Skew of LN(Deal_Value_INR) | B4: =SKEW(Q2:Q2504) -> -1.0474035 | Q4: =LN(Sales_Deals!G4) -> 12.320222
A5: Kurtosis of LN(Deal_Value_INR) | B5: =KURT(Q2:Q2504) -> 1.3875692 | Q5: =LN(Sales_Deals!G5) -> 12.490292
Q6: =LN(Sales_Deals!G6) -> 12.449227
A8: Histogram- Deal_Value_INR (bin width ₹50,000)
A9: Bin Upper Bound | B9: Frequency
A10: 50000 | B10: =COUNTIFS(Sales_Deals!$G$2:$G$2501,">0",Sales_Deals!$G$2:$G$2501,"<="&A10) -> 182 | Q10: =LN(Sales_Deals!G7) -> 12.873679
A11: 100000 | B11: =COUNTIFS(Sales_Deals!$G$2:$G$2501,">"&A10,Sales_Deals!$G$2:$G$2501,"<="&A11) -> 244 | Q11: =LN(Sales_Deals!G8) -> 12.881687
A12: 150000 | B12: =COUNTIFS(Sales_Deals!$G$2:$G$2501,">"&A11,Sales_Deals!$G$2:$G$2501,"<="&A12) -> 256 | Q12: =LN(Sales_Deals!G9) -> 12.596431
A13: 200000 | B13: =COUNTIFS(Sales_Deals!$G$2:$G$2501,">"&A12,Sales_Deals!$G$2:$G$2501,"<="&A13) -> 227 | Q13: =LN(Sales_Deals!G10) -> 12.058263
A14: 250000 | B14: =COUNTIFS(Sales_Deals!$G$2:$G$2501,">"&A13,Sales_Deals!$G$2:$G$2501,"<="&A14) -> 284 | Q14: =LN(Sales_Deals!G11) -> 11.897439
A15: 300000 | B15: =COUNTIFS(Sales_Deals!$G$2:$G$2501,">"&A14,Sales_Deals!$G$2:$G$2501,"<="&A15) -> 241 | Q15: =LN(Sales_Deals!G12) -> 12.398592
A16: 350000 | B16: =COUNTIFS(Sales_Deals!$G$2:$G$2501,">"&A15,Sales_Deals!$G$2:$G$2501,"<="&A16) -> 281 | Q16: =LN(Sales_Deals!G13) -> 12.891271
A17: 400000 | B17: =COUNTIFS(Sales_Deals!$G$2:$G$2501,">"&A16,Sales_Deals!$G$2:$G$2501,"<="&A17) -> 247 | Q17: =LN(Sales_Deals!G14) -> 12.243311
A18: 450000 | B18: =COUNTIFS(Sales_Deals!$G$2:$G$2501,">"&A17,Sales_Deals!$G$2:$G$2501,"<="&A18) -> 232 | Q18: =LN(Sales_Deals!G15) -> 12.408144
A19: 500000 | B19: =COUNTIFS(Sales_Deals!$G$2:$G$2501,">"&A18,Sales_Deals!$G$2:$G$2501,"<="&A19) -> 259 | Q19: =LN(Sales_Deals!G16) -> 12.316361
A20: 550000 | B20: =COUNTIFS(Sales_Deals!$G$2:$G$2501,">"&A19,Sales_Deals!$G$2:$G$2501,"<="&A20) -> 0 | Q20: =LN(Sales_Deals!G17) -> 12.741082
A21: 600000 | B21: =COUNTIFS(Sales_Deals!$G$2:$G$2501,">"&A20,Sales_Deals!$G$2:$G$2501,"<="&A21) -> 0 | Q21: =LN(Sales_Deals!G18) -> 12.940523
A22: 650000 | B22: =COUNTIFS(Sales_Deals!$G$2:$G$2501,">"&A21,Sales_Deals!$G$2:$G$2501,"<="&A22) -> 0 | Q22: =LN(Sales_Deals!G19) -> 11.122694
... A33: 1200000 | B33: =COUNTIFS(Sales_Deals!$G$2:$G$2501,">"&A32,Sales_Deals!$G$2:$G$2501,"<="&A33) -> 1 | Q33: =LN(Sales_Deals!G30) -> 13.103158
Q34: =LN(Sales_Deals!G31) -> 12.495438
Q35: =LN(Sales_Deals!G32) -> 12.738749
Q36: =LN(Sales_Deals!G33) -> 12.976752
Q37: =LN(Sales_Deals!G34) -> 13.016643
Q38: =LN(Sales_Deals!G35) -> 12.693959
Q39: =LN(Sales_Deals!G36) -> 12.436569
Q40: =LN(Sales_Deals!G37) -> 12.41233
Q41: =LN(Sales_Deals!G38) -> 11.762002
Q42: =LN(Sales_Deals!G39) -> 11.964587
Q43: =LN(Sales_Deals!G40) -> 12.86858
Q44: =LN(Sales_Deals!G41) -> 12.491229
Q45: =LN(Sales_Deals!G42) -> 13.738431
... Q2504: =LN(Sales_Deals!G2501) -> 11.779795

Sheet  Q40_ANOVA
A1: 40- One- Way ANOVA: Deal Value Across Products
A2: H0: Mean deal value is the same across all products.
A3: H1: At least one product’s mean deal value differs.
A5: Group Statistics
A6: Product | B6: n | C6: Mean | D6: Std Dev
A7: AI Insights Module | B7: =COUNTIFS(Sales_Deals!$D$2:$D$2501,A7) -> 392 | C7: =AVERAGEIFS(Sales_Deals!$G$2:$G$2501,Sales_Deals!$D$2:$D$2501,A7) -> 267177.72 | D7: {=SQRT(SUMPRODUCT((Sales_Deals!$D$2:$D$2501=A7)*(Sales_Deals!$G$2:$G$2501-C7)^2)/(B7-1))} -> 183476.59
A8: AnalyticsEdge | B8: =COUNTIFS(Sales_Deals!$D$2:$D$2501,A8) -> 440 | C8: =AVERAGEIFS(Sales_Deals!$G$2:$G$2501,Sales_Deals!$D$2:$D$2501,A8) -> 286596.08 | D8: {=SQRT(SUMPRODUCT((Sales_Deals!$D$2:$D$2501=A8)*(Sales_Deals!$G$2:$G$2501-C8)^2)/(B8-1))} -> 226112.27
A9: CloudShift Platform | B9: =COUNTIFS(Sales_Deals!$D$2:$D$2501,A9) -> 402 | C9: =AVERAGEIFS(Sales_Deals!$G$2:$G$2501,Sales_Deals!$D$2:$D$2501,A9) -> 299067.05 | D9: {=SQRT(SUMPRODUCT((Sales_Deals!$D$2:$D$2501=A9)*(Sales_Deals!$G$2:$G$2501-C9)^2)/(B9-1))} -> 227259.98
A10: DataVault Pro | B10: =COUNTIFS(Sales_Deals!$D$2:$D$2501,A10) -> 431 | C10: =AVERAGEIFS(Sales_Deals!$G$2:$G$2501,Sales_Deals!$D$2:$D$2501,A10) -> 263633.78 | D10: {=SQRT(SUMPRODUCT((Sales_Deals!$D$2:$D$2501=A10)*(Sales_Deals!$G$2:$G$2501-C10)^2)/(B10-1))} -> 193525.9
A11: DevOps Accelerator | B11: =COUNTIFS(Sales_Deals!$D$2:$D$2501,A11) -> 409 | C11: =AVERAGEIFS(Sales_Deals!$G$2:$G$2501,Sales_Deals!$D$2:$D$2501,A11) -> 259443.58 | D11: {=SQRT(SUMPRODUCT((Sales_Deals!$D$2:$D$2501=A11)*(Sales_Deals!$G$2:$G$2501-C11)^2)/(B11-1))} -> 192844.28
A12: SecureNet Suite | B12: =COUNTIFS(Sales_Deals!$D$2:$D$2501,A12) -> 426 | C12: =AVERAGEIFS(Sales_Deals!$G$2:$G$2501,Sales_Deals!$D$2:$D$2501,A12) -> 294227.35 | D12: {=SQRT(SUMPRODUCT((Sales_Deals!$D$2:$D$2501=A12)*(Sales_Deals!$G$2:$G$2501-C12)^2)/(B12-1))} -> 233786.43
A14: Grand Mean | B14: =AVERAGE(Sales_Deals!G2:G2501) -> 278456.13
A15: Total n | B15: =SUM(B7:B12) -> 2500
A18: ANOVA Table
A19: SS Between | B19: {=SUMPRODUCT(B7:B12,(C7:C12-B14)^2)} -> 5.9828619e+11
A20: SS Within | B20: {=SUMPRODUCT((Sales_Deals!$D$2:$D$2501=A7)*(Sales_Deals!$G$2:$G$2501-C7)^2)+SUMPRODUCT((Sales_Deals!$D$2:$D$2501=A8)*(Sales_Deals!$G$2:$G$2501-C8)^2)+SUMPRODUCT((Sales_Deals!$D$2:$D$2501=A9)*(Sales_Deals!$G$2:$G$2501-C9)^2)+SUMPRODUCT((Sales_Deals!$D$2:$D$2501=A10)*(Sales_Deals!$G$2:$G$2501-C10)^2)+SUMPRODUCT((Sales_Deals!$D$2:$D$2501=A11)*(Sales_Deals!$G$2:$G$2501-C11)^2)+SUMPRODUCT((Sales_Deals!$D$2:$D$2501=A12)*(Sales_Deals!$G$2:$G$2501-C12)^2)} -> 1.1082402e+14
A21: df Between | B21: =COUNTA(A7:A12)-1 -> 5
A22: df Within | B22: =B15-COUNTA(A7:A12) -> 2494
A23: MS Between | B23: =B19/B21 -> 1.1965724e+11
A24: MS Within | B24: =B20/B22 -> 4.4436255e+10
A25: F-statistic | B25: =B23/B24 -> 2.692784
A26: p-value | B26: =FDIST(B25,B21,B22) -> 0.019619936
A28: Conclusion (alpha=0.05) | B28: =IF(B26<0.05,"Reject H0 - deal value differs by product","Fail to reject H0 - no real difference by product") -> Reject H0 - deal value differs by product
