Workbook

Sheet Summary
A1: Task/Case Study 2
A2: Cleaning the Lens - Data Preparation and Departmental Analysis
A3: NovaByte Solutions | Sales & Finance
A5: Part A - Data Cleaning Summary
A6: 1 | B6: Dates standardized: Sales_Deals.Created_Date mixed 91 text-formatted dates (MM/DD/YYYY) with proper datetime values; all dates across both files now display as YYYY-MM-DD.
A7: 2 | B7: Duplicates removed: 40 exact duplicate rows in Sales_Deals (2,540 → 2,500) and 25 in Finance_Expenses (1,025 → 1,000).
A8: 3 | B8: Missing values - Sales_Deals: Sales_Rep and Lead_Source blanks filled with placeholder values ("Unassigned"/"Unknown"); Discount_Percent left blank where missing rather than guessed. Close_Date/Days_to_Close are blank on open deals - expected, not an error.
A9: 4 | B9: Missing values - Finance_Expenses: Department and Category blanks filled with placeholder values; Budget_Allocated_INR (and therefore Variance) left blank where the source data had no budget figure to work from.
A10: 5 | B10: Text fields (casing, extra spaces, blank names): checked across Sales_Rep, Product, Lead_Source, Deal_Stage, Region, Department, Category, and Vendor - no casing or whitespace inconsistencies were found in this data pull. All categorical values are already clean and consistently formatted.
A11: 6 | B11: Outlier deal values: 40 deals flagged above the mean + 3 standard deviation threshold - kept in the data, not removed, since large deals can be legitimate.
A12: 7 | B12: Negative Finance amounts: 40 rows with negative Amount_INR kept as is - these are credit/refund transactions, not data errors.
A14: Part B - Sales Analysis: Key Findings
A15: 1 | B15: Revenue is trending down: Closed Won revenue fell from ₹2.33 crore in Q1-2023 to ₹1.55 crore in Q1-2025 - a decline of roughly a third over nine quarters, not a single-quarter dip. This directly supports the case brief's premise of a revenue slowdown.
A16: 2 | B16: Win rate is healthy and fairly consistent: in the 55 - 71% range across sales reps, and a narrower 61- 67% range across regions - no single rep or region stands out as a structural problem, though the lower performers may be worth a coaching conversation.
A17: 3 | B17: Days-to-close varies more by lead source than by product: Cold Outreach and Webinar-sourced deals close fastest; Trade Show and unrecorded ("Unknown") lead sources take noticeably longer.
A19: Part C - Finance Analysis: Key Findings
A20: 1 | B20: At the department level, every department is under its cumulative allocated budget for the period - none show a positive (over-budget) variance in aggregate.
A21: 2 | B21: Top vendors by total spend: Wipro, Zoom, TCS, AWS, and Google Cloud lead the list - cloud infrastructure and consulting/collaboration tools account for the largest share of vendor spend.
A22: 3 | B22: 181 expense records exceeding ₹200,000 are currently sitting in Pending or Rejected status - a meaningful amount of spend in unresolved approval limbo, worth flagging to Finance leadership for follow-up.
A24: Where to Find Each Deliverable Item
A25: 1 | B25: Raw data: Raw_Sales_Deals, Raw_Finance_Expenses
A26: 2 | B26: Cleaned data: Cleaned_Sales_Deals, Cleaned_Finance_Expenses
A27: 3 | B27: Pivot tables, win rate, days-to-close, and revenue chart: Sales Analysis
A28: 4 | B28: Expense pivot, budget variance, top vendors, and flagged expenses: Finance Analysis

Sheet Raw_Sales_Deals
A1: Deal_ID | B1: Sales_Rep | C1: Client_ID | D1: Product | E1: Lead_Source | F1: Deal_Stage | G1: Deal_Value_INR | H1: Created_Date | I1: Close_Date | J1: Days_to_Close | K1: Discount_Percent | L1: Region | M1: Quarter
A2: DEAL-01440 | B2: Rohit Mehta | C2: CLI-0014 | D2: SecureNet Suite | E2: Referral | F2: Closed Lost | G2: 160271 | H2: 2023-12-03 | I2: 45406 | J2: 143 | K2: 3.7 | L2: West | M2: Q4-2023
A3: DEAL-02021 | B3: Amit Pillai | C3: CLI-0208 | D3: AI Insights Module | E3: Organic Search | F3: Prospecting | G3: 491510 | H3: 2023-04-14 | L3: South | M3: Q2-2023
A4: DEAL-00174 | B4: Amit Pillai | C4: CLI-0084 | D4: AI Insights Module | E4: Referral | F4: Proposal Sent | G4: 224184 | H4: 2023-01-30 | L4: West | M4: Q1-2023
A5: DEAL-02399 | B5: Vikram Patel | C5: CLI-0096 | D5: AnalyticsEdge | E5: Organic Search | F5: Closed Won | G5: 265745 | H5: 2024-10-25 | I5: 45650 | J5: 60 | K5: 17.8 | L5: South | M5: Q4-2024
A6: DEAL-00243 | B6: Siddharth Joshi | C6: CLI-0071 | D6: DataVault Pro | E6: Email Campaign | F6: Closed Won | G6: 255053 | H6: 2023-12-06 | I6: 45429 | J6: 163 | K6: 8.4 | L6: East | M6: Q4-2023
A7: DEAL-02410 | C7: CLI-0238 | D7: DataVault Pro | E7: Organic Search | F7: Qualification | G7: 389913 | H7: 2023-12-16 | L7: South | M7: Q4-2023
A8: DEAL-02158 | B8: Amit Pillai | C8: CLI-0081 | D8: AI Insights Module | E8: Email Campaign | F8: Closed Won | G8: 393048 | H8: 2024-11-17 | I8: 45784 | J8: 171 | K8: 1.1 | L8: West | M8: Q4-2024
A9: DEAL-01161 | B9: Aditya Pillai | C9: CLI-0236 | D9: AI Insights Module | E9: Google Ads | F9: Closed Won | G9: 295502 | H9: 2025-02-08 | I9: 45821 | J9: 125 | K9: 15.8 | L9: East | M9: Q1-2025
A10: DEAL-00586 | B10: Meera Reddy | C10: CLI-0128 | D10: CloudShift Platform | E10: Organic Search | F10: Proposal Sent | G10: 172519 | H10: 2024-03-20 | K10: 14.2 | L10: South | M10: Q1-2024
A11: DEAL-00863 | B11: Aditya Pillai | C11: CLI-0147 | D11: DataVault Pro | E11: LinkedIn Campaign | F11: Closed Won | G11: 146890 | H11: 2024-03-05 | I11: 45414 | J11: 58 | K11: 8.5 | L11: West | M11: Q1-2024
A12: DEAL-01273 | B12: Ananya Sharma | C12: CLI-0237 | D12: AnalyticsEdge | E12: Webinar | F12: Closed Won | G12: 242460 | H12: 2024-02-24 | I12: 45463 | J12: 117 | K12: 23 | L12: East | M12: Q1-2024
A13: DEAL-01938 | B13: Siddharth Gupta | C13: CLI-0261 | D13: DataVault Pro | E13: LinkedIn Campaign | F13: Closed Won | G13: 396833 | H13: 2023-10-20 | I13: 45236 | J13: 17 | K13: 4.3 | L13: South | M13: Q4-2023
A14: DEAL-01122 | B14: Rahul Patel | C14: CLI-0070 | D14: AI Insights Module | E14: Webinar | F14: Closed Won | G14: 207588 | H14: 2024-02-13 | I14: 45486 | J14: 151 | K14: 4.3 | L14: East | M14: Q1-2024
A15: DEAL-01643 | B15: Riya Das | C15: CLI-0298 | D15: DevOps Accelerator | E15: Referral | F15: Closed Won | G15: 244787 | H15: 2023-10-11 | I15: 45327 | J15: 117 | K15: 7.8 | L15: East | M15: Q4-2023
A16: DEAL-00234 | B16: Ananya Sharma | C16: CLI-0286 | D16: SecureNet Suite | E16: Trade Show | F16: Closed Won | G16: 223320 | H16: 2024-11-27 | I16: 45770 | J16: 147 | K16: 9 | L16: North | M16: Q4-2024
A17: DEAL-01783 | B17: Vikram Iyer | C17: CLI-0050 | D17: AI Insights Module | E17: Cold Outreach | F17: Proposal Sent | G17: 341493 | H17: 2023-08-04 | L17: West | M17: Q3-2023
A18: DEAL-00305 | B18: Neha Pillai | C18: CLI-0035 | D18: AI Insights Module | E18: Google Ads | F18: Closed Lost | G18: 416867 | H18: 2024-05-14 | I18: 45541 | J18: 115 | K18: 12.2 | L18: South | M18: Q2-2024
A19: DEAL-00351 | B19: Arjun Rao | C19: CLI-0090 | D19: CloudShift Platform | E19: Trade Show | F19: Proposal Sent | G19: 67690 | H19: 2025-02-20 | K19: 12.5 | L19: South | M19: Q1-2025
A20: DEAL-02148 | B20: Aditya Pillai | C20: CLI-0202 | D20: CloudShift Platform | E20: Email Campaign | F20: Closed Won | G20: 453993 | H20: 2024-01-25 | I20: 45466 | J20: 150 | K20: 9.5 | L20: West | M20: Q1-2024
A21: DEAL-01377 | B21: Vikram Patel | C21: CLI-0102 | D21: AnalyticsEdge | E21: Trade Show | F21: Proposal Sent | G21: 404058 | H21: 05/20/2024 | K21: 5.3 | L21: South | M21: Q2-2024
A22: DEAL-01947 | B22: Arjun Rao | C22: CLI-0135 | D22: CloudShift Platform | E22: LinkedIn Campaign | F22: Qualification | G22: 117974 | H22: 2023-01-24 | K22: 11.5 | L22: East | M22: Q1-2023
A23: DEAL-02354 | B23: Meera Reddy | C23: CLI-0120 | D23: CloudShift Platform | E23: LinkedIn Campaign | F23: Proposal Sent | G23: 111938 | H23: 2025-03-09 | L23: South | M23: Q1-2025
A24: DEAL-01835 | B24: Rahul Patel | C24: CLI-0070 | D24: AI Insights Module | E24: Cold Outreach | F24: Closed Lost | G24: 133407 | H24: 2023-04-30 | I24: 45166 | J24: 120 | K24: 10.9 | L24: North | M24: Q2-2023
A25: DEAL-02057 | B25: Deepika Das | C25: CLI-0125 | D25: SecureNet Suite | F25: Negotiation | G25: 125962 | H25: 2024-02-25 | K25: 12.9 | L25: East | M25: Q1-2024
A26: DEAL-00631 | B26: Aditya Pillai | C26: CLI-0222 | D26: AnalyticsEdge | E26: Trade Show | F26: Closed Won | G26: 71017 | H26: 2023-03-09 | I26: 45095 | J26: 101 | K26: 3.5 | L26: West | M26: Q1-2023
A27: DEAL-02059 | B27: Vikram Iyer | C27: CLI-0191 | D27: AnalyticsEdge | E27: Cold Outreach | F27: Closed Won | G27: 80078 | H27: 2024-12-26 | I27: 45722 | J27: 70 | K27: 4.9 | L27: North | M27: Q4-2024
A28: DEAL-00946 | B28: Rahul Patel | C28: CLI-0158 | D28: SecureNet Suite | E28: Cold Outreach | F28: Negotiation | G28: 147459 | H28: 2023-04-10 | K28: 6.4 | L28: South | M28: Q2-2023
A29: DEAL-01560 | B29: Siddharth Gupta | C29: CLI-0219 | D29: AI Insights Module | E29: Webinar | F29: Closed Lost | G29: 59394 | H29: 2023-12-18 | I29: 45351 | J29: 73 | K29: 2.1 | L29: East | M29: Q4-2023
A30: DEAL-01779 | B30: Neha Pillai | C30: CLI-0266 | D30: CloudShift Platform | E30: LinkedIn Campaign | F30: Prospecting | G30: 490489 | H30: 2025-02-11 | L30: North | M30: Q1-2025
A31: DEAL-01223 | B31: Ananya Sharma | C31: CLI-0006 | D31: DevOps Accelerator | E31: Trade Show | F31: Proposal Sent | G31: 267116 | H31: 2024-07-02 | K31: 3 | L31: South | M31: Q3-2024
A32: DEAL-02345 | B32: Riya Das | C32: CLI-0060 | D32: DevOps Accelerator | E32: Trade Show | F32: Closed Lost | G32: 340697 | H32: 2023-06-17 | I32: 45174 | J32: 80 | K32: 6.7 | L32: North | M32: Q2-2023
A33: DEAL-00816 | B33: Aditya Pillai | C33: CLI-0278 | D33: CloudShift Platform | E33: Referral | F33: Negotiation | G33: 432247 | H33: 2025-03-13 | K33: 13.4 | L33: North | M33: Q1-2025
A34: DEAL-01909 | B34: Amit Pillai | C34: CLI-0063 | D34: AnalyticsEdge | E34: Email Campaign | F34: Closed Lost | G34: 449838 | H34: 2024-05-30 | I34: 45589 | J34: 147 | K34: 6.8 | L34: West | M34: Q2-2024
A35: DEAL-00184 | B35: Siddharth Gupta | C35: CLI-0080 | D35: AI Insights Module | E35: LinkedIn Campaign | F35: Negotiation | G35: 325774 | H35: 2024-02-13 | L35: West | M35: Q1-2024
A36: DEAL-00430 | B36: Siddharth Gupta | C36: CLI-0088 | D36: AnalyticsEdge | E36: Trade Show | F36: Closed Lost | G36: 251845 | H36: 2024-07-26 | I36: 45520 | J36: 21 | K36: 6.3 | L36: East | M36: Q3-2024
A37: DEAL-01657 | B37: Arjun Rao | C37: CLI-0154 | D37: CloudShift Platform | E37: Cold Outreach | F37: Proposal Sent | G37: 245814 | H37: 2023-04-01 | L37: North | M37: Q2-2023
A38: DEAL-01118 | B38: Rohit Mehta | C38: CLI-0086 | D38: AI Insights Module | E38: Webinar | F38: Qualification | G38: 128284 | H38: 2023-06-06 | K38: 1.5 | L38: South | M38: Q2-2023
A39: DEAL-00337 | B39: Meera Reddy | C39: CLI-0286 | D39: SecureNet Suite | F39: Proposal Sent | G39: 157092 | H39: 2024-12-29 | K39: 6.3 | L39: North | M39: Q4-2024
A40: DEAL-01051 | B40: Priya Kumar | C40: CLI-0284 | D40: DevOps Accelerator | E40: Trade Show | F40: Qualification | G40: 387930 | H40: 2024-10-22 | K40: 2.8 | L40: West | M40: Q4-2024
A41: DEAL-01916 | B41: Arjun Rao | C41: CLI-0288 | D41: DevOps Accelerator | E41: Webinar | F41: Negotiation | G41: 265994 | H41: 2025-03-28 | K41: 0.7 | L41: North | M41: Q1-2025
A42: DEAL-00718 | B42: Rohit Mehta | C42: CLI-0272 | D42: SecureNet Suite | E42: Webinar | F42: Closed Won | G42: 925816 | H42: 2024-06-06 | I42: 45467 | J42: 18 | K42: 16.6 | L42: North | M42: Q2-2024
A43: DEAL-02141 | B43: Siddharth Joshi | C43: CLI-0218 | D43: DataVault Pro | E43: LinkedIn Campaign | F43: Closed Won | G43: 57872 | H43: 2024-04-09 | I43: 45559 | J43: 168 | K43: 4.5 | L43: South | M43: Q2-2024
A44: DEAL-00488 | B44: Riya Das | C44: CLI-0221 | D44: AnalyticsEdge | E44: Trade Show | F44: Closed Won | G44: 25184 | H44: 2024-06-03 | I44: 45516 | J44: 70 | K44: 19.6 | L44: North | M44: Q2-2024
A45: DEAL-01718 | B45: Aditya Pillai | C45: CLI-0138 | D45: AI Insights Module | E45: Google Ads | F45: Qualification | G45: 46255 | H45: 2024-01-18 | L45: West | M45: Q1-2024
A46: DEAL-01359 | B46: Rahul Patel | C46: CLI-0162 | D46: AI Insights Module | E46: Organic Search | F46: Closed Won | G46: 34502 | H46: 2024-12-03 | I46: 45690 | J46: 61 | K46: 2.3 | L46: North | M46: Q4-2024
A47: DEAL-01902 | B47: Meera Reddy | C47: CLI-0007 | D47: SecureNet Suite | E47: Google Ads | F47: Closed Won | G47: 242893 | H47: 2023-12-05 | I47: 45286 | J47: 21 | K47: 14.4 | L47: West | M47: Q4-2023
A48: DEAL-00388 | B48: Riya Das | C48: CLI-0052 | D48: CloudShift Platform | F48: Closed Won | G48: 276108 | H48: 2024-11-05 | I48: 45683 | J48: 82 | K48: 22.6 | L48: West | M48: Q4-2024
A49: DEAL-02216 | B49: Deepika Das | C49: CLI-0278 | D49: AI Insights Module | E49: Organic Search | F49: Proposal Sent | G49: 225261 | H49: 2023-11-18 | K49: 12.7 | L49: North | M49: Q4-2023
A50: DEAL-00556 | B50: Siddharth Gupta | C50: CLI-0138 | D50: AI Insights Module | E50: Cold Outreach | F50: Negotiation | G50: 321651 | H50: 2023-05-24 | L50: South | M50: Q2-2023
A51: DEAL-01130 | B51: Vikram Iyer | C51: CLI-0216 | D51: AnalyticsEdge | E51: Referral | F51: Prospecting | G51: 495204 | H51: 2025-03-18 | L51: North | M51: Q1-2025
A52: DEAL-00938 | B52: Deepika Das | C52: CLI-0160 | D52: SecureNet Suite | E52: Google Ads | F52: Negotiation | G52: 130238 | H52: 2023-09-22 | L52: West | M52: Q3-2023
A53: DEAL-00794 | B53: Siddharth Gupta | C53: CLI-0135 | D53: AnalyticsEdge | E53: Cold Outreach | F53: Proposal Sent | G53: 115669 | H53: 2023-05-30 | K53: 3.1 | L53: South | M53: Q2-2023
A54: DEAL-00604 | B54: Aditya Pillai | C54: CLI-0043 | D54: DataVault Pro | E54: Email Campaign | F54: Qualification | G54: 154425 | H54: 2023-01-12 | K54: 9.6 | L54: North | M54: Q1-2023
A55: DEAL-00954 | B55: Riya Das | C55: CLI-0208 | D55: DevOps Accelerator | E55: Trade Show | F55: Proposal Sent | G55: 225199 | H55: 2025-03-19 | L55: East | M55: Q1-2025
A56: DEAL-01107 | B56: Rahul Patel | C56: CLI-0005 | D56: SecureNet Suite | E56: Cold Outreach | F56: Negotiation | G56: 487991 | H56: 2024-12-29 | L56: West | M56: Q4-2024
A57: DEAL-00597 | B57: Neha Pillai | C57: CLI-0230 | D57: DevOps Accelerator | E57: Email Campaign | F57: Closed Won | G57: 360231 | H57: 2025-02-20 | I57: 45855 | J57: 147 | K57: 19.5 | L57: West | M57: Q1-2025
A58: DEAL-01404 | B58: Deepika Das | C58: CLI-0286 | D58: AI Insights Module | E58: LinkedIn Campaign | F58: Closed Won | G58: 128919 | H58: 2025-03-23 | I58: 45836 | J58: 97 | K58: 5 | L58: West | M58: Q1-2025
A59: DEAL-02242 | B59: Aditya Pillai | C59: CLI-0002 | D59: DataVault Pro | E59: Referral | F59: Proposal Sent | G59: 422278 | H59: 2024-08-28 | K59: 13.7 | L59: East | M59: Q3-2024
A60: DEAL-02405 | B60: Rohit Mehta | C60: CLI-0077 | D60: SecureNet Suite | E60: Webinar | F60: Negotiation | G60: 36712 | H60: 2023-07-29 | K60: 5.8 | L60: South | M60: Q3-2023
A61: DEAL-00721 | B61: Arjun Rao | C61: CLI-0135 | D61: AnalyticsEdge | E61: Google Ads | F61: Qualification | G61: 390892 | H61: 2024-02-05 | K61: 6.7 | L61: South | M61: Q1-2024
A62: DEAL-00504 | B62: Siddharth Gupta | C62: CLI-0237 | D62: DataVault Pro | E62: Webinar | F62: Negotiation | G62: 12937 | H62: 2023-07-12 | L62: West | M62: Q3-2023
A63: DEAL-00937 | B63: Rahul Patel | C63: CLI-0060 | D63: AnalyticsEdge | E63: Cold Outreach | F63: Closed Won | G63: 324521 | H63: 2024-07-27 | I63: 45644 | J63: 144 | K63: 18.2 | L63: West | M63: Q3-2024
A64: DEAL-01769 | B64: Deepika Das | C64: CLI-0208 | D64: AI Insights Module | E64: Referral | F64: Proposal Sent | G64: 113876 | H64: 2025-03-28 | L64: South | M64: Q1-2025
A65: DEAL-01725 | B65: Aditya Pillai | C65: CLI-0197 | D65: CloudShift Platform | E65: Webinar | F65: Proposal Sent | G65: 499086 | H65: 2023-01-05 | K65: 4.9 | L65: East | M65: Q1-2023
A66: DEAL-00951 | B66: Ananya Sharma | C66: CLI-0063 | D66: CloudShift Platform | E66: Email Campaign | F66: Closed Lost | G66: 139182 | H66: 2024-01-26 | I66: 45343 | J66: 26 | L66: North | M66: Q1-2024
A67: DEAL-00313 | B67: Siddharth Joshi | C67: CLI-0063 | D67: DevOps Accelerator | E67: Webinar | F67: Prospecting | G67: 244478 | H67: 2023-05-06 | K67: 0.6 | L67: South | M67: Q2-2023
A68: DEAL-00726 | B68: Vikram Patel | C68: CLI-0251 | D68: DevOps Accelerator | E68: Trade Show | F68: Closed Won | G68: 108751 | H68: 2025-03-16 | I68: 45782 | J68: 50 | K68: 17.2 | L68: South | M68: Q1-2025
A69: DEAL-01062 | B69: Ananya Sharma | C69: CLI-0243 | D69: SecureNet Suite | E69: LinkedIn Campaign | F69: Proposal Sent | G69: 387686 | H69: 2023-03-21 | K69: 8.5 | L69: East | M69: Q1-2023
A70: DEAL-00072 | B70: Neha Pillai | C70: CLI-0228 | D70: SecureNet Suite | E70: Email Campaign | F70: Closed Won | G70: 42234 | H70: 2023-05-23 | I70: 45232 | J70: 163 | K70: 15.9 | L70: North | M70: Q2-2023
A71: DEAL-00593 | B71: Meera Reddy | C71: CLI-0084 | D71: DevOps Accelerator | E71: LinkedIn Campaign | F71: Qualification | G71: 141423 | H71: 2024-11-06 | K71: 4.5 | L71: West | M71: Q4-2024
A72: DEAL-00633 | B72: Rahul Patel | C72: CLI-0275 | D72: DataVault Pro | E72: Cold Outreach | F72: Closed Lost | G72: 233514 | H72: 2024-01-22 | I72: 45349 | J72: 36 | K72: 7.4 | L72: West | M72: Q1-2024
A73: DEAL-00241 | B73: Rohit Mehta | C73: CLI-0292 | D73: CloudShift Platform | E73: Google Ads | F73: Qualification | G73: 316458 | H73: 2024-10-29 | K73: 11.3 | L73: South | M73: Q4-2024
A74: DEAL-00879 | B74: Neha Pillai | C74: CLI-0031 | D74: CloudShift Platform | E74: Referral | F74: Closed Lost | G74: 274493 | H74: 2024-12-28 | I74: 45769 | J74: 115 | K74: 0.4 | L74: East | M74: Q4-2024
A75: DEAL-01532 | B75: Arjun Rao | C75: CLI-0109 | D75: CloudShift Platform | E75: Google Ads | F75: Negotiation | G75: 187167 | H75: 2023-05-27 | L75: South | M75: Q2-2023
A76: DEAL-02348 | B76: Meera Reddy | C76: CLI-0295 | D76: SecureNet Suite | E76: LinkedIn Campaign | F76: Closed Lost | G76: 263320 | H76: 2024-04-22 | I76: 45429 | J76: 25 | L76: North | M76: Q2-2024
A77: DEAL-01079 | B77: Amit Pillai | C77: CLI-0172 | D77: CloudShift Platform | E77: Referral | F77: Prospecting | G77: 168215 | H77: 2024-03-19 | K77: 12.7 | L77: North | M77: Q1-2024
A78: DEAL-01305 | B78: Amit Pillai | C78: CLI-0206 | D78: SecureNet Suite | E78: Google Ads | F78: Closed Won | G78: 20087 | H78: 2024-06-12 | I78: 45599 | J78: 144 | K78: 24.1 | L78: South | M78: Q2-2024
A79: DEAL-00187 | B79: Siddharth Gupta | C79: CLI-0180 | D79: AI Insights Module | E79: Referral | F79: Closed Won | G79: 384150 | H79: 2024-05-22 | I79: 45583 | J79: 149 | K79: 13.1 | L79: East | M79: Q2-2024
A80: DEAL-02217 | B80: Ananya Sharma | C80: CLI-0270 | D80: SecureNet Suite | E80: Referral | F80: Negotiation | G80: 354315 | H80: 2023-02-26 | K80: 10.3 | L80: East | M80: Q1-2023
A81: DEAL-00347 | B81: Siddharth Gupta | C81: CLI-0077 | D81: AI Insights Module | E81: Google Ads | F81: Closed Won | G81: 124965 | H81: 2023-10-14 | I81: 45273 | J81: 60 | K81: 0.4 | L81: North | M81: Q4-2023
A82: DEAL-00971 | B82: Aditya Pillai | C82: CLI-0087 | D82: AnalyticsEdge | E82: Webinar | F82: Closed Lost | G82: 410731 | H82: 2023-03-04 | I82: 45082 | J82: 93 | K82: 4.7 | L82: South | M82: Q1-2023
A83: DEAL-00709 | B83: Aditya Pillai | C83: CLI-0183 | D83: AI Insights Module | E83: Email Campaign | F83: Closed Lost | G83: 272141 | H83: 2023-02-01 | I83: 45038 | J83: 80 | K83: 12.9 | L83: North | M83: Q1-2023
A84: DEAL-00383 | B84: Ananya Sharma | C84: CLI-0138 | D84: AI Insights Module | E84: LinkedIn Campaign | F84: Prospecting | G84: 400965 | H84: 2024-03-06 | K84: 10.4 | L84: West | M84: Q1-2024
A85: DEAL-01809 | B85: Siddharth Joshi | C85: CLI-0103 | D85: CloudShift Platform | E85: Organic Search | F85: Negotiation | G85: 217920 | H85: 2024-12-02 | L85: West | M85: Q4-2024
A86: DEAL-00077 | B86: Rahul Patel | C86: CLI-0075 | D86: DataVault Pro | E86: Trade Show | F86: Closed Lost | G86: 478494 | H86: 2024-09-10 | I86: 45668 | J86: 123 | K86: 6.8 | L86: West | M86: Q3-2024
A87: DEAL-00423 | B87: Vikram Patel | C87: CLI-0146 | D87: AnalyticsEdge | E87: Webinar | F87: Proposal Sent | G87: 366026 | H87: 2023-12-06 | K87: 5.9 | L87: East | M87: Q4-2023
A88: DEAL-01237 | B88: Amit Pillai | C88: CLI-0033 | D88: AI Insights Module | E88: Email Campaign | F88: Closed Won | G88: 210971 | H88: 2024-07-30 | I88: 45562 | J88: 59 | K88: 19.3 | L88: West | M88: Q3-2024
A89: DEAL-01217 | B89: Amit Pillai | C89: CLI-0017 | D89: AnalyticsEdge | E89: Webinar | F89: Qualification | G89: 392720 | H89: 2024-06-01 | K89: 5.8 | L89: South | M89: Q2-2024
A90: DEAL-01724 | B90: Neha Pillai | C90: CLI-0090 | D90: AnalyticsEdge | E90: LinkedIn Campaign | F90: Negotiation | G90: 268444 | H90: 05/12/2024 | L90: East | M90: Q2-2024
A91: DEAL-00151 | B91: Siddharth Gupta | C91: CLI-0099 | D91: CloudShift Platform | E91: Google Ads | F91: Qualification | G91: 202104 | H91: 2025-01-29 | K91: 8.8 | L91: East | M91: Q1-2025
A92: DEAL-00418 | B92: Deepika Das | C92: CLI-0295 | D92: AI Insights Module | E92: Referral | F92: Qualification | G92: 367272 | H92: 07/11/2023 | K92: 5 | L92: North | M92: Q3-2023
A93: DEAL-01039 | B93: Priya Kumar | C93: CLI-0212 | D93: AI Insights Module | E93: Organic Search | F93: Closed Lost | G93: 199001 | H93: 2024-03-23 | I93: 45483 | J93: 109 | L93: West | M93: Q1-2024
A94: DEAL-01871 | B94: Siddharth Joshi | C94: CLI-0026 | D94: DevOps Accelerator | E94: Email Campaign | F94: Qualification | G94: 321550 | H94: 2023-07-12 | L94: East | M94: Q3-2023
A95: DEAL-01438 | B95: Ananya Sharma | C95: CLI-0259 | D95: SecureNet Suite | E95: Referral | F95: Negotiation | G95: 376342 | H95: 2024-02-22 | K95: 1.9 | L95: East | M95: Q1-2024
A96: DEAL-02064 | B96: Rohit Mehta | C96: CLI-0248 | D96: DevOps Accelerator | E96: Referral | F96: Closed Lost | G96: 119352 | H96: 2024-02-24 | I96: 45410 | J96: 64 | K96: 5.9 | L96: South | M96: Q1-2024
A97: DEAL-00140 | B97: Aditya Pillai | C97: CLI-0261 | D97: DevOps Accelerator | E97: LinkedIn Campaign | F97: Prospecting | G97: 313108 | H97: 06/25/2024 | L97: East | M97: Q2-2024
A98: DEAL-01175 | B98: Ananya Sharma | C98: CLI-0273 | D98: DataVault Pro | E98: Cold Outreach | F98: Negotiation | G98: 254116 | H98: 2025-01-17 | K98: 11 | L98: West | M98: Q1-2025
A99: DEAL-01177 | B99: Rahul Patel | C99: CLI-0122 | D99: CloudShift Platform | E99: LinkedIn Campaign | F99: Negotiation | G99: 336032 | H99: 2023-07-17 | K99: 4.6 | L99: North | M99: Q3-2023
A100: DEAL-02224 | B100: Deepika Das | C100: CLI-0166 | D100: DevOps Accelerator | E100: Google Ads | F100: Closed Won | G100: 345065 | H100: 2023-09-25 | I100: 45267 | J100: 73 | K100: 2.5 | L100: West | M100: Q3-2023
...

Sheet Raw_Finance_Expenses
A1: Expense_ID | B1: Department | C1: Category | D1: Vendor | E1: Amount_INR | F1: Budget_Allocated_INR | G1: Variance_INR | H1: Expense_Date | I1: Approval_Status | J1: Payment_Mode | K1: Fiscal_Year | L1: Remarks
A2: EXP-00594 | C2: Cloud Infrastructure | D2: Slack | E2: 209189 | F2: 170793.17 | G2: 38395.83 | H2: 45126 | I2: Pending | J2: Vendor Credit | K2: FY2023-2024 | L2: Under review
A3: EXP-00495 | B3: Operations | C3: Utilities | D3: HubSpot | E3: 6214 | F3: 7523.05 | G3: -1309.05 | H3: 45209 | I3: Approved | J3: Bank Transfer | K3: FY2023-2024 | L3: Recurring
A4: EXP-00587 | B4: Sales | C4: Marketing Spend | D4: SAP | E4: 499533 | F4: 550589.56 | G4: -51056.56 | H4: 45310 | I4: Approved | J4: Bank Transfer | K4: FY2023-2024 | L4: Recurring
A5: EXP-00178 | B5: Finance | C5: Utilities | D5: Infosys | E5: 403234 | F5: 426617.54 | G5: -23383.54 | H5: 45732 | I5: Approved | J5: Bank Transfer | K5: FY2024-2025
A6: EXP-00869 | C6: Cloud Infrastructure | D6: TCS | E6: 187461 | F6: 156297.94 | G6: 31163.06 | H6: 44963 | I6: Approved | J6: Credit Card | K6: FY2022-2023
A7: EXP-00674 | B7: Sales | C7: Hardware | D7: TCS | E7: 352393 | F7: 449410.33 | G7: -97017.33 | H7: 45365 | I7: Approved | J7: Bank Transfer | K7: FY2023-2024
A8: EXP-00181 | B8: Engineering | C8: Hardware | D8: Slack | E8: 361946 | F8: 354476.37 | G8: 7469.63 | H8: 45152 | I8: Pending | J8: Vendor Credit | K8: FY2023-2024 | L8: Urgent
A9: EXP-00277 | B9: Support | C9: Office Supplies | D9: Wipro | E9: 398503 | F9: 438557.67 | G9: -40054.67 | H9: 45145 | I9: Approved | J9: Credit Card | K9: FY2023-2024
A10: EXP-00515 | B10: Support | C10: Consulting Fees | D10: Oracle | E10: 345565 | F10: 382355.25 | G10: -36790.25 | H10: 45437 | I10: Approved | J10: Vendor Credit | K10: FY2024-2025 | L10: Duplicate entry
A11: EXP-00339 | B11: Engineering | C11: Hardware | D11: HubSpot | E11: 441930 | F11: 426169.24 | G11: 15760.76 | H11: 45740 | I11: Approved | J11: Credit Card | K11: FY2024-2025 | L11: Under review
A12: EXP-00555 | C12: Office Supplies | D12: SAP | E12: 304214 | F12: 345611.18 | G12: -41397.18 | H12: 45689 | I12: Approved | J12: Bank Transfer | K12: FY2024-2025 | L12: Recurring
A13: EXP-00803 | B13: Support | C13: Travel | D13: Freshdesk | E13: 65791 | F13: 59739.7 | G13: 6051.3 | H13: 45346 | I13: Approved | J13: Petty Cash | K13: FY2023-2024 | L13: Under review
A14: EXP-00875 | B14: Engineering | C14: Software Licenses | D14: Google Cloud | E14: 49237 | G14: 7036.11 | H14: 45457 | I14: Pending | J14: Petty Cash | K14: FY2024-2025 | L14: Duplicate entry
A15: EXP-00691 | B15: HR | C15: Office Supplies | D15: TCS | E15: 365283 | F15: 359381.54 | G15: 5901.46 | H15: 45645 | I15: Approved | J15: Credit Card | K15: FY2024-2025
A16: EXP-00233 | B16: HR | C16: Consulting Fees | D16: Google Cloud | E16: 201346 | F16: 197464.53 | H16: 45719 | I16: Pending | J16: Bank Transfer | K16: FY2024-2025 | L16: Under review
A17: EXP-00071 | B17: Sales | C17: Hardware | D17: HubSpot | E17: 375484 | F17: 303740.88 | G17: 71743.12 | H17: 45454 | I17: Pending | J17: Bank Transfer | K17: FY2024-2025 | L17: One-time
A18: EXP-00860 | B18: Operations | C18: Cloud Infrastructure | D18: Wipro | E18: 91274 | F18: 117271.6 | G18: -25997.6 | H18: 45367 | I18: Approved | J18: Petty Cash | K18: FY2023-2024
A19: EXP-00607 | B19: Finance | C19: Hardware | D19: Jira | E19: 58546 | F19: 54790.73 | G19: 3755.27 | H19: 45324 | I19: Approved | J19: Petty Cash | K19: FY2023-2024 | L19: Under review
A20: EXP-00651 | C20: Marketing Spend | D20: SAP | E20: 10904 | F20: 13676.8 | G20: -2772.8 | H20: 44973 | I20: Approved | J20: Vendor Credit | K20: FY2022-2023 | L20: Duplicate entry
A21: EXP-00652 | B21: Operations | C21: Utilities | D21: AWS | E21: 65481 | F21: 81303.61 | G21: -15822.61 | H21: 44962 | I21: Pending | J21: Vendor Credit | K21: FY2022-2023 | L21: Duplicate entry
A22: EXP-00369 | B22: Marketing | C22: Marketing Spend | D22: HubSpot | E22: 66000 | F22: 78840.27 | G22: -12840.27 | H22: 45341 | I22: Approved | J22: Credit Card | K22: FY2023-2024 | L22: Under review
A23: EXP-00721 | B23: Finance | C23: Office Supplies | D23: Slack | E23: 32147 | F23: 36235.03 | G23: -4088.03 | H23: 45247 | I23: Approved | J23: Credit Card | K23: FY2023-2024
A24: EXP-00390 | C24: Consulting Fees | D24: Wipro | E24: 312310 | F24: 339411.41 | G24: -27101.41 | H24: 45270 | I24: Pending | J24: Bank Transfer | K24: FY2023-2024 | L24: Duplicate entry
A25: EXP-00520 | B25: HR | C25: Utilities | D25: Infosys | E25: 145866 | F25: 176369.11 | G25: -30503.11 | H25: 45589 | I25: Approved | J25: Petty Cash | K25: FY2024-2025 | L25: Recurring
A26: EXP-00971 | B26: Finance | C26: Training | D26: Oracle | E26: -270391 | F26: 224861.48 | G26: 45529.52 | H26: 44992 | I26: Approved | J26: Credit Card | K26: FY2022-2023 | L26: Duplicate entry
A27: EXP-00411 | B27: HR | C27: Hardware | D27: Microsoft Azure | E27: 410046 | F27: 483620.72 | G27: -73574.72 | H27: 45456 | I27: Approved | J27: Petty Cash | K27: FY2024-2025
A28: EXP-00354 | B28: Sales | C28: Salaries | D28: Oracle | E28: 406494 | G28: -13532 | H28: 45553 | I28: Approved | J28: Credit Card | K28: FY2024-2025 | L28: Recurring
A29: EXP-00600 | B29: Engineering | C29: Travel | D29: Zoom | E29: 66859 | F29: 75521.94 | G29: -8662.94 | H29: 45442 | I29: Approved | J29: Petty Cash | K29: FY2024-2025
A30: EXP-00034 | B30: Support | C30: Consulting Fees | D30: Oracle | E30: 389612 | F30: 356713.15 | G30: 32898.85 | H30: 45486 | I30: Pending | J30: Petty Cash | K30: FY2024-2025
A31: EXP-00200 | B31: Sales | C31: Salaries | D31: TCS | E31: 397643 | F31: 366588.32 | H31: 45309 | I31: Pending | J31: Petty Cash | K31: FY2023-2024
A32: EXP-00925 | B32: Sales | C32: Software Licenses | D32: Google Cloud | E32: 367122 | F32: 465065.53 | G32: -97943.53 | H32: 45084 | I32: Pending | J32: Credit Card | K32: FY2023-2024 | L32: One-time
A33: EXP-00546 | B33: Marketing | C33: Travel | D33: Adobe | E33: 65667 | F33: 72499.12 | G33: -6832.12 | H33: 45077 | I33: Approved | J33: Petty Cash | K33: FY2023-2024
A34: EXP-00602 | C34: Salaries | D34: Wipro | E34: 350446 | F34: 293167.5 | G34: 57278.5 | H34: 45395 | I34: Approved | J34: Vendor Credit | K34: FY2024-2025
A35: EXP-00083 | B35: Support | C35: Maintenance | D35: Wipro | E35: 215496 | F35: 269360.68 | H35: 45427 | I35: Rejected | J35: Petty Cash | K35: FY2024-2025 | L35: Duplicate entry
A36: EXP-00750 | B36: Sales | C36: Recruitment | D36: Freshdesk | E36: 7227 | F36: 9023.9 | G36: -1796.9 | H36: 45131 | I36: Approved | J36: Vendor Credit | K36: FY2023-2024
A37: EXP-00172 | B37: Operations | C37: Travel | D37: AWS | E37: 481644 | F37: 431586.58 | G37: 50057.42 | H37: 45338 | I37: Approved | J37: Vendor Credit | K37: FY2023-2024 | L37: Urgent
A38: EXP-00531 | B38: Sales | C38: Recruitment | D38: AWS | E38: -214583 | F38: 220195.61 | G38: -5612.61 | H38: 45157 | I38: Approved | J38: Petty Cash | K38: FY2023-2024
A39: EXP-00337 | B39: Sales | C39: Utilities | D39: HubSpot | E39: 71717 | F39: 89231.77 | G39: -17514.77 | H39: 45573 | I39: Approved | J39: Credit Card | K39: FY2024-2025 | L39: Urgent
A40: EXP-00832 | B40: Engineering | C40: Training | D40: Infosys | E40: 352092 | F40: 424330.22 | G40: -72238.22 | H40: 45540 | I40: Approved | J40: Bank Transfer | K40: FY2024-2025 | L40: One-time
A41: EXP-00717 | B41: HR | C41: Office Supplies | D41: Internal | E41: 3606815 | F41: 3411626.7 | G41: 195188.28 | H41: 45464 | I41: Pending | J41: Bank Transfer | K41: FY2024-2025 | L41: Recurring
A42: EXP-00601 | B42: Sales | C42: Cloud Infrastructure | D42: Wipro | E42: 128850 | F42: 118183.64 | G42: 10666.36 | H42: 45143 | I42: Approved | J42: Vendor Credit | K42: FY2023-2024
A43: EXP-00275 | B43: Operations | C43: Utilities | D43: SAP | E43: 166769 | F43: 196065.31 | G43: -29296.31 | H43: 45175 | I43: Approved | J43: Credit Card | K43: FY2023-2024 | L43: Recurring
A44: EXP-00466 | B44: Support | C44: Software Licenses | D44: Adobe | E44: 454117 | G44: -112004.76 | H44: 45077 | I44: Approved | J44: Vendor Credit | K44: FY2023-2024 | L44: Under review
A45: EXP-00663 | B45: Sales | C45: Recruitment | D45: Google Cloud | E45: 225901 | F45: 254208.33 | G45: -28307.33 | H45: 45520 | I45: Approved | J45: Petty Cash | K45: FY2024-2025 | L45: Recurring
A46: EXP-00954 | B46: Engineering | C46: Training | D46: AWS | E46: 173047 | F46: 149662.31 | H46: 45249 | I46: Approved | J46: Vendor Credit | K46: FY2023-2024 | L46: Under review
A47: EXP-00024 | B47: Finance | C47: Maintenance | D47: Infosys | E47: 247370 | F47: 268703.57 | G47: -21333.57 | H47: 45554 | I47: Approved | J47: Bank Transfer | K47: FY2024-2025
A48: EXP-00430 | B48: Engineering | C48: Marketing Spend | D48: Wipro | E48: 295595 | F48: 333028.71 | G48: -37433.71 | H48: 45555 | I48: Pending | J48: Vendor Credit | K48: FY2024-2025 | L48: Urgent
A49: EXP-00219 | B49: Finance | C49: Training | D49: HubSpot | E49: 344780 | F49: 378391.66 | G49: -33611.66 | H49: 44976 | I49: Approved | J49: Bank Transfer | K49: FY2022-2023
A50: EXP-00318 | B50: Finance | C50: Training | D50: Slack | E50: 228003 | F50: 192790.08 | G50: 35212.92 | H50: 45366 | I50: Approved | J50: Credit Card | K50: FY2023-2024 | L50: Under review
A51: EXP-00235 | B51: Support | C51: Training | D51: Internal | E51: 205500 | F51: 166546.9 | G51: 38953.1 | H51: 45180 | I51: Approved | J51: Vendor Credit | K51: FY2023-2024 | L51: Duplicate entry
A52: EXP-00231 | B52: Sales | C52: Utilities | D52: Adobe | E52: 336583 | F52: 372109.92 | G52: -35526.92 | H52: 44983 | I52: Approved | J52: Credit Card | K52: FY2022-2023 | L52: Under review
A53: EXP-00680 | B53: Support | C53: Recruitment | D53: Jira | E53: 76037 | F53: 88996.48 | G53: -12959.48 | H53: 45229 | I53: Approved | J53: Bank Transfer | K53: FY2023-2024
A54: EXP-00301 | B54: Support | C54: Hardware | D54: Internal | E54: 51292 | F54: 52199.26 | G54: -907.26 | H54: 45250 | I54: Approved | J54: Petty Cash | K54: FY2023-2024 | L54: Urgent
A55: EXP-00617 | B55: Support | C55: Training | D55: HubSpot | E55: -307191 | F55: 328740.27 | G55: -21549.27 | H55: 45684 | I55: Approved | J55: Bank Transfer | K55: FY2024-2025 | L55: Under review
A56: EXP-00994 | B56: Operations | C56: Marketing Spend | D56: Infosys | E56: 333909 | F56: 401580.86 | G56: -67671.86 | H56: 45317 | I56: Rejected | J56: Bank Transfer | K56: FY2023-2024 | L56: Recurring
A57: EXP-00548 | B57: Finance | C57: Training | D57: SAP | E57: 325449 | F57: 392529.63 | G57: -67080.63 | H57: 45709 | I57: Approved | J57: Bank Transfer | K57: FY2024-2025 | L57: Urgent
A58: EXP-00738 | B58: Operations | C58: Consulting Fees | D58: Wipro | E58: 10526 | F58: 9003.53 | G58: 1522.47 | H58: 45217 | I58: Approved | J58: Bank Transfer | K58: FY2023-2024 | L58: Under review
A59: EXP-00490 | B59: Sales | D59: SAP | E59: 464884 | F59: 581075.86 | G59: -116191.86 | H59: 45636 | I59: Rejected | J59: Vendor Credit | K59: FY2024-2025 | L59: Duplicate entry
A60: EXP-00449 | B60: Sales | C60: Recruitment | D60: Adobe | E60: 265649 | F60: 235191.89 | G60: 30457.11 | H60: 45298 | I60: Approved | J60: Credit Card | K60: FY2023-2024
A61: EXP-00147 | B61: Finance | C61: Travel | D61: Adobe | E61: 32268 | F61: 26832.63 | G61: 5435.37 | H61: 45157 | I61: Approved | J61: Credit Card | K61: FY2023-2024 | L61: Under review
A62: EXP-00348 | B62: Finance | C62: Hardware | D62: Wipro | E62: 79555 | F62: 101962.75 | G62: -22407.75 | H62: 44958 | I62: Approved | J62: Bank Transfer | K62: FY2022-2023
A63: EXP-00372 | B63: Sales | C63: Utilities | D63: Zoom | E63: 411030 | F63: 392369.5 | G63: 18660.5 | H63: 44966 | I63: Approved | J63: Vendor Credit | K63: FY2022-2023
A64: EXP-00397 | B64: Finance | C64: Cloud Infrastructure | D64: HubSpot | E64: 2583687 | F64: 2695007.7 | G64: -111320.68 | H64: 45655 | I64: Pending | J64: Vendor Credit | K64: FY2024-2025
A65: EXP-00806 | B65: Sales | C65: Travel | D65: Zoom | E65: 99203 | F65: 111995.57 | G65: -12792.57 | H65: 45616 | I65: Approved | J65: Bank Transfer | K65: FY2024-2025
A66: EXP-00660 | B66: Support | C66: Training | D66: Adobe | E66: 413818 | F66: 475823.4 | G66: -62005.4 | H66: 45461 | I66: Pending | J66: Credit Card | K66: FY2024-2025
A67: EXP-00207 | B67: HR | C67: Utilities | D67: Internal | E67: 277583 | F67: 262488.11 | G67: 15094.89 | H67: 45270 | I67: Pending | J67: Credit Card | K67: FY2023-2024 | L67: Urgent
A68: EXP-00085 | B68: Sales | C68: Training | D68: Salesforce | E68: 457651 | F68: 467629.28 | G68: -9978.28 | H68: 45307 | I68: Approved | J68: Vendor Credit | K68: FY2023-2024 | L68: Urgent
A69: EXP-00209 | B69: Support | C69: Salaries | D69: Google Cloud | E69: 62205 | F69: 68491.3 | H69: 45306 | I69: Approved | J69: Petty Cash | K69: FY2023-2024 | L69: Recurring
A70: EXP-00089 | B70: Support | C70: Utilities | D70: HubSpot | E70: 395114 | F70: 453184.31 | G70: -58070.31 | H70: 44998 | I70: Pending | J70: Petty Cash | K70: FY2022-2023 | L70: Urgent
A71: EXP-00889 | B71: Sales | C71: Office Supplies | D71: Microsoft Azure | E71: 97690 | F71: 91260.03 | G71: 6429.97 | H71: 45440 | I71: Approved | J71: Petty Cash | K71: FY2024-2025
A72: EXP-00899 | B72: Operations | C72: Recruitment | D72: Zoom | E72: 491563 | F72: 637066.96 | G72: -145503.96 | H72: 44937 | I72: Approved | J72: Vendor Credit | K72: FY2022-2023 | L72: Recurring
A73: EXP-00470 | B73: Support | C73: Maintenance | D73: Oracle | E73: 417255 | F73: 398887.4 | G73: 18367.6 | H73: 45228 | I73: Approved | J73: Vendor Credit | K73: FY2023-2024 | L73: Duplicate entry
A74: EXP-00720 | B74: Engineering | C74: Utilities | D74: HubSpot | E74: 388564 | F74: 433099.82 | G74: -44535.82 | H74: 45302 | I74: Approved | J74: Credit Card | K74: FY2023-2024 | L74: Urgent
A75: EXP-00033 | B75: Sales | D75: Salesforce | E75: 476675 | F75: 601228.87 | G75: -124553.87 | H75: 45426 | I75: Approved | J75: Vendor Credit | K75: FY2024-2025 | L75: Duplicate entry
A76: EXP-00636 | B76: Sales | C76: Software Licenses | D76: HubSpot | E76: 118973 | F76: 134000.41 | G76: -15027.41 | H76: 45671 | I76: Approved | J76: Vendor Credit | K76: FY2024-2025
A77: EXP-00382 | B77: Support | C77: Maintenance | D77: SAP | E77: 22538 | F77: 19899.53 | G77: 2638.47 | H77: 45425 | I77: Approved | J77: Vendor Credit | K77: FY2024-2025
A78: EXP-00550 | B78: Finance | C78: Office Supplies | D78: Zoom | E78: 443662 | G78: 85569.69 | H78: 45673 | I78: Pending | J78: Vendor Credit | K78: FY2024-2025 | L78: One-time
A79: EXP-00163 | B79: Support | C79: Travel | D79: Slack | E79: 353333 | F79: 458964.2 | G79: -105631.2 | H79: 45702 | I79: Approved | J79: Credit Card | K79: FY2024-2025 | L79: Urgent
A80: EXP-00795 | B80: Marketing | C80: Recruitment | D80: Oracle | E80: 290249 | F80: 369613.63 | G80: -79364.63 | H80: 45299 | I80: Approved | J80: Petty Cash | K80: FY2023-2024 | L80: Under review
A81: EXP-00727 | B81: Finance | C81: Travel | D81: HubSpot | E81: 309034 | F81: 273262.53 | G81: 35771.47 | H81: 45384 | I81: Pending | J81: Petty Cash | K81: FY2024-2025 | L81: Recurring
A82: EXP-00403 | B82: Engineering | C82: Travel | D82: Microsoft Azure | E82: 106902 | F82: 123641.31 | G82: -16739.31 | H82: 45022 | I82: Pending | J82: Credit Card | K82: FY2023-2024
A83: EXP-00569 | B83: Operations | C83: Travel | D83: Freshdesk | E83: 429973 | F83: 376365.53 | G83: 53607.47 | H83: 45230 | I83: Pending | J83: Vendor Credit | K83: FY2023-2024
A84: EXP-00396 | B84: Operations | C84: Office Supplies | D84: AWS | E84: 206116 | F84: 229625.18 | G84: -23509.18 | H84: 45699 | I84: Pending | J84: Vendor Credit | K84: FY2024-2025
A85: EXP-00865 | C85: Travel | D85: Microsoft Azure | E85: 1422304 | F85: 1675743.1 | G85: -253439.07 | H85: 45310 | I85: Approved | J85: Bank Transfer | K85: FY2023-2024 | L85: Recurring
A86: EXP-00271 | B86: Operations | C86: Software Licenses | D86: Adobe | E86: 495376 | F86: 532148.51 | G86: -36772.51 | H86: 45728 | I86: Pending | J86: Petty Cash | K86: FY2024-2025 | L86: Recurring
A87: EXP-00272 | B87: HR | C87: Cloud Infrastructure | D87: Zoom | E87: 374421 | F87: 472252.91 | G87: -97831.91 | H87: 45125 | I87: Approved | J87: Credit Card | K87: FY2023-2024
A88: EXP-00583 | B88: HR | C88: Office Supplies | D88: Slack | E88: 277952 | F88: 236373.9 | G88: 41578.1 | H88: 45665 | I88: Rejected | J88: Credit Card | K88: FY2024-2025
A89: EXP-00533 | B89: Finance | C89: Maintenance | D89: Salesforce | E89: 314597 | F89: 405247.51 | G89: -90650.51 | H89: 45576 | I89: Pending | J89: Bank Transfer | K89: FY2024-2025 | L89: Recurring
A90: EXP-00371 | B90: Support | C90: Software Licenses | D90: Internal | E90: 109346 | F90: 139986.84 | G90: -30640.84 | H90: 45178 | I90: Pending | J90: Credit Card | K90: FY2023-2024 | L90: Recurring
A91: EXP-00835 | B91: Sales | C91: Office Supplies | D91: Freshdesk | E91: -57182 | F91: 60104.14 | H91: 45051 | I91: Approved | J91: Bank Transfer | K91: FY2023-2024
A92: EXP-00923 | B92: HR | C92: Office Supplies | D92: SAP | E92: 429501 | F92: 466352.17 | G92: -36851.17 | H92: 45638 | I92: Pending | J92: Credit Card | K92: FY2024-2025 | L92: Recurring
A93: EXP-00169 | B93: Sales | C93: Travel | D93: Salesforce | E93: 478753 | F93: 566440.71 | G93: -87687.71 | H93: 45164 | I93: Pending | J93: Bank Transfer | K93: FY2023-2024 | L93: Recurring
A94: EXP-00683 | B94: Sales | C94: Training | D94: Slack | E94: 62031 | F94: 62498.04 | G94: -467.04 | H94: 45178 | I94: Rejected | J94: Bank Transfer | K94: FY2023-2024
A95: EXP-00506 | B95: Marketing | C95: Marketing Spend | D95: Slack | E95: 288581 | F95: 353638.16 | G95: -65057.16 | H95: 45602 | I95: Approved | J95: Bank Transfer | K95: FY2024-2025 | L95: Duplicate entry
A96: EXP-00540 | B96: Marketing | C96: Utilities | D96: Oracle | E96: 123062 | F96: 152975.35 | G96: -29913.35 | H96: 45200 | I96: Pending | J96: Vendor Credit | K96: FY2023-2024 | L96: Duplicate entry
A97: EXP-00532 | B97: Marketing | C97: Consulting Fees | D97: Google Cloud | E97: 481569 | F97: 451100.97 | G97: 30468.03 | H97: 45078 | I97: Approved | J97: Petty Cash | K97: FY2023-2024
A98: EXP-00898 | B98: Sales | C98: Consulting Fees | D98: Salesforce | E98: 163410 | F98: 200577.85 | H98: 45458 | I98: Approved | J98: Bank Transfer | K98: FY2024-2025 | L98: Urgent
A99: EXP-00179 | B99: HR | C99: Travel | D99: TCS | E99: 377326 | F99: 461081.99 | G99: -83755.99 | H99: 45255 | I99: Approved | J99: Vendor Credit | K99: FY2023-2024
A100: EXP-00321 | B100: Operations | C100: Marketing Spend | D100: TCS | E100: 79297 | F100: 66599.44 | G100: 12697.56 | H100: 45023 | I100: Approved | J100: Petty Cash | K100: FY2023-2024 | L100: Under review
...

Sheet Cleaned_Sales_Deals
A1: Deal_ID | B1: Sales_Rep | C1: Client_ID | D1: Product | E1: Lead_Source | F1: Deal_Stage | G1: Deal_Value_INR | H1: Created_Date | I1: Close_Date | J1: Days_to_Close | K1: Discount_Percent | L1: Region | M1: Quarter | N1: Outlier_Flag
A2: DEAL-01440 | B2: Rohit Mehta | C2: CLI-0014 | D2: SecureNet Suite | E2: Referral | F2: Closed Lost | G2: 160271 | H2: 45263 | I2: 45406 | J2: 143 | K2: 3.7 | L2: West | M2: Q4-2023 | N2: =IF(G2>$R$5,"High Outlier",IF(G2<$R$6,"Low Outlier","Normal")) -> Normal | Q2: Deal Value Outlier Statistics | R2: Value
A3: DEAL-02021 | B3: Amit Pillai | C3: CLI-0208 | D3: AI Insights Module | E3: Organic Search | F3: Prospecting | G3: 491510 | H3: 45030 | L3: South | M3: Q2-2023 | N3: =IF(G3>$R$5,"High Outlier",IF(G3<$R$6,"Low Outlier","Normal")) -> Normal | Q3: Mean Deal Value (INR) | R3: =AVERAGE(G2:G2501) -> 278456.13
A4: DEAL-00174 | B4: Amit Pillai | C4: CLI-0084 | D4: AI Insights Module | E4: Referral | F4: Proposal Sent | G4: 224184 | H4: 44956 | L4: West | M4: Q1-2023 | N4: =IF(G4>$R$5,"High Outlier",IF(G4<$R$6,"Low Outlier","Normal")) -> Normal | Q4: Std Dev (INR) | R4: =STDEV(G2:G2501) -> 211155.77
A5: DEAL-02399 | B5: Vikram Patel | C5: CLI-0096 | D5: AnalyticsEdge | E5: Organic Search | F5: Closed Won | G5: 265745 | H5: 45590 | I5: 45650 | J5: 60 | K5: 17.8 | L5: South | M5: Q4-2024 | N5: =IF(G5>$R$5,"High Outlier",IF(G5<$R$6,"Low Outlier","Normal")) -> Normal | Q5: Upper Threshold (Mean+3*STD) | R5: =R3+3*R4 -> 911923.43
A6: DEAL-00243 | B6: Siddharth Joshi | C6: CLI-0071 | D6: DataVault Pro | E6: Email Campaign | F6: Closed Won | G6: 255053 | H6: 45266 | I6: 45429 | J6: 163 | K6: 8.4 | L6: East | M6: Q4-2023 | N6: =IF(G6>$R$5,"High Outlier",IF(G6<$R$6,"Low Outlier","Normal")) -> Normal | Q6: Lower Threshold (Mean-3*STD) | R6: =R3-3*R4 -> -355011.17
A7: DEAL-02410 | B7: Unassigned | C7: CLI-0238 | D7: DataVault Pro | E7: Organic Search | F7: Qualification | G7: 389913 | H7: 45276 | L7: South | M7: Q4-2023 | N7: =IF(G7>$R$5,"High Outlier",IF(G7<$R$6,"Low Outlier","Normal")) -> Normal
A8: DEAL-02158 | B8: Amit Pillai | C8: CLI-0081 | D8: AI Insights Module | E8: Email Campaign | F8: Closed Won | G8: 393048 | H8: 45613 | I8: 45784 | J8: 171 | K8: 1.1 | L8: West | M8: Q4-2024 | N8: =IF(G8>$R$5,"High Outlier",IF(G8<$R$6,"Low Outlier","Normal")) -> Normal
A9: DEAL-01161 | B9: Aditya Pillai | C9: CLI-0236 | D9: AI Insights Module | E9: Google Ads | F9: Closed Won | G9: 295502 | H9: 45696 | I9: 45821 | J9: 125 | K9: 15.8 | L9: East | M9: Q1-2025 | N9: =IF(G9>$R$5,"High Outlier",IF(G9<$R$6,"Low Outlier","Normal")) -> Normal
A10: DEAL-00586 | B10: Meera Reddy | C10: CLI-0128 | D10: CloudShift Platform | E10: Organic Search | F10: Proposal Sent | G10: 172519 | H10: 45371 | K10: 14.2 | L10: South | M10: Q1-2024 | N10: =IF(G10>$R$5,"High Outlier",IF(G10<$R$6,"Low Outlier","Normal")) -> Normal
A11: DEAL-00863 | B11: Aditya Pillai | C11: CLI-0147 | D11: DataVault Pro | E11: LinkedIn Campaign | F11: Closed Won | G11: 146890 | H11: 45356 | I11: 45414 | J11: 58 | K11: 8.5 | L11: West | M11: Q1-2024 | N11: =IF(G11>$R$5,"High Outlier",IF(G11<$R$6,"Low Outlier","Normal")) -> Normal
A12: DEAL-01273 | B12: Ananya Sharma | C12: CLI-0237 | D12: AnalyticsEdge | E12: Webinar | F12: Closed Won | G12: 242460 | H12: 45346 | I12: 45463 | J12: 117 | K12: 23 | L12: East | M12: Q1-2024 | N12: =IF(G12>$R$5,"High Outlier",IF(G12<$R$6,"Low Outlier","Normal")) -> Normal
A13: DEAL-01938 | B13: Siddharth Gupta | C13: CLI-0261 | D13: DataVault Pro | E13: LinkedIn Campaign | F13: Closed Won | G13: 396833 | H13: 45219 | I13: 45236 | J13: 17 | K13: 4.3 | L13: South | M13: Q4-2023 | N13: =IF(G13>$R$5,"High Outlier",IF(G13<$R$6,"Low Outlier","Normal")) -> Normal
A14: DEAL-01122 | B14: Rahul Patel | C14: CLI-0070 | D14: AI Insights Module | E14: Webinar | F14: Closed Won | G14: 207588 | H14: 45335 | I14: 45486 | J14: 151 | K14: 4.3 | L14: East | M14: Q1-2024 | N14: =IF(G14>$R$5,"High Outlier",IF(G14<$R$6,"Low Outlier","Normal")) -> Normal
A15: DEAL-01643 | B15: Riya Das | C15: CLI-0298 | D15: DevOps Accelerator | E15: Referral | F15: Closed Won | G15: 244787 | H15: 45210 | I15: 45327 | J15: 117 | K15: 7.8 | L15: East | M15: Q4-2023 | N15: =IF(G15>$R$5,"High Outlier",IF(G15<$R$6,"Low Outlier","Normal")) -> Normal
A16: DEAL-00234 | B16: Ananya Sharma | C16: CLI-0286 | D16: SecureNet Suite | E16: Trade Show | F16: Closed Won | G16: 223320 | H16: 45623 | I16: 45770 | J16: 147 | K16: 9 | L16: North | M16: Q4-2024 | N16: =IF(G16>$R$5,"High Outlier",IF(G16<$R$6,"Low Outlier","Normal")) -> Normal
A17: DEAL-01783 | B17: Vikram Iyer | C17: CLI-0050 | D17: AI Insights Module | E17: Cold Outreach | F17: Proposal Sent | G17: 341493 | H17: 45142 | L17: West | M17: Q3-2023 | N17: =IF(G17>$R$5,"High Outlier",IF(G17<$R$6,"Low Outlier","Normal")) -> Normal
A18: DEAL-00305 | B18: Neha Pillai | C18: CLI-0035 | D18: AI Insights Module | E18: Google Ads | F18: Closed Lost | G18: 416867 | H18: 45426 | I18: 45541 | J18: 115 | K18: 12.2 | L18: South | M18: Q2-2024 | N18: =IF(G18>$R$5,"High Outlier",IF(G18<$R$6,"Low Outlier","Normal")) -> Normal
A19: DEAL-00351 | B19: Arjun Rao | C19: CLI-0090 | D19: CloudShift Platform | E19: Trade Show | F19: Proposal Sent | G19: 67690 | H19: 45708 | K19: 12.5 | L19: South | M19: Q1-2025 | N19: =IF(G19>$R$5,"High Outlier",IF(G19<$R$6,"Low Outlier","Normal")) -> Normal
A20: DEAL-02148 | B20: Aditya Pillai | C20: CLI-0202 | D20: CloudShift Platform | E20: Email Campaign | F20: Closed Won | G20: 453993 | H20: 45316 | I20: 45466 | J20: 150 | K20: 9.5 | L20: West | M20: Q1-2024 | N20: =IF(G20>$R$5,"High Outlier",IF(G20<$R$6,"Low Outlier","Normal")) -> Normal
A21: DEAL-01377 | B21: Vikram Patel | C21: CLI-0102 | D21: AnalyticsEdge | E21: Trade Show | F21: Proposal Sent | G21: 404058 | H21: 45432 | K21: 5.3 | L21: South | M21: Q2-2024 | N21: =IF(G21>$R$5,"High Outlier",IF(G21<$R$6,"Low Outlier","Normal")) -> Normal
A22: DEAL-01947 | B22: Arjun Rao | C22: CLI-0135 | D22: CloudShift Platform | E22: LinkedIn Campaign | F22: Qualification | G22: 117974 | H22: 44950 | K22: 11.5 | L22: East | M22: Q1-2023 | N22: =IF(G22>$R$5,"High Outlier",IF(G22<$R$6,"Low Outlier","Normal")) -> Normal
A23: DEAL-02354 | B23: Meera Reddy | C23: CLI-0120 | D23: CloudShift Platform | E23: LinkedIn Campaign | F23: Proposal Sent | G23: 111938 | H23: 45725 | L23: South | M23: Q1-2025 | N23: =IF(G23>$R$5,"High Outlier",IF(G23<$R$6,"Low Outlier","Normal")) -> Normal
A24: DEAL-01835 | B24: Rahul Patel | C24: CLI-0070 | D24: AI Insights Module | E24: Cold Outreach | F24: Closed Lost | G24: 133407 | H24: 45046 | I24: 45166 | J24: 120 | K24: 10.9 | L24: North | M24: Q2-2023 | N24: =IF(G24>$R$5,"High Outlier",IF(G24<$R$6,"Low Outlier","Normal")) -> Normal
A25: DEAL-02057 | B25: Deepika Das | C25: CLI-0125 | D25: SecureNet Suite | E25: Unknown | F25: Negotiation | G25: 125962 | H25: 45347 | K25: 12.9 | L25: East | M25: Q1-2024 | N25: =IF(G25>$R$5,"High Outlier",IF(G25<$R$6,"Low Outlier","Normal")) -> Normal
A26: DEAL-00631 | B26: Aditya Pillai | C26: CLI-0222 | D26: AnalyticsEdge | E26: Trade Show | F26: Closed Won | G26: 71017 | H26: 44994 | I26: 45095 | J26: 101 | K26: 3.5 | L26: West | M26: Q1-2023 | N26: =IF(G26>$R$5,"High Outlier",IF(G26<$R$6,"Low Outlier","Normal")) -> Normal
A27: DEAL-02059 | B27: Vikram Iyer | C27: CLI-0191 | D27: AnalyticsEdge | E27: Cold Outreach | F27: Closed Won | G27: 80078 | H27: 45652 | I27: 45722 | J27: 70 | K27: 4.9 | L27: North | M27: Q4-2024 | N27: =IF(G27>$R$5,"High Outlier",IF(G27<$R$6,"Low Outlier","Normal")) -> Normal
A28: DEAL-00946 | B28: Rahul Patel | C28: CLI-0158 | D28: SecureNet Suite | E28: Cold Outreach | F28: Negotiation | G28: 147459 | H28: 45026 | K28: 6.4 | L28: South | M28: Q2-2023 | N28: =IF(G28>$R$5,"High Outlier",IF(G28<$R$6,"Low Outlier","Normal")) -> Normal
A29: DEAL-01560 | B29: Siddharth Gupta | C29: CLI-0219 | D29: AI Insights Module | E29: Webinar | F29: Closed Lost | G29: 59394 | H29: 45278 | I29: 45351 | J29: 73 | K29: 2.1 | L29: East | M29: Q4-2023 | N29: =IF(G29>$R$5,"High Outlier",IF(G29<$R$6,"Low Outlier","Normal")) -> Normal
A30: DEAL-01779 | B30: Neha Pillai | C30: CLI-0266 | D30: CloudShift Platform | E30: LinkedIn Campaign | F30: Prospecting | G30: 490489 | H30: 45699 | L30: North | M30: Q1-2025 | N30: =IF(G30>$R$5,"High Outlier",IF(G30<$R$6,"Low Outlier","Normal")) -> Normal
A31: DEAL-01223 | B31: Ananya Sharma | C31: CLI-0006 | D31: DevOps Accelerator | E31: Trade Show | F31: Proposal Sent | G31: 267116 | H31: 45475 | K31: 3 | L31: South | M31: Q3-2024 | N31: =IF(G31>$R$5,"High Outlier",IF(G31<$R$6,"Low Outlier","Normal")) -> Normal
A32: DEAL-02345 | B32: Riya Das | C32: CLI-0060 | D32: DevOps Accelerator | E32: Trade Show | F32: Closed Lost | G32: 340697 | H32: 45094 | I32: 45174 | J32: 80 | K32: 6.7 | L32: North | M32: Q2-2023 | N32: =IF(G32>$R$5,"High Outlier",IF(G32<$R$6,"Low Outlier","Normal")) -> Normal
A33: DEAL-00816 | B33: Aditya Pillai | C33: CLI-0278 | D33: CloudShift Platform | E33: Referral | F33: Negotiation | G33: 432247 | H33: 45729 | K33: 13.4 | L33: North | M33: Q1-2025 | N33: =IF(G33>$R$5,"High Outlier",IF(G33<$R$6,"Low Outlier","Normal")) -> Normal
A34: DEAL-01909 | B34: Amit Pillai | C34: CLI-0063 | D34: AnalyticsEdge | E34: Email Campaign | F34: Closed Lost | G34: 449838 | H34: 45442 | I34: 45589 | J34: 147 | K34: 6.8 | L34: West | M34: Q2-2024 | N34: =IF(G34>$R$5,"High Outlier",IF(G34<$R$6,"Low Outlier","Normal")) -> Normal
A35: DEAL-00184 | B35: Siddharth Gupta | C35: CLI-0080 | D35: AI Insights Module | E35: LinkedIn Campaign | F35: Negotiation | G35: 325774 | H35: 45335 | L35: West | M35: Q1-2024 | N35: =IF(G35>$R$5,"High Outlier",IF(G35<$R$6,"Low Outlier","Normal")) -> Normal
A36: DEAL-00430 | B36: Siddharth Gupta | C36: CLI-0088 | D36: AnalyticsEdge | E36: Trade Show | F36: Closed Lost | G36: 251845 | H36: 45499 | I36: 45520 | J36: 21 | K36: 6.3 | L36: East | M36: Q3-2024 | N36: =IF(G36>$R$5,"High Outlier",IF(G36<$R$6,"Low Outlier","Normal")) -> Normal
A37: DEAL-01657 | B37: Arjun Rao | C37: CLI-0154 | D37: CloudShift Platform | E37: Cold Outreach | F37: Proposal Sent | G37: 245814 | H37: 45017 | L37: North | M37: Q2-2023 | N37: =IF(G37>$R$5,"High Outlier",IF(G37<$R$6,"Low Outlier","Normal")) -> Normal
A38: DEAL-01118 | B38: Rohit Mehta | C38: CLI-0086 | D38: AI Insights Module | E38: Webinar | F38: Qualification | G38: 128284 | H38: 45083 | K38: 1.5 | L38: South | M38: Q2-2023 | N38: =IF(G38>$R$5,"High Outlier",IF(G38<$R$6,"Low Outlier","Normal")) -> Normal
A39: DEAL-00337 | B39: Meera Reddy | C39: CLI-0286 | D39: SecureNet Suite | E39: Unknown | F39: Proposal Sent | G39: 157092 | H39: 45655 | K39: 6.3 | L39: North | M39: Q4-2024 | N39: =IF(G39>$R$5,"High Outlier",IF(G39<$R$6,"Low Outlier","Normal")) -> Normal
A40: DEAL-01051 | B40: Priya Kumar | C40: CLI-0284 | D40: DevOps Accelerator | E40: Trade Show | F40: Qualification | G40: 387930 | H40: 45587 | K40: 2.8 | L40: West | M40: Q4-2024 | N40: =IF(G40>$R$5,"High Outlier",IF(G40<$R$6,"Low Outlier","Normal")) -> Normal
A41: DEAL-01916 | B41: Arjun Rao | C41: CLI-0288 | D41: DevOps Accelerator | E41: Webinar | F41: Negotiation | G41: 265994 | H41: 45744 | K41: 0.7 | L41: North | M41: Q1-2025 | N41: =IF(G41>$R$5,"High Outlier",IF(G41<$R$6,"Low Outlier","Normal")) -> Normal
A42: DEAL-00718 | B42: Rohit Mehta | C42: CLI-0272 | D42: SecureNet Suite | E42: Webinar | F42: Closed Won | G42: 925816 | H42: 45449 | I42: 45467 | J42: 18 | K42: 16.6 | L42: North | M42: Q2-2024 | N42: =IF(G42>$R$5,"High Outlier",IF(G42<$R$6,"Low Outlier","Normal")) -> High Outlier
A43: DEAL-02141 | B43: Siddharth Joshi | C43: CLI-0218 | D43: DataVault Pro | E43: LinkedIn Campaign | F43: Closed Won | G43: 57872 | H43: 45391 | I43: 45559 | J43: 168 | K43: 4.5 | L43: South | M43: Q2-2024 | N43: =IF(G43>$R$5,"High Outlier",IF(G43<$R$6,"Low Outlier","Normal")) -> Normal
A44: DEAL-00488 | B44: Riya Das | C44: CLI-0221 | D44: AnalyticsEdge | E44: Trade Show | F44: Closed Won | G44: 25184 | H44: 45446 | I44: 45516 | J44: 70 | K44: 19.6 | L44: North | M44: Q2-2024 | N44: =IF(G44>$R$5,"High Outlier",IF(G44<$R$6,"Low Outlier","Normal")) -> Normal
A45: DEAL-01718 | B45: Aditya Pillai | C45: CLI-0138 | D45: AI Insights Module | E45: Google Ads | F45: Qualification | G45: 46255 | H45: 45309 | L45: West | M45: Q1-2024 | N45: =IF(G45>$R$5,"High Outlier",IF(G45<$R$6,"Low Outlier","Normal")) -> Normal
A46: DEAL-01359 | B46: Rahul Patel | C46: CLI-0162 | D46: AI Insights Module | E46: Organic Search | F46: Closed Won | G46: 34502 | H46: 45629 | I46: 45690 | J46: 61 | K46: 2.3 | L46: North | M46: Q4-2024 | N46: =IF(G46>$R$5,"High Outlier",IF(G46<$R$6,"Low Outlier","Normal")) -> Normal
A47: DEAL-01902 | B47: Meera Reddy | C47: CLI-0007 | D47: SecureNet Suite | E47: Google Ads | F47: Closed Won | G47: 242893 | H47: 45265 | I47: 45286 | J47: 21 | K47: 14.4 | L47: West | M47: Q4-2023 | N47: =IF(G47>$R$5,"High Outlier",IF(G47<$R$6,"Low Outlier","Normal")) -> Normal
A48: DEAL-00388 | B48: Riya Das | C48: CLI-0052 | D48: CloudShift Platform | E48: Unknown | F48: Closed Won | G48: 276108 | H48: 45601 | I48: 45683 | J48: 82 | K48: 22.6 | L48: West | M48: Q4-2024 | N48: =IF(G48>$R$5,"High Outlier",IF(G48<$R$6,"Low Outlier","Normal")) -> Normal
A49: DEAL-02216 | B49: Deepika Das | C49: CLI-0278 | D49: AI Insights Module | E49: Organic Search | F49: Proposal Sent | G49: 225261 | H49: 45248 | K49: 12.7 | L49: North | M49: Q4-2023 | N49: =IF(G49>$R$5,"High Outlier",IF(G49<$R$6,"Low Outlier","Normal")) -> Normal
A50: DEAL-00556 | B50: Siddharth Gupta | C50: CLI-0138 | D50: AI Insights Module | E50: Cold Outreach | F50: Negotiation | G50: 321651 | H50: 45070 | L50: South | M50: Q2-2023 | N50: =IF(G50>$R$5,"High Outlier",IF(G50<$R$6,"Low Outlier","Normal")) -> Normal
A51: DEAL-01130 | B51: Vikram Iyer | C51: CLI-0216 | D51: AnalyticsEdge | E51: Referral | F51: Prospecting | G51: 495204 | H51: 45734 | L51: North | M51: Q1-2025 | N51: =IF(G51>$R$5,"High Outlier",IF(G51<$R$6,"Low Outlier","Normal")) -> Normal
A52: DEAL-00938 | B52: Deepika Das | C52: CLI-0160 | D52: SecureNet Suite | E52: Google Ads | F52: Negotiation | G52: 130238 | H52: 45191 | L52: West | M52: Q3-2023 | N52: =IF(G52>$R$5,"High Outlier",IF(G52<$R$6,"Low Outlier","Normal")) -> Normal
A53: DEAL-00794 | B53: Siddharth Gupta | C53: CLI-0135 | D53: AnalyticsEdge | E53: Cold Outreach | F53: Proposal Sent | G53: 115669 | H53: 45076 | K53: 3.1 | L53: South | M53: Q2-2023 | N53: =IF(G53>$R$5,"High Outlier",IF(G53<$R$6,"Low Outlier","Normal")) -> Normal
A54: DEAL-00604 | B54: Aditya Pillai | C54: CLI-0043 | D54: DataVault Pro | E54: Email Campaign | F54: Qualification | G54: 154425 | H54: 44938 | K54: 9.6 | L54: North | M54: Q1-2023 | N54: =IF(G54>$R$5,"High Outlier",IF(G54<$R$6,"Low Outlier","Normal")) -> Normal
A55: DEAL-00954 | B55: Riya Das | C55: CLI-0208 | D55: DevOps Accelerator | E55: Trade Show | F55: Proposal Sent | G55: 225199 | H55: 45735 | L55: East | M55: Q1-2025 | N55: =IF(G55>$R$5,"High Outlier",IF(G55<$R$6,"Low Outlier","Normal")) -> Normal
A56: DEAL-01107 | B56: Rahul Patel | C56: CLI-0005 | D56: SecureNet Suite | E56: Cold Outreach | F56: Negotiation | G56: 487991 | H56: 45655 | L56: West | M56: Q4-2024 | N56: =IF(G56>$R$5,"High Outlier",IF(G56<$R$6,"Low Outlier","Normal")) -> Normal
A57: DEAL-00597 | B57: Neha Pillai | C57: CLI-0230 | D57: DevOps Accelerator | E57: Email Campaign | F57: Closed Won | G57: 360231 | H57: 45708 | I57: 45855 | J57: 147 | K57: 19.5 | L57: West | M57: Q1-2025 | N57: =IF(G57>$R$5,"High Outlier",IF(G57<$R$6,"Low Outlier","Normal")) -> Normal
A58: DEAL-01404 | B58: Deepika Das | C58: CLI-0286 | D58: AI Insights Module | E58: LinkedIn Campaign | F58: Closed Won | G58: 128919 | H58: 45739 | I58: 45836 | J58: 97 | K58: 5 | L58: West | M58: Q1-2025 | N58: =IF(G58>$R$5,"High Outlier",IF(G58<$R$6,"Low Outlier","Normal")) -> Normal
A59: DEAL-02242 | B59: Aditya Pillai | C59: CLI-0002 | D59: DataVault Pro | E59: Referral | F59: Proposal Sent | G59: 422278 | H59: 45532 | K59: 13.7 | L59: East | M59: Q3-2024 | N59: =IF(G59>$R$5,"High Outlier",IF(G59<$R$6,"Low Outlier","Normal")) -> Normal
A60: DEAL-02405 | B60: Rohit Mehta | C60: CLI-0077 | D60: SecureNet Suite | E60: Webinar | F60: Negotiation | G60: 36712 | H60: 45136 | K60: 5.8 | L60: South | M60: Q3-2023 | N60: =IF(G60>$R$5,"High Outlier",IF(G60<$R$6,"Low Outlier","Normal")) -> Normal
A61: DEAL-00721 | B61: Arjun Rao | C61: CLI-0135 | D61: AnalyticsEdge | E61: Google Ads | F61: Qualification | G61: 390892 | H61: 45327 | K61: 6.7 | L61: South | M61: Q1-2024 | N61: =IF(G61>$R$5,"High Outlier",IF(G61<$R$6,"Low Outlier","Normal")) -> Normal
A62: DEAL-00504 | B62: Siddharth Gupta | C62: CLI-0237 | D62: DataVault Pro | E62: Webinar | F62: Negotiation | G62: 12937 | H62: 45119 | L62: West | M62: Q3-2023 | N62: =IF(G62>$R$5,"High Outlier",IF(G62<$R$6,"Low Outlier","Normal")) -> Normal
A63: DEAL-00937 | B63: Rahul Patel | C63: CLI-0060 | D63: AnalyticsEdge | E63: Cold Outreach | F63: Closed Won | G63: 324521 | H63: 45500 | I63: 45644 | J63: 144 | K63: 18.2 | L63: West | M63: Q3-2024 | N63: =IF(G63>$R$5,"High Outlier",IF(G63<$R$6,"Low Outlier","Normal")) -> Normal
A64: DEAL-01769 | B64: Deepika Das | C64: CLI-0208 | D64: AI Insights Module | E64: Referral | F64: Proposal Sent | G64: 113876 | H64: 45744 | L64: South | M64: Q1-2025 | N64: =IF(G64>$R$5,"High Outlier",IF(G64<$R$6,"Low Outlier","Normal")) -> Normal
A65: DEAL-01725 | B65: Aditya Pillai | C65: CLI-0197 | D65: CloudShift Platform | E65: Webinar | F65: Proposal Sent | G65: 499086 | H65: 44931 | K65: 4.9 | L65: East | M65: Q1-2023 | N65: =IF(G65>$R$5,"High Outlier",IF(G65<$R$6,"Low Outlier","Normal")) -> Normal
A66: DEAL-00951 | B66: Ananya Sharma | C66: CLI-0063 | D66: CloudShift Platform | E66: Email Campaign | F66: Closed Lost | G66: 139182 | H66: 45317 | I66: 45343 | J66: 26 | L66: North | M66: Q1-2024 | N66: =IF(G66>$R$5,"High Outlier",IF(G66<$R$6,"Low Outlier","Normal")) -> Normal
A67: DEAL-00313 | B67: Siddharth Joshi | C67: CLI-0063 | D67: DevOps Accelerator | E67: Webinar | F67: Prospecting | G67: 244478 | H67: 45052 | K67: 0.6 | L67: South | M67: Q2-2023 | N67: =IF(G67>$R$5,"High Outlier",IF(G67<$R$6,"Low Outlier","Normal")) -> Normal
A68: DEAL-00726 | B68: Vikram Patel | C68: CLI-0251 | D68: DevOps Accelerator | E68: Trade Show | F68: Closed Won | G68: 108751 | H68: 45732 | I68: 45782 | J68: 50 | K68: 17.2 | L68: South | M68: Q1-2025 | N68: =IF(G68>$R$5,"High Outlier",IF(G68<$R$6,"Low Outlier","Normal")) -> Normal
A69: DEAL-01062 | B69: Ananya Sharma | C69: CLI-0243 | D69: SecureNet Suite | E69: LinkedIn Campaign | F69: Proposal Sent | G69: 387686 | H69: 45006 | K69: 8.5 | L69: East | M69: Q1-2023 | N69: =IF(G69>$R$5,"High Outlier",IF(G69<$R$6,"Low Outlier","Normal")) -> Normal
A70: DEAL-00072 | B70: Neha Pillai | C70: CLI-0228 | D70: SecureNet Suite | E70: Email Campaign | F70: Closed Won | G70: 42234 | H70: 45069 | I70: 45232 | J70: 163 | K70: 15.9 | L70: North | M70: Q2-2023 | N70: =IF(G70>$R$5,"High Outlier",IF(G70<$R$6,"Low Outlier","Normal")) -> Normal
A71: DEAL-00593 | B71: Meera Reddy | C71: CLI-0084 | D71: DevOps Accelerator | E71: LinkedIn Campaign | F71: Qualification | G71: 141423 | H71: 45602 | K71: 4.5 | L71: West | M71: Q4-2024 | N71: =IF(G71>$R$5,"High Outlier",IF(G71<$R$6,"Low Outlier","Normal")) -> Normal
A72: DEAL-00633 | B72: Rahul Patel | C72: CLI-0275 | D72: DataVault Pro | E72: Cold Outreach | F72: Closed Lost | G72: 233514 | H72: 45313 | I72: 45349 | J72: 36 | K72: 7.4 | L72: West | M72: Q1-2024 | N72: =IF(G72>$R$5,"High Outlier",IF(G72<$R$6,"Low Outlier","Normal")) -> Normal
A73: DEAL-00241 | B73: Rohit Mehta | C73: CLI-0292 | D73: CloudShift Platform | E73: Google Ads | F73: Qualification | G73: 316458 | H73: 45594 | K73: 11.3 | L73: South | M73: Q4-2024 | N73: =IF(G73>$R$5,"High Outlier",IF(G73<$R$6,"Low Outlier","Normal")) -> Normal
A74: DEAL-00879 | B74: Neha Pillai | C74: CLI-0031 | D74: CloudShift Platform | E74: Referral | F74: Closed Lost | G74: 274493 | H74: 45654 | I74: 45769 | J74: 115 | K74: 0.4 | L74: East | M74: Q4-2024 | N74: =IF(G74>$R$5,"High Outlier",IF(G74<$R$6,"Low Outlier","Normal")) -> Normal
A75: DEAL-01532 | B75: Arjun Rao | C75: CLI-0109 | D75: CloudShift Platform | E75: Google Ads | F75: Negotiation | G75: 187167 | H75: 45073 | L75: South | M75: Q2-2023 | N75: =IF(G75>$R$5,"High Outlier",IF(G75<$R$6,"Low Outlier","Normal")) -> Normal
A76: DEAL-02348 | B76: Meera Reddy | C76: CLI-0295 | D76: SecureNet Suite | E76: LinkedIn Campaign | F76: Closed Lost | G76: 263320 | H76: 45404 | I76: 45429 | J76: 25 | L76: North | M76: Q2-2024 | N76: =IF(G76>$R$5,"High Outlier",IF(G76<$R$6,"Low Outlier","Normal")) -> Normal
A77: DEAL-01079 | B77: Amit Pillai | C77: CLI-0172 | D77: CloudShift Platform | E77: Referral | F77: Prospecting | G77: 168215 | H77: 45370 | K77: 12.7 | L77: North | M77: Q1-2024 | N77: =IF(G77>$R$5,"High Outlier",IF(G77<$R$6,"Low Outlier","Normal")) -> Normal
A78: DEAL-01305 | B78: Amit Pillai | C78: CLI-0206 | D78: SecureNet Suite | E78: Google Ads | F78: Closed Won | G78: 20087 | H78: 45455 | I78: 45599 | J78: 144 | K78: 24.1 | L78: South | M78: Q2-2024 | N78: =IF(G78>$R$5,"High Outlier",IF(G78<$R$6,"Low Outlier","Normal")) -> Normal
A79: DEAL-00187 | B79: Siddharth Gupta | C79: CLI-0180 | D79: AI Insights Module | E79: Referral | F79: Closed Won | G79: 384150 | H79: 45434 | I79: 45583 | J79: 149 | K79: 13.1 | L79: East | M79: Q2-2024 | N79: =IF(G79>$R$5,"High Outlier",IF(G79<$R$6,"Low Outlier","Normal")) -> Normal
A80: DEAL-02217 | B80: Ananya Sharma | C80: CLI-0270 | D80: SecureNet Suite | E80: Referral | F80: Negotiation | G80: 354315 | H80: 44983 | K80: 10.3 | L80: East | M80: Q1-2023 | N80: =IF(G80>$R$5,"High Outlier",IF(G80<$R$6,"Low Outlier","Normal")) -> Normal
A81: DEAL-00347 | B81: Siddharth Gupta | C81: CLI-0077 | D81: AI Insights Module | E81: Google Ads | F81: Closed Won | G81: 124965 | H81: 45213 | I81: 45273 | J81: 60 | K81: 0.4 | L81: North | M81: Q4-2023 | N81: =IF(G81>$R$5,"High Outlier",IF(G81<$R$6,"Low Outlier","Normal")) -> Normal
A82: DEAL-00971 | B82: Aditya Pillai | C82: CLI-0087 | D82: AnalyticsEdge | E82: Webinar | F82: Closed Lost | G82: 410731 | H82: 44989 | I82: 45082 | J82: 93 | K82: 4.7 | L82: South | M82: Q1-2023 | N82: =IF(G82>$R$5,"High Outlier",IF(G82<$R$6,"Low Outlier","Normal")) -> Normal
A83: DEAL-00709 | B83: Aditya Pillai | C83: CLI-0183 | D83: AI Insights Module | E83: Email Campaign | F83: Closed Lost | G83: 272141 | H83: 44958 | I83: 45038 | J83: 80 | K83: 12.9 | L83: North | M83: Q1-2023 | N83: =IF(G83>$R$5,"High Outlier",IF(G83<$R$6,"Low Outlier","Normal")) -> Normal
A84: DEAL-00383 | B84: Ananya Sharma | C84: CLI-0138 | D84: AI Insights Module | E84: LinkedIn Campaign | F84: Prospecting | G84: 400965 | H84: 45357 | K84: 10.4 | L84: West | M84: Q1-2024 | N84: =IF(G84>$R$5,"High Outlier",IF(G84<$R$6,"Low Outlier","Normal")) -> Normal
A85: DEAL-01809 | B85: Siddharth Joshi | C85: CLI-0103 | D85: CloudShift Platform | E85: Organic Search | F85: Negotiation | G85: 217920 | H85: 45628 | L85: West | M85: Q4-2024 | N85: =IF(G85>$R$5,"High Outlier",IF(G85<$R$6,"Low Outlier","Normal")) -> Normal
A86: DEAL-00077 | B86: Rahul Patel | C86: CLI-0075 | D86: DataVault Pro | E86: Trade Show | F86: Closed Lost | G86: 478494 | H86: 45545 | I86: 45668 | J86: 123 | K86: 6.8 | L86: West | M86: Q3-2024 | N86: =IF(G86>$R$5,"High Outlier",IF(G86<$R$6,"Low Outlier","Normal")) -> Normal
A87: DEAL-00423 | B87: Vikram Patel | C87: CLI-0146 | D87: AnalyticsEdge | E87: Webinar | F87: Proposal Sent | G87: 366026 | H87: 45266 | K87: 5.9 | L87: East | M87: Q4-2023 | N87: =IF(G87>$R$5,"High Outlier",IF(G87<$R$6,"Low Outlier","Normal")) -> Normal
A88: DEAL-01237 | B88: Amit Pillai | C88: CLI-0033 | D88: AI Insights Module | E88: Email Campaign | F88: Closed Won | G88: 210971 | H88: 45503 | I88: 45562 | J88: 59 | K88: 19.3 | L88: West | M88: Q3-2024 | N88: =IF(G88>$R$5,"High Outlier",IF(G88<$R$6,"Low Outlier","Normal")) -> Normal
A89: DEAL-01217 | B89: Amit Pillai | C89: CLI-0017 | D89: AnalyticsEdge | E89: Webinar | F89: Qualification | G89: 392720 | H89: 45444 | K89: 5.8 | L89: South | M89: Q2-2024 | N89: =IF(G89>$R$5,"High Outlier",IF(G89<$R$6,"Low Outlier","Normal")) -> Normal
A90: DEAL-01724 | B90: Neha Pillai | C90: CLI-0090 | D90: AnalyticsEdge | E90: LinkedIn Campaign | F90: Negotiation | G90: 268444 | H90: 45424 | L90: East | M90: Q2-2024 | N90: =IF(G90>$R$5,"High Outlier",IF(G90<$R$6,"Low Outlier","Normal")) -> Normal
A91: DEAL-00151 | B91: Siddharth Gupta | C91: CLI-0099 | D91: CloudShift Platform | E91: Google Ads | F91: Qualification | G91: 202104 | H91: 45686 | K91: 8.8 | L91: East | M91: Q1-2025 | N91: =IF(G91>$R$5,"High Outlier",IF(G91<$R$6,"Low Outlier","Normal")) -> Normal
A92: DEAL-00418 | B92: Deepika Das | C92: CLI-0295 | D92: AI Insights Module | E92: Referral | F92: Qualification | G92: 367272 | H92: 45118 | K92: 5 | L92: North | M92: Q3-2023 | N92: =IF(G92>$R$5,"High Outlier",IF(G92<$R$6,"Low Outlier","Normal")) -> Normal
A93: DEAL-01039 | B93: Priya Kumar | C93: CLI-0212 | D93: AI Insights Module | E93: Organic Search | F93: Closed Lost | G93: 199001 | H93: 45374 | I93: 45483 | J93: 109 | L93: West | M93: Q1-2024 | N93: =IF(G93>$R$5,"High Outlier",IF(G93<$R$6,"Low Outlier","Normal")) -> Normal
A94: DEAL-01871 | B94: Siddharth Joshi | C94: CLI-0026 | D94: DevOps Accelerator | E94: Email Campaign | F94: Qualification | G94: 321550 | H94: 45119 | L94: East | M94: Q3-2023 | N94: =IF(G94>$R$5,"High Outlier",IF(G94<$R$6,"Low Outlier","Normal")) -> Normal
A95: DEAL-01438 | B95: Ananya Sharma | C95: CLI-0259 | D95: SecureNet Suite | E95: Referral | F95: Negotiation | G95: 376342 | H95: 45344 | K95: 1.9 | L95: East | M95: Q1-2024 | N95: =IF(G95>$R$5,"High Outlier",IF(G95<$R$6,"Low Outlier","Normal")) -> Normal
A96: DEAL-02064 | B96: Rohit Mehta | C96: CLI-0248 | D96: DevOps Accelerator | E96: Referral | F96: Closed Lost | G96: 119352 | H96: 45346 | I96: 45410 | J96: 64 | K96: 5.9 | L96: South | M96: Q1-2024 | N96: =IF(G96>$R$5,"High Outlier",IF(G96<$R$6,"Low Outlier","Normal")) -> Normal
A97: DEAL-00140 | B97: Aditya Pillai | C97: CLI-0261 | D97: DevOps Accelerator | E97: LinkedIn Campaign | F97: Prospecting | G97: 313108 | H97: 45468 | L97: East | M97: Q2-2024 | N97: =IF(G97>$R$5,"High Outlier",IF(G97<$R$6,"Low Outlier","Normal")) -> Normal
A98: DEAL-01175 | B98: Ananya Sharma | C98: CLI-0273 | D98: DataVault Pro | E98: Cold Outreach | F98: Negotiation | G98: 254116 | H98: 45674 | K98: 11 | L98: West | M98: Q1-2025 | N98: =IF(G98>$R$5,"High Outlier",IF(G98<$R$6,"Low Outlier","Normal")) -> Normal
A99: DEAL-01177 | B99: Rahul Patel | C99: CLI-0122 | D99: CloudShift Platform | E99: LinkedIn Campaign | F99: Negotiation | G99: 336032 | H99: 45124 | K99: 4.6 | L99: North | M99: Q3-2023 | N99: =IF(G99>$R$5,"High Outlier",IF(G99<$R$6,"Low Outlier","Normal")) -> Normal
A100: DEAL-02224 | B100: Deepika Das | C100: CLI-0166 | D100: DevOps Accelerator | E100: Google Ads | F100: Closed Won | G100: 345065 | H100: 45194 | I100: 45267 | J100: 73 | K100: 2.5 | L100: West | M100: Q3-2023 | N100: =IF(G100>$R$5,"High Outlier",IF(G100<$R$6,"Low Outlier","Normal")) -> Normal
...

Sheet Cleaned_Finance_Expenses
A1: Expense_ID | B1: Department | C1: Category | D1: Vendor | E1: Amount_INR | F1: Budget_Allocated_INR | G1: Recomputed_Variance_INR | H1: Variance_INR | I1: Expense_Date | J1: Approval_Status | K1: Payment_Mode | L1: Fiscal_Year | M1: Remarks | N1: Amount_Type_Flag | O1: High_Value_Pending_Rejected_Flag
A2: EXP-00594 | B2: Unspecified | C2: Cloud Infrastructure | D2: Slack | E2: 209189 | F2: 170793.17 | G2: =IF(F2="","",E2-F2) -> 38395.83 | H2: 38395.83 | I2: 45126 | J2: Pending | K2: Vendor Credit | L2: FY2023-2024 | M2: Under review | N2: =IF(E2<0,"Credit/Refund","Expense") -> Expense | O2: =IF(AND(OR(J2="Pending",J2="Rejected"),E2>200000),"Flag: High-Value "&J2,"") -> Flag: High-Value Pending
A3: EXP-00495 | B3: Operations | C3: Utilities | D3: HubSpot | E3: 6214 | F3: 7523.05 | G3: =IF(F3="","",E3-F3) -> -1309.05 | H3: -1309.05 | I3: 45209 | J3: Approved | K3: Bank Transfer | L3: FY2023-2024 | M3: Recurring | N3: =IF(E3<0,"Credit/Refund","Expense") -> Expense | O3: =IF(AND(OR(J3="Pending",J3="Rejected"),E3>200000),"Flag: High-Value "&J3,"")
A4: EXP-00587 | B4: Sales | C4: Marketing Spend | D4: SAP | E4: 499533 | F4: 550589.56 | G4: =IF(F4="","",E4-F4) -> -51056.56 | H4: -51056.56 | I4: 45310 | J4: Approved | K4: Bank Transfer | L4: FY2023-2024 | M4: Recurring | N4: =IF(E4<0,"Credit/Refund","Expense") -> Expense | O4: =IF(AND(OR(J4="Pending",J4="Rejected"),E4>200000),"Flag: High-Value "&J4,"")
A5: EXP-00178 | B5: Finance | C5: Utilities | D5: Infosys | E5: 403234 | F5: 426617.54 | G5: =IF(F5="","",E5-F5) -> -23383.54 | H5: -23383.54 | I5: 45732 | J5: Approved | K5: Bank Transfer | L5: FY2024-2025 | N5: =IF(E5<0,"Credit/Refund","Expense") -> Expense | O5: =IF(AND(OR(J5="Pending",J5="Rejected"),E5>200000),"Flag: High-Value "&J5,"")
A6: EXP-00869 | B6: Unspecified | C6: Cloud Infrastructure | D6: TCS | E6: 187461 | F6: 156297.94 | G6: =IF(F6="","",E6-F6) -> 31163.06 | H6: 31163.06 | I6: 44963 | J6: Approved | K6: Credit Card | L6: FY2022-2023 | N6: =IF(E6<0,"Credit/Refund","Expense") -> Expense | O6: =IF(AND(OR(J6="Pending",J6="Rejected"),E6>200000),"Flag: High-Value "&J6,"")
A7: EXP-00674 | B7: Sales | C7: Hardware | D7: TCS | E7: 352393 | F7: 449410.33 | G7: =IF(F7="","",E7-F7) -> -97017.33 | H7: -97017.33 | I7: 45365 | J7: Approved | K7: Bank Transfer | L7: FY2023-2024 | N7: =IF(E7<0,"Credit/Refund","Expense") -> Expense | O7: =IF(AND(OR(J7="Pending",J7="Rejected"),E7>200000),"Flag: High-Value "&J7,"")
A8: EXP-00181 | B8: Engineering | C8: Hardware | D8: Slack | E8: 361946 | F8: 354476.37 | G8: =IF(F8="","",E8-F8) -> 7469.63 | H8: 7469.63 | I8: 45152 | J8: Pending | K8: Vendor Credit | L8: FY2023-2024 | M8: Urgent | N8: =IF(E8<0,"Credit/Refund","Expense") -> Expense | O8: =IF(AND(OR(J8="Pending",J8="Rejected"),E8>200000),"Flag: High-Value "&J8,"") -> Flag: High-Value Pending
A9: EXP-00277 | B9: Support | C9: Office Supplies | D9: Wipro | E9: 398503 | F9: 438557.67 | G9: =IF(F9="","",E9-F9) -> -40054.67 | H9: -40054.67 | I9: 45145 | J9: Approved | K9: Credit Card | L9: FY2023-2024 | N9: =IF(E9<0,"Credit/Refund","Expense") -> Expense | O9: =IF(AND(OR(J9="Pending",J9="Rejected"),E9>200000),"Flag: High-Value "&J9,"")
A10: EXP-00515 | B10: Support | C10: Consulting Fees | D10: Oracle | E10: 345565 | F10: 382355.25 | G10: =IF(F10="","",E10-F10) -> -36790.25 | H10: -36790.25 | I10: 45437 | J10: Approved | K10: Vendor Credit | L10: FY2024-2025 | M10: Duplicate entry | N10: =IF(E10<0,"Credit/Refund","Expense") -> Expense | O10: =IF(AND(OR(J10="Pending",J10="Rejected"),E10>200000),"Flag: High-Value "&J10,"")
A11: EXP-00339 | B11: Engineering | C11: Hardware | D11: HubSpot | E11: 441930 | F11: 426169.24 | G11: =IF(F11="","",E11-F11) -> 15760.76 | H11: 15760.76 | I11: 45740 | J11: Approved | K11: Credit Card | L11: FY2024-2025 | M11: Under review | N11: =IF(E11<0,"Credit/Refund","Expense") -> Expense | O11: =IF(AND(OR(J11="Pending",J11="Rejected"),E11>200000),"Flag: High-Value "&J11,"")
A12: EXP-00555 | B12: Unspecified | C12: Office Supplies | D12: SAP | E12: 304214 | F12: 345611.18 | G12: =IF(F12="","",E12-F12) -> -41397.18 | H12: -41397.18 | I12: 45689 | J12: Approved | K12: Bank Transfer | L12: FY2024-2025 | M12: Recurring | N12: =IF(E12<0,"Credit/Refund","Expense") -> Expense | O12: =IF(AND(OR(J12="Pending",J12="Rejected"),E12>200000),"Flag: High-Value "&J12,"")
A13: EXP-00803 | B13: Support | C13: Travel | D13: Freshdesk | E13: 65791 | F13: 59739.7 | G13: =IF(F13="","",E13-F13) -> 6051.3 | H13: 6051.3 | I13: 45346 | J13: Approved | K13: Petty Cash | L13: FY2023-2024 | M13: Under review | N13: =IF(E13<0,"Credit/Refund","Expense") -> Expense | O13: =IF(AND(OR(J13="Pending",J13="Rejected"),E13>200000),"Flag: High-Value "&J13,"")
A14: EXP-00875 | B14: Engineering | C14: Software Licenses | D14: Google Cloud | E14: 49237 | G14: =IF(F14="","",E14-F14) | H14: 7036.11 | I14: 45457 | J14: Pending | K14: Petty Cash | L14: FY2024-2025 | M14: Duplicate entry | N14: =IF(E14<0,"Credit/Refund","Expense") -> Expense | O14: =IF(AND(OR(J14="Pending",J14="Rejected"),E14>200000),"Flag: High-Value "&J14,"")
A15: EXP-00691 | B15: HR | C15: Office Supplies | D15: TCS | E15: 365283 | F15: 359381.54 | G15: =IF(F15="","",E15-F15) -> 5901.46 | H15: 5901.46 | I15: 45645 | J15: Approved | K15: Credit Card | L15: FY2024-2025 | N15: =IF(E15<0,"Credit/Refund","Expense") -> Expense | O15: =IF(AND(OR(J15="Pending",J15="Rejected"),E15>200000),"Flag: High-Value "&J15,"")
A16: EXP-00233 | B16: HR | C16: Consulting Fees | D16: Google Cloud | E16: 201346 | F16: 197464.53 | G16: =IF(F16="","",E16-F16) -> 3881.47 | I16: 45719 | J16: Pending | K16: Bank Transfer | L16: FY2024-2025 | M16: Under review | N16: =IF(E16<0,"Credit/Refund","Expense") -> Expense | O16: =IF(AND(OR(J16="Pending",J16="Rejected"),E16>200000),"Flag: High-Value "&J16,"") -> Flag: High-Value Pending
A17: EXP-00071 | B17: Sales | C17: Hardware | D17: HubSpot | E17: 375484 | F17: 303740.88 | G17: =IF(F17="","",E17-F17) -> 71743.12 | H17: 71743.12 | I17: 45454 | J17: Pending | K17: Bank Transfer | L17: FY2024-2025 | M17: One-time | N17: =IF(E17<0,"Credit/Refund","Expense") -> Expense | O17: =IF(AND(OR(J17="Pending",J17="Rejected"),E17>200000),"Flag: High-Value "&J17,"") -> Flag: High-Value Pending
A18: EXP-00860 | B18: Operations | C18: Cloud Infrastructure | D18: Wipro | E18: 91274 | F18: 117271.6 | G18: =IF(F18="","",E18-F18) -> -25997.6 | H18: -25997.6 | I18: 45367 | J18: Approved | K18: Petty Cash | L18: FY2023-2024 | N18: =IF(E18<0,"Credit/Refund","Expense") -> Expense | O18: =IF(AND(OR(J18="Pending",J18="Rejected"),E18>200000),"Flag: High-Value "&J18,"")
A19: EXP-00607 | B19: Finance | C19: Hardware | D19: Jira | E19: 58546 | F19: 54790.73 | G19: =IF(F19="","",E19-F19) -> 3755.27 | H19: 3755.27 | I19: 45324 | J19: Approved | K19: Petty Cash | L19: FY2023-2024 | M19: Under review | N19: =IF(E19<0,"Credit/Refund","Expense") -> Expense | O19: =IF(AND(OR(J19="Pending",J19="Rejected"),E19>200000),"Flag: High-Value "&J19,"")
A20: EXP-00651 | B20: Unspecified | C20: Marketing Spend | D20: SAP | E20: 10904 | F20: 13676.8 | G20: =IF(F20="","",E20-F20) -> -2772.8 | H20: -2772.8 | I20: 44973 | J20: Approved | K20: Vendor Credit | L20: FY2022-2023 | M20: Duplicate entry | N20: =IF(E20<0,"Credit/Refund","Expense") -> Expense | O20: =IF(AND(OR(J20="Pending",J20="Rejected"),E20>200000),"Flag: High-Value "&J20,"")
A21: EXP-00652 | B21: Operations | C21: Utilities | D21: AWS | E21: 65481 | F21: 81303.61 | G21: =IF(F21="","",E21-F21) -> -15822.61 | H21: -15822.61 | I21: 44962 | J21: Pending | K21: Vendor Credit | L21: FY2022-2023 | M21: Duplicate entry | N21: =IF(E21<0,"Credit/Refund","Expense") -> Expense | O21: =IF(AND(OR(J21="Pending",J21="Rejected"),E21>200000),"Flag: High-Value "&J21,"")
A22: EXP-00369 | B22: Marketing | C22: Marketing Spend | D22: HubSpot | E22: 66000 | F22: 78840.27 | G22: =IF(F22="","",E22-F22) -> -12840.27 | H22: -12840.27 | I22: 45341 | J22: Approved | K22: Credit Card | L22: FY2023-2024 | M22: Under review | N22: =IF(E22<0,"Credit/Refund","Expense") -> Expense | O22: =IF(AND(OR(J22="Pending",J22="Rejected"),E22>200000),"Flag: High-Value "&J22,"")
A23: EXP-00721 | B23: Finance | C23: Office Supplies | D23: Slack | E23: 32147 | F23: 36235.03 | G23: =IF(F23="","",E23-F23) -> -4088.03 | H23: -4088.03 | I23: 45247 | J23: Approved | K23: Credit Card | L23: FY2023-2024 | N23: =IF(E23<0,"Credit/Refund","Expense") -> Expense | O23: =IF(AND(OR(J23="Pending",J23="Rejected"),E23>200000),"Flag: High-Value "&J23,"")
A24: EXP-00390 | B24: Unspecified | C24: Consulting Fees | D24: Wipro | E24: 312310 | F24: 339411.41 | G24: =IF(F24="","",E24-F24) -> -27101.41 | H24: -27101.41 | I24: 45270 | J24: Pending | K24: Bank Transfer | L24: FY2023-2024 | M24: Duplicate entry | N24: =IF(E24<0,"Credit/Refund","Expense") -> Expense | O24: =IF(AND(OR(J24="Pending",J24="Rejected"),E24>200000),"Flag: High-Value "&J24,"") -> Flag: High-Value Pending
A25: EXP-00520 | B25: HR | C25: Utilities | D25: Infosys | E25: 145866 | F25: 176369.11 | G25: =IF(F25="","",E25-F25) -> -30503.11 | H25: -30503.11 | I25: 45589 | J25: Approved | K25: Petty Cash | L25: FY2024-2025 | M25: Recurring | N25: =IF(E25<0,"Credit/Refund","Expense") -> Expense | O25: =IF(AND(OR(J25="Pending",J25="Rejected"),E25>200000),"Flag: High-Value "&J25,"")
A26: EXP-00971 | B26: Finance | C26: Training | D26: Oracle | E26: -270391 | F26: 224861.48 | G26: =IF(F26="","",E26-F26) -> -495252.48 | H26: 45529.52 | I26: 44992 | J26: Approved | K26: Credit Card | L26: FY2022-2023 | M26: Duplicate entry | N26: =IF(E26<0,"Credit/Refund","Expense") -> Credit/Refund | O26: =IF(AND(OR(J26="Pending",J26="Rejected"),E26>200000),"Flag: High-Value "&J26,"")
A27: EXP-00411 | B27: HR | C27: Hardware | D27: Microsoft Azure | E27: 410046 | F27: 483620.72 | G27: =IF(F27="","",E27-F27) -> -73574.72 | H27: -73574.72 | I27: 45456 | J27: Approved | K27: Petty Cash | L27: FY2024-2025 | N27: =IF(E27<0,"Credit/Refund","Expense") -> Expense | O27: =IF(AND(OR(J27="Pending",J27="Rejected"),E27>200000),"Flag: High-Value "&J27,"")
A28: EXP-00354 | B28: Sales | C28: Salaries | D28: Oracle | E28: 406494 | G28: =IF(F28="","",E28-F28) | H28: -13532 | I28: 45553 | J28: Approved | K28: Credit Card | L28: FY2024-2025 | M28: Recurring | N28: =IF(E28<0,"Credit/Refund","Expense") -> Expense | O28: =IF(AND(OR(J28="Pending",J28="Rejected"),E28>200000),"Flag: High-Value "&J28,"")
A29: EXP-00600 | B29: Engineering | C29: Travel | D29: Zoom | E29: 66859 | F29: 75521.94 | G29: =IF(F29="","",E29-F29) -> -8662.94 | H29: -8662.94 | I29: 45442 | J29: Approved | K29: Petty Cash | L29: FY2024-2025 | N29: =IF(E29<0,"Credit/Refund","Expense") -> Expense | O29: =IF(AND(OR(J29="Pending",J29="Rejected"),E29>200000),"Flag: High-Value "&J29,"")
A30: EXP-00034 | B30: Support | C30: Consulting Fees | D30: Oracle | E30: 389612 | F30: 356713.15 | G30: =IF(F30="","",E30-F30) -> 32898.85 | H30: 32898.85 | I30: 45486 | J30: Pending | K30: Petty Cash | L30: FY2024-2025 | N30: =IF(E30<0,"Credit/Refund","Expense") -> Expense | O30: =IF(AND(OR(J30="Pending",J30="Rejected"),E30>200000),"Flag: High-Value "&J30,"") -> Flag: High-Value Pending
A31: EXP-00200 | B31: Sales | C31: Salaries | D31: TCS | E31: 397643 | F31: 366588.32 | G31: =IF(F31="","",E31-F31) -> 31054.68 | I31: 45309 | J31: Pending | K31: Petty Cash | L31: FY2023-2024 | N31: =IF(E31<0,"Credit/Refund","Expense") -> Expense | O31: =IF(AND(OR(J31="Pending",J31="Rejected"),E31>200000),"Flag: High-Value "&J31,"") -> Flag: High-Value Pending
A32: EXP-00925 | B32: Sales | C32: Software Licenses | D32: Google Cloud | E32: 367122 | F32: 465065.53 | G32: =IF(F32="","",E32-F32) -> -97943.53 | H32: -97943.53 | I32: 45084 | J32: Pending | K32: Credit Card | L32: FY2023-2024 | M32: One-time | N32: =IF(E32<0,"Credit/Refund","Expense") -> Expense | O32: =IF(AND(OR(J32="Pending",J32="Rejected"),E32>200000),"Flag: High-Value "&J32,"") -> Flag: High-Value Pending
A33: EXP-00546 | B33: Marketing | C33: Travel | D33: Adobe | E33: 65667 | F33: 72499.12 | G33: =IF(F33="","",E33-F33) -> -6832.12 | H33: -6832.12 | I33: 45077 | J33: Approved | K33: Petty Cash | L33: FY2023-2024 | N33: =IF(E33<0,"Credit/Refund","Expense") -> Expense | O33: =IF(AND(OR(J33="Pending",J33="Rejected"),E33>200000),"Flag: High-Value "&J33,"")
A34: EXP-00602 | B34: Unspecified | C34: Salaries | D34: Wipro | E34: 350446 | F34: 293167.5 | G34: =IF(F34="","",E34-F34) -> 57278.5 | H34: 57278.5 | I34: 45395 | J34: Approved | K34: Vendor Credit | L34: FY2024-2025 | N34: =IF(E34<0,"Credit/Refund","Expense") -> Expense | O34: =IF(AND(OR(J34="Pending",J34="Rejected"),E34>200000),"Flag: High-Value "&J34,"")
A35: EXP-00083 | B35: Support | C35: Maintenance | D35: Wipro | E35: 215496 | F35: 269360.68 | G35: =IF(F35="","",E35-F35) -> -53864.68 | I35: 45427 | J35: Rejected | K35: Petty Cash | L35: FY2024-2025 | M35: Duplicate entry | N35: =IF(E35<0,"Credit/Refund","Expense") -> Expense | O35: =IF(AND(OR(J35="Pending",J35="Rejected"),E35>200000),"Flag: High-Value "&J35,"") -> Flag: High-Value Rejected
A36: EXP-00750 | B36: Sales | C36: Recruitment | D36: Freshdesk | E36: 7227 | F36: 9023.9 | G36: =IF(F36="","",E36-F36) -> -1796.9 | H36: -1796.9 | I36: 45131 | J36: Approved | K36: Vendor Credit | L36: FY2023-2024 | N36: =IF(E36<0,"Credit/Refund","Expense") -> Expense | O36: =IF(AND(OR(J36="Pending",J36="Rejected"),E36>200000),"Flag: High-Value "&J36,"")
A37: EXP-00172 | B37: Operations | C37: Travel | D37: AWS | E37: 481644 | F37: 431586.58 | G37: =IF(F37="","",E37-F37) -> 50057.42 | H37: 50057.42 | I37: 45338 | J37: Approved | K37: Vendor Credit | L37: FY2023-2024 | M37: Urgent | N37: =IF(E37<0,"Credit/Refund","Expense") -> Expense | O37: =IF(AND(OR(J37="Pending",J37="Rejected"),E37>200000),"Flag: High-Value "&J37,"")
A38: EXP-00531 | B38: Sales | C38: Recruitment | D38: AWS | E38: -214583 | F38: 220195.61 | G38: =IF(F38="","",E38-F38) -> -434778.61 | H38: -5612.61 | I38: 45157 | J38: Approved | K38: Petty Cash | L38: FY2023-2024 | N38: =IF(E38<0,"Credit/Refund","Expense") -> Credit/Refund | O38: =IF(AND(OR(J38="Pending",J38="Rejected"),E38>200000),"Flag: High-Value "&J38,"")
A39: EXP-00337 | B39: Sales | C39: Utilities | D39: HubSpot | E39: 71717 | F39: 89231.77 | G39: =IF(F39="","",E39-F39) -> -17514.77 | H39: -17514.77 | I39: 45573 | J39: Approved | K39: Credit Card | L39: FY2024-2025 | M39: Urgent | N39: =IF(E39<0,"Credit/Refund","Expense") -> Expense | O39: =IF(AND(OR(J39="Pending",J39="Rejected"),E39>200000),"Flag: High-Value "&J39,"")
A40: EXP-00832 | B40: Engineering | C40: Training | D40: Infosys | E40: 352092 | F40: 424330.22 | G40: =IF(F40="","",E40-F40) -> -72238.22 | H40: -72238.22 | I40: 45540 | J40: Approved | K40: Bank Transfer | L40: FY2024-2025 | M40: One-time | N40: =IF(E40<0,"Credit/Refund","Expense") -> Expense | O40: =IF(AND(OR(J40="Pending",J40="Rejected"),E40>200000),"Flag: High-Value "&J40,"")
A41: EXP-00717 | B41: HR | C41: Office Supplies | D41: Internal | E41: 3606815 | F41: 3411626.7 | G41: =IF(F41="","",E41-F41) -> 195188.28 | H41: 195188.28 | I41: 45464 | J41: Pending | K41: Bank Transfer | L41: FY2024-2025 | M41: Recurring | N41: =IF(E41<0,"Credit/Refund","Expense") -> Expense | O41: =IF(AND(OR(J41="Pending",J41="Rejected"),E41>200000),"Flag: High-Value "&J41,"") -> Flag: High-Value Pending
A42: EXP-00601 | B42: Sales | C42: Cloud Infrastructure | D42: Wipro | E42: 128850 | F42: 118183.64 | G42: =IF(F42="","",E42-F42) -> 10666.36 | H42: 10666.36 | I42: 45143 | J42: Approved | K42: Vendor Credit | L42: FY2023-2024 | N42: =IF(E42<0,"Credit/Refund","Expense") -> Expense | O42: =IF(AND(OR(J42="Pending",J42="Rejected"),E42>200000),"Flag: High-Value "&J42,"")
A43: EXP-00275 | B43: Operations | C43: Utilities | D43: SAP | E43: 166769 | F43: 196065.31 | G43: =IF(F43="","",E43-F43) -> -29296.31 | H43: -29296.31 | I43: 45175 | J43: Approved | K43: Credit Card | L43: FY2023-2024 | M43: Recurring | N43: =IF(E43<0,"Credit/Refund","Expense") -> Expense | O43: =IF(AND(OR(J43="Pending",J43="Rejected"),E43>200000),"Flag: High-Value "&J43,"")
A44: EXP-00466 | B44: Support | C44: Software Licenses | D44: Adobe | E44: 454117 | G44: =IF(F44="","",E44-F44) | H44: -112004.76 | I44: 45077 | J44: Approved | K44: Vendor Credit | L44: FY2023-2024 | M44: Under review | N44: =IF(E44<0,"Credit/Refund","Expense") -> Expense | O44: =IF(AND(OR(J44="Pending",J44="Rejected"),E44>200000),"Flag: High-Value "&J44,"")
A45: EXP-00663 | B45: Sales | C45: Recruitment | D45: Google Cloud | E45: 225901 | F45: 254208.33 | G45: =IF(F45="","",E45-F45) -> -28307.33 | H45: -28307.33 | I45: 45520 | J45: Approved | K45: Petty Cash | L45: FY2024-2025 | M45: Recurring | N45: =IF(E45<0,"Credit/Refund","Expense") -> Expense | O45: =IF(AND(OR(J45="Pending",J45="Rejected"),E45>200000),"Flag: High-Value "&J45,"")
A46: EXP-00954 | B46: Engineering | C46: Training | D46: AWS | E46: 173047 | F46: 149662.31 | G46: =IF(F46="","",E46-F46) -> 23384.69 | I46: 45249 | J46: Approved | K46: Vendor Credit | L46: FY2023-2024 | M46: Under review | N46: =IF(E46<0,"Credit/Refund","Expense") -> Expense | O46: =IF(AND(OR(J46="Pending",J46="Rejected"),E46>200000),"Flag: High-Value "&J46,"")
A47: EXP-00024 | B47: Finance | C47: Maintenance | D47: Infosys | E47: 247370 | F47: 268703.57 | G47: =IF(F47="","",E47-F47) -> -21333.57 | H47: -21333.57 | I47: 45554 | J47: Approved | K47: Bank Transfer | L47: FY2024-2025 | N47: =IF(E47<0,"Credit/Refund","Expense") -> Expense | O47: =IF(AND(OR(J47="Pending",J47="Rejected"),E47>200000),"Flag: High-Value "&J47,"")
A48: EXP-00430 | B48: Engineering | C48: Marketing Spend | D48: Wipro | E48: 295595 | F48: 333028.71 | G48: =IF(F48="","",E48-F48) -> -37433.71 | H48: -37433.71 | I48: 45555 | J48: Pending | K48: Vendor Credit | L48: FY2024-2025 | M48: Urgent | N48: =IF(E48<0,"Credit/Refund","Expense") -> Expense | O48: =IF(AND(OR(J48="Pending",J48="Rejected"),E48>200000),"Flag: High-Value "&J48,"") -> Flag: High-Value Pending
A49: EXP-00219 | B49: Finance | C49: Training | D49: HubSpot | E49: 344780 | F49: 378391.66 | G49: =IF(F49="","",E49-F49) -> -33611.66 | H49: -33611.66 | I49: 44976 | J49: Approved | K49: Bank Transfer | L49: FY2022-2023 | N49: =IF(E49<0,"Credit/Refund","Expense") -> Expense | O49: =IF(AND(OR(J49="Pending",J49="Rejected"),E49>200000),"Flag: High-Value "&J49,"")
A50: EXP-00318 | B50: Finance | C50: Training | D50: Slack | E50: 228003 | F50: 192790.08 | G50: =IF(F50="","",E50-F50) -> 35212.92 | H50: 35212.92 | I50: 45366 | J50: Approved | K50: Credit Card | L50: FY2023-2024 | M50: Under review | N50: =IF(E50<0,"Credit/Refund","Expense") -> Expense | O50: =IF(AND(OR(J50="Pending",J50="Rejected"),E50>200000),"Flag: High-Value "&J50,"")
A51: EXP-00235 | B51: Support | C51: Training | D51: Internal | E51: 205500 | F51: 166546.9 | G51: =IF(F51="","",E51-F51) -> 38953.1 | H51: 38953.1 | I51: 45180 | J51: Approved | K51: Vendor Credit | L51: FY2023-2024 | M51: Duplicate entry | N51: =IF(E51<0,"Credit/Refund","Expense") -> Expense | O51: =IF(AND(OR(J51="Pending",J51="Rejected"),E51>200000),"Flag: High-Value "&J51,"")
A52: EXP-00231 | B52: Sales | C52: Utilities | D52: Adobe | E52: 336583 | F52: 372109.92 | G52: =IF(F52="","",E52-F52) -> -35526.92 | H52: -35526.92 | I52: 44983 | J52: Approved | K52: Credit Card | L52: FY2022-2023 | M52: Under review | N52: =IF(E52<0,"Credit/Refund","Expense") -> Expense | O52: =IF(AND(OR(J52="Pending",J52="Rejected"),E52>200000),"Flag: High-Value "&J52,"")
A53: EXP-00680 | B53: Support | C53: Recruitment | D53: Jira | E53: 76037 | F53: 88996.48 | G53: =IF(F53="","",E53-F53) -> -12959.48 | H53: -12959.48 | I53: 45229 | J53: Approved | K53: Bank Transfer | L53: FY2023-2024 | N53: =IF(E53<0,"Credit/Refund","Expense") -> Expense | O53: =IF(AND(OR(J53="Pending",J53="Rejected"),E53>200000),"Flag: High-Value "&J53,"")
A54: EXP-00301 | B54: Support | C54: Hardware | D54: Internal | E54: 51292 | F54: 52199.26 | G54: =IF(F54="","",E54-F54) -> -907.26 | H54: -907.26 | I54: 45250 | J54: Approved | K54: Petty Cash | L54: FY2023-2024 | M54: Urgent | N54: =IF(E54<0,"Credit/Refund","Expense") -> Expense | O54: =IF(AND(OR(J54="Pending",J54="Rejected"),E54>200000),"Flag: High-Value "&J54,"")
A55: EXP-00617 | B55: Support | C55: Training | D55: HubSpot | E55: -307191 | F55: 328740.27 | G55: =IF(F55="","",E55-F55) -> -635931.27 | H55: -21549.27 | I55: 45684 | J55: Approved | K55: Bank Transfer | L55: FY2024-2025 | M55: Under review | N55: =IF(E55<0,"Credit/Refund","Expense") -> Credit/Refund | O55: =IF(AND(OR(J55="Pending",J55="Rejected"),E55>200000),"Flag: High-Value "&J55,"")
A56: EXP-00994 | B56: Operations | C56: Marketing Spend | D56: Infosys | E56: 333909 | F56: 401580.86 | G56: =IF(F56="","",E56-F56) -> -67671.86 | H56: -67671.86 | I56: 45317 | J56: Rejected | K56: Bank Transfer | L56: FY2023-2024 | M56: Recurring | N56: =IF(E56<0,"Credit/Refund","Expense") -> Expense | O56: =IF(AND(OR(J56="Pending",J56="Rejected"),E56>200000),"Flag: High-Value "&J56,"") -> Flag: High-Value Rejected
A57: EXP-00548 | B57: Finance | C57: Training | D57: SAP | E57: 325449 | F57: 392529.63 | G57: =IF(F57="","",E57-F57) -> -67080.63 | H57: -67080.63 | I57: 45709 | J57: Approved | K57: Bank Transfer | L57: FY2024-2025 | M57: Urgent | N57: =IF(E57<0,"Credit/Refund","Expense") -> Expense | O57: =IF(AND(OR(J57="Pending",J57="Rejected"),E57>200000),"Flag: High-Value "&J57,"")
A58: EXP-00738 | B58: Operations | C58: Consulting Fees | D58: Wipro | E58: 10526 | F58: 9003.53 | G58: =IF(F58="","",E58-F58) -> 1522.47 | H58: 1522.47 | I58: 45217 | J58: Approved | K58: Bank Transfer | L58: FY2023-2024 | M58: Under review | N58: =IF(E58<0,"Credit/Refund","Expense") -> Expense | O58: =IF(AND(OR(J58="Pending",J58="Rejected"),E58>200000),"Flag: High-Value "&J58,"")
A59: EXP-00490 | B59: Sales | C59: Uncategorized | D59: SAP | E59: 464884 | F59: 581075.86 | G59: =IF(F59="","",E59-F59) -> -116191.86 | H59: -116191.86 | I59: 45636 | J59: Rejected | K59: Vendor Credit | L59: FY2024-2025 | M59: Duplicate entry | N59: =IF(E59<0,"Credit/Refund","Expense") -> Expense | O59: =IF(AND(OR(J59="Pending",J59="Rejected"),E59>200000),"Flag: High-Value "&J59,"") -> Flag: High-Value Rejected
A60: EXP-00449 | B60: Sales | C60: Recruitment | D60: Adobe | E60: 265649 | F60: 235191.89 | G60: =IF(F60="","",E60-F60) -> 30457.11 | H60: 30457.11 | I60: 45298 | J60: Approved | K60: Credit Card | L60: FY2023-2024 | N60: =IF(E60<0,"Credit/Refund","Expense") -> Expense | O60: =IF(AND(OR(J60="Pending",J60="Rejected"),E60>200000),"Flag: High-Value "&J60,"")
A61: EXP-00147 | B61: Finance | C61: Travel | D61: Adobe | E61: 32268 | F61: 26832.63 | G61: =IF(F61="","",E61-F61) -> 5435.37 | H61: 5435.37 | I61: 45157 | J61: Approved | K61: Credit Card | L61: FY2023-2024 | M61: Under review | N61: =IF(E61<0,"Credit/Refund","Expense") -> Expense | O61: =IF(AND(OR(J61="Pending",J61="Rejected"),E61>200000),"Flag: High-Value "&J61,"")
A62: EXP-00348 | B62: Finance | C62: Hardware | D62: Wipro | E62: 79555 | F62: 101962.75 | G62: =IF(F62="","",E62-F62) -> -22407.75 | H62: -22407.75 | I62: 44958 | J62: Approved | K62: Bank Transfer | L62: FY2022-2023 | N62: =IF(E62<0,"Credit/Refund","Expense") -> Expense | O62: =IF(AND(OR(J62="Pending",J62="Rejected"),E62>200000),"Flag: High-Value "&J62,"")
A63: EXP-00372 | B63: Sales | C63: Utilities | D63: Zoom | E63: 411030 | F63: 392369.5 | G63: =IF(F63="","",E63-F63) -> 18660.5 | H63: 18660.5 | I63: 44966 | J63: Approved | K63: Vendor Credit | L63: FY2022-2023 | N63: =IF(E63<0,"Credit/Refund","Expense") -> Expense | O63: =IF(AND(OR(J63="Pending",J63="Rejected"),E63>200000),"Flag: High-Value "&J63,"")
A64: EXP-00397 | B64: Finance | C64: Cloud Infrastructure | D64: HubSpot | E64: 2583687 | F64: 2695007.7 | G64: =IF(F64="","",E64-F64) -> -111320.68 | H64: -111320.68 | I64: 45655 | J64: Pending | K64: Vendor Credit | L64: FY2024-2025 | N64: =IF(E64<0,"Credit/Refund","Expense") -> Expense | O64: =IF(AND(OR(J64="Pending",J64="Rejected"),E64>200000),"Flag: High-Value "&J64,"") -> Flag: High-Value Pending
A65: EXP-00806 | B65: Sales | C65: Travel | D65: Zoom | E65: 99203 | F65: 111995.57 | G65: =IF(F65="","",E65-F65) -> -12792.57 | H65: -12792.57 | I65: 45616 | J65: Approved | K65: Bank Transfer | L65: FY2024-2025 | N65: =IF(E65<0,"Credit/Refund","Expense") -> Expense | O65: =IF(AND(OR(J65="Pending",J65="Rejected"),E65>200000),"Flag: High-Value "&J65,"")
A66: EXP-00660 | B66: Support | C66: Training | D66: Adobe | E66: 413818 | F66: 475823.4 | G66: =IF(F66="","",E66-F66) -> -62005.4 | H66: -62005.4 | I66: 45461 | J66: Pending | K66: Credit Card | L66: FY2024-2025 | N66: =IF(E66<0,"Credit/Refund","Expense") -> Expense | O66: =IF(AND(OR(J66="Pending",J66="Rejected"),E66>200000),"Flag: High-Value "&J66,"") -> Flag: High-Value Pending
A67: EXP-00207 | B67: HR | C67: Utilities | D67: Internal | E67: 277583 | F67: 262488.11 | G67: =IF(F67="","",E67-F67) -> 15094.89 | H67: 15094.89 | I67: 45270 | J67: Pending | K67: Credit Card | L67: FY2023-2024 | M67: Urgent | N67: =IF(E67<0,"Credit/Refund","Expense") -> Expense | O67: =IF(AND(OR(J67="Pending",J67="Rejected"),E67>200000),"Flag: High-Value "&J67,"") -> Flag: High-Value Pending
A68: EXP-00085 | B68: Sales | C68: Training | D68: Salesforce | E68: 457651 | F68: 467629.28 | G68: =IF(F68="","",E68-F68) -> -9978.28 | H68: -9978.28 | I68: 45307 | J68: Approved | K68: Vendor Credit | L68: FY2023-2024 | M68: Urgent | N68: =IF(E68<0,"Credit/Refund","Expense") -> Expense | O68: =IF(AND(OR(J68="Pending",J68="Rejected"),E68>200000),"Flag: High-Value "&J68,"")
A69: EXP-00209 | B69: Support | C69: Salaries | D69: Google Cloud | E69: 62205 | F69: 68491.3 | G69: =IF(F69="","",E69-F69) -> -6286.3 | I69: 45306 | J69: Approved | K69: Petty Cash | L69: FY2023-2024 | M69: Recurring | N69: =IF(E69<0,"Credit/Refund","Expense") -> Expense | O69: =IF(AND(OR(J69="Pending",J69="Rejected"),E69>200000),"Flag: High-Value "&J69,"")
A70: EXP-00089 | B70: Support | C70: Utilities | D70: HubSpot | E70: 395114 | F70: 453184.31 | G70: =IF(F70="","",E70-F70) -> -58070.31 | H70: -58070.31 | I70: 44998 | J70: Pending | K70: Petty Cash | L70: FY2022-2023 | M70: Urgent | N70: =IF(E70<0,"Credit/Refund","Expense") -> Expense | O70: =IF(AND(OR(J70="Pending",J70="Rejected"),E70>200000),"Flag: High-Value "&J70,"") -> Flag: High-Value Pending
A71: EXP-00889 | B71: Sales | C71: Office Supplies | D71: Microsoft Azure | E71: 97690 | F71: 91260.03 | G71: =IF(F71="","",E71-F71) -> 6429.97 | H71: 6429.97 | I71: 45440 | J71: Approved | K71: Petty Cash | L71: FY2024-2025 | N71: =IF(E71<0,"Credit/Refund","Expense") -> Expense | O71: =IF(AND(OR(J71="Pending",J71="Rejected"),E71>200000),"Flag: High-Value "&J71,"")
A72: EXP-00899 | B72: Operations | C72: Recruitment | D72: Zoom | E72: 491563 | F72: 637066.96 | G72: =IF(F72="","",E72-F72) -> -145503.96 | H72: -145503.96 | I72: 44937 | J72: Approved | K72: Vendor Credit | L72: FY2022-2023 | M72: Recurring | N72: =IF(E72<0,"Credit/Refund","Expense") -> Expense | O72: =IF(AND(OR(J72="Pending",J72="Rejected"),E72>200000),"Flag: High-Value "&J72,"")
A73: EXP-00470 | B73: Support | C73: Maintenance | D73: Oracle | E73: 417255 | F73: 398887.4 | G73: =IF(F73="","",E73-F73) -> 18367.6 | H73: 18367.6 | I73: 45228 | J73: Approved | K73: Vendor Credit | L73: FY2023-2024 | M73: Duplicate entry | N73: =IF(E73<0,"Credit/Refund","Expense") -> Expense | O73: =IF(AND(OR(J73="Pending",J73="Rejected"),E73>200000),"Flag: High-Value "&J73,"")
A74: EXP-00720 | B74: Engineering | C74: Utilities | D74: HubSpot | E74: 388564 | F74: 433099.82 | G74: =IF(F74="","",E74-F74) -> -44535.82 | H74: -44535.82 | I74: 45302 | J74: Approved | K74: Credit Card | L74: FY2023-2024 | M74: Urgent | N74: =IF(E74<0,"Credit/Refund","Expense") -> Expense | O74: =IF(AND(OR(J74="Pending",J74="Rejected"),E74>200000),"Flag: High-Value "&J74,"")
A75: EXP-00033 | B75: Sales | C75: Uncategorized | D75: Salesforce | E75: 476675 | F75: 601228.87 | G75: =IF(F75="","",E75-F75) -> -124553.87 | H75: -124553.87 | I75: 45426 | J75: Approved | K75: Vendor Credit | L75: FY2024-2025 | M75: Duplicate entry | N75: =IF(E75<0,"Credit/Refund","Expense") -> Expense | O75: =IF(AND(OR(J75="Pending",J75="Rejected"),E75>200000),"Flag: High-Value "&J75,"")
A76: EXP-00636 | B76: Sales | C76: Software Licenses | D76: HubSpot | E76: 118973 | F76: 134000.41 | G76: =IF(F76="","",E76-F76) -> -15027.41 | H76: -15027.41 | I76: 45671 | J76: Approved | K76: Vendor Credit | L76: FY2024-2025 | N76: =IF(E76<0,"Credit/Refund","Expense") -> Expense | O76: =IF(AND(OR(J76="Pending",J76="Rejected"),E76>200000),"Flag: High-Value "&J76,"")
A77: EXP-00382 | B77: Support | C77: Maintenance | D77: SAP | E77: 22538 | F77: 19899.53 | G77: =IF(F77="","",E77-F77) -> 2638.47 | H77: 2638.47 | I77: 45425 | J77: Approved | K77: Vendor Credit | L77: FY2024-2025 | N77: =IF(E77<0,"Credit/Refund","Expense") -> Expense | O77: =IF(AND(OR(J77="Pending",J77="Rejected"),E77>200000),"Flag: High-Value "&J77,"")
A78: EXP-00550 | B78: Finance | C78: Office Supplies | D78: Zoom | E78: 443662 | G78: =IF(F78="","",E78-F78) | H78: 85569.69 | I78: 45673 | J78: Pending | K78: Vendor Credit | L78: FY2024-2025 | M78: One-time | N78: =IF(E78<0,"Credit/Refund","Expense") -> Expense | O78: =IF(AND(OR(J78="Pending",J78="Rejected"),E78>200000),"Flag: High-Value "&J78,"") -> Flag: High-Value Pending
A79: EXP-00163 | B79: Support | C79: Travel | D79: Slack | E79: 353333 | F79: 458964.2 | G79: =IF(F79="","",E79-F79) -> -105631.2 | H79: -105631.2 | I79: 45702 | J79: Approved | K79: Credit Card | L79: FY2024-2025 | M79: Urgent | N79: =IF(E79<0,"Credit/Refund","Expense") -> Expense | O79: =IF(AND(OR(J79="Pending",J79="Rejected"),E79>200000),"Flag: High-Value "&J79,"")
A80: EXP-00795 | B80: Marketing | C80: Recruitment | D80: Oracle | E80: 290249 | F80: 369613.63 | G80: =IF(F80="","",E80-F80) -> -79364.63 | H80: -79364.63 | I80: 45299 | J80: Approved | K80: Petty Cash | L80: FY2023-2024 | M80: Under review | N80: =IF(E80<0,"Credit/Refund","Expense") -> Expense | O80: =IF(AND(OR(J80="Pending",J80="Rejected"),E80>200000),"Flag: High-Value "&J80,"")
A81: EXP-00727 | B81: Finance | C81: Travel | D81: HubSpot | E81: 309034 | F81: 273262.53 | G81: =IF(F81="","",E81-F81) -> 35771.47 | H81: 35771.47 | I81: 45384 | J81: Pending | K81: Petty Cash | L81: FY2024-2025 | M81: Recurring | N81: =IF(E81<0,"Credit/Refund","Expense") -> Expense | O81: =IF(AND(OR(J81="Pending",J81="Rejected"),E81>200000),"Flag: High-Value "&J81,"") -> Flag: High-Value Pending
A82: EXP-00403 | B82: Engineering | C82: Travel | D82: Microsoft Azure | E82: 106902 | F82: 123641.31 | G82: =IF(F82="","",E82-F82) -> -16739.31 | H82: -16739.31 | I82: 45022 | J82: Pending | K82: Credit Card | L82: FY2023-2024 | N82: =IF(E82<0,"Credit/Refund","Expense") -> Expense | O82: =IF(AND(OR(J82="Pending",J82="Rejected"),E82>200000),"Flag: High-Value "&J82,"")
A83: EXP-00569 | B83: Operations | C83: Travel | D83: Freshdesk | E83: 429973 | F83: 376365.53 | G83: =IF(F83="","",E83-F83) -> 53607.47 | H83: 53607.47 | I83: 45230 | J83: Pending | K83: Vendor Credit | L83: FY2023-2024 | N83: =IF(E83<0,"Credit/Refund","Expense") -> Expense | O83: =IF(AND(OR(J83="Pending",J83="Rejected"),E83>200000),"Flag: High-Value "&J83,"") -> Flag: High-Value Pending
A84: EXP-00396 | B84: Operations | C84: Office Supplies | D84: AWS | E84: 206116 | F84: 229625.18 | G84: =IF(F84="","",E84-F84) -> -23509.18 | H84: -23509.18 | I84: 45699 | J84: Pending | K84: Vendor Credit | L84: FY2024-2025 | N84: =IF(E84<0,"Credit/Refund","Expense") -> Expense | O84: =IF(AND(OR(J84="Pending",J84="Rejected"),E84>200000),"Flag: High-Value "&J84,"") -> Flag: High-Value Pending
A85: EXP-00865 | B85: Unspecified | C85: Travel | D85: Microsoft Azure | E85: 1422304 | F85: 1675743.1 | G85: =IF(F85="","",E85-F85) -> -253439.07 | H85: -253439.07 | I85: 45310 | J85: Approved | K85: Bank Transfer | L85: FY2023-2024 | M85: Recurring | N85: =IF(E85<0,"Credit/Refund","Expense") -> Expense | O85: =IF(AND(OR(J85="Pending",J85="Rejected"),E85>200000),"Flag: High-Value "&J85,"")
A86: EXP-00271 | B86: Operations | C86: Software Licenses | D86: Adobe | E86: 495376 | F86: 532148.51 | G86: =IF(F86="","",E86-F86) -> -36772.51 | H86: -36772.51 | I86: 45728 | J86: Pending | K86: Petty Cash | L86: FY2024-2025 | M86: Recurring | N86: =IF(E86<0,"Credit/Refund","Expense") -> Expense | O86: =IF(AND(OR(J86="Pending",J86="Rejected"),E86>200000),"Flag: High-Value "&J86,"") -> Flag: High-Value Pending
A87: EXP-00272 | B87: HR | C87: Cloud Infrastructure | D87: Zoom | E87: 374421 | F87: 472252.91 | G87: =IF(F87="","",E87-F87) -> -97831.91 | H87: -97831.91 | I87: 45125 | J87: Approved | K87: Credit Card | L87: FY2023-2024 | N87: =IF(E87<0,"Credit/Refund","Expense") -> Expense | O87: =IF(AND(OR(J87="Pending",J87="Rejected"),E87>200000),"Flag: High-Value "&J87,"")
A88: EXP-00583 | B88: HR | C88: Office Supplies | D88: Slack | E88: 277952 | F88: 236373.9 | G88: =IF(F88="","",E88-F88) -> 41578.1 | H88: 41578.1 | I88: 45665 | J88: Rejected | K88: Credit Card | L88: FY2024-2025 | N88: =IF(E88<0,"Credit/Refund","Expense") -> Expense | O88: =IF(AND(OR(J88="Pending",J88="Rejected"),E88>200000),"Flag: High-Value "&J88,"") -> Flag: High-Value Rejected
A89: EXP-00533 | B89: Finance | C89: Maintenance | D89: Salesforce | E89: 314597 | F89: 405247.51 | G89: =IF(F89="","",E89-F89) -> -90650.51 | H89: -90650.51 | I89: 45576 | J89: Pending | K89: Bank Transfer | L89: FY2024-2025 | M89: Recurring | N89: =IF(E89<0,"Credit/Refund","Expense") -> Expense | O89: =IF(AND(OR(J89="Pending",J89="Rejected"),E89>200000),"Flag: High-Value "&J89,"") -> Flag: High-Value Pending
A90: EXP-00371 | B90: Support | C90: Software Licenses | D90: Internal | E90: 109346 | F90: 139986.84 | G90: =IF(F90="","",E90-F90) -> -30640.84 | H90: -30640.84 | I90: 45178 | J90: Pending | K90: Credit Card | L90: FY2023-2024 | M90: Recurring | N90: =IF(E90<0,"Credit/Refund","Expense") -> Expense | O90: =IF(AND(OR(J90="Pending",J90="Rejected"),E90>200000),"Flag: High-Value "&J90,"")
A91: EXP-00835 | B91: Sales | C91: Office Supplies | D91: Freshdesk | E91: -57182 | F91: 60104.14 | G91: =IF(F91="","",E91-F91) -> -117286.14 | I91: 45051 | J91: Approved | K91: Bank Transfer | L91: FY2023-2024 | N91: =IF(E91<0,"Credit/Refund","Expense") -> Credit/Refund | O91: =IF(AND(OR(J91="Pending",J91="Rejected"),E91>200000),"Flag: High-Value "&J91,"")
A92: EXP-00923 | B92: HR | C92: Office Supplies | D92: SAP | E92: 429501 | F92: 466352.17 | G92: =IF(F92="","",E92-F92) -> -36851.17 | H92: -36851.17 | I92: 45638 | J92: Pending | K92: Credit Card | L92: FY2024-2025 | M92: Recurring | N92: =IF(E92<0,"Credit/Refund","Expense") -> Expense | O92: =IF(AND(OR(J92="Pending",J92="Rejected"),E92>200000),"Flag: High-Value "&J92,"") -> Flag: High-Value Pending
A93: EXP-00169 | B93: Sales | C93: Travel | D93: Salesforce | E93: 478753 | F93: 566440.71 | G93: =IF(F93="","",E93-F93) -> -87687.71 | H93: -87687.71 | I93: 45164 | J93: Pending | K93: Bank Transfer | L93: FY2023-2024 | M93: Recurring | N93: =IF(E93<0,"Credit/Refund","Expense") -> Expense | O93: =IF(AND(OR(J93="Pending",J93="Rejected"),E93>200000),"Flag: High-Value "&J93,"") -> Flag: High-Value Pending
A94: EXP-00683 | B94: Sales | C94: Training | D94: Slack | E94: 62031 | F94: 62498.04 | G94: =IF(F94="","",E94-F94) -> -467.04 | H94: -467.04 | I94: 45178 | J94: Rejected | K94: Bank Transfer | L94: FY2023-2024 | N94: =IF(E94<0,"Credit/Refund","Expense") -> Expense | O94: =IF(AND(OR(J94="Pending",J94="Rejected"),E94>200000),"Flag: High-Value "&J94,"")
A95: EXP-00506 | B95: Marketing | C95: Marketing Spend | D95: Slack | E95: 288581 | F95: 353638.16 | G95: =IF(F95="","",E95-F95) -> -65057.16 | H95: -65057.16 | I95: 45602 | J95: Approved | K95: Bank Transfer | L95: FY2024-2025 | M95: Duplicate entry | N95: =IF(E95<0,"Credit/Refund","Expense") -> Expense | O95: =IF(AND(OR(J95="Pending",J95="Rejected"),E95>200000),"Flag: High-Value "&J95,"")
A96: EXP-00540 | B96: Marketing | C96: Utilities | D96: Oracle | E96: 123062 | F96: 152975.35 | G96: =IF(F96="","",E96-F96) -> -29913.35 | H96: -29913.35 | I96: 45200 | J96: Pending | K96: Vendor Credit | L96: FY2023-2024 | M96: Duplicate entry | N96: =IF(E96<0,"Credit/Refund","Expense") -> Expense | O96: =IF(AND(OR(J96="Pending",J96="Rejected"),E96>200000),"Flag: High-Value "&J96,"")
A97: EXP-00532 | B97: Marketing | C97: Consulting Fees | D97: Google Cloud | E97: 481569 | F97: 451100.97 | G97: =IF(F97="","",E97-F97) -> 30468.03 | H97: 30468.03 | I97: 45078 | J97: Approved | K97: Petty Cash | L97: FY2023-2024 | N97: =IF(E97<0,"Credit/Refund","Expense") -> Expense | O97: =IF(AND(OR(J97="Pending",J97="Rejected"),E97>200000),"Flag: High-Value "&J97,"")
A98: EXP-00898 | B98: Sales | C98: Consulting Fees | D98: Salesforce | E98: 163410 | F98: 200577.85 | G98: =IF(F98="","",E98-F98) -> -37167.85 | I98: 45458 | J98: Approved | K98: Bank Transfer | L98: FY2024-2025 | M98: Urgent | N98: =IF(E98<0,"Credit/Refund","Expense") -> Expense | O98: =IF(AND(OR(J98="Pending",J98="Rejected"),E98>200000),"Flag: High-Value "&J98,"")
A99: EXP-00179 | B99: HR | C99: Travel | D99: TCS | E99: 377326 | F99: 461081.99 | G99: =IF(F99="","",E99-F99) -> -83755.99 | H99: -83755.99 | I99: 45255 | J99: Approved | K99: Vendor Credit | L99: FY2023-2024 | N99: =IF(E99<0,"Credit/Refund","Expense") -> Expense | O99: =IF(AND(OR(J99="Pending",J99="Rejected"),E99>200000),"Flag: High-Value "&J99,"")
A100: EXP-00321 | B100: Operations | C100: Marketing Spend | D100: TCS | E100: 79297 | F100: 66599.44 | G100: =IF(F100="","",E100-F100) -> 12697.56 | H100: 12697.56 | I100: 45023 | J100: Approved | K100: Petty Cash | L100: FY2023-2024 | M100: Under review | N100: =IF(E100<0,"Credit/Refund","Expense") -> Expense | O100: =IF(AND(OR(J100="Pending",J100="Rejected"),E100>200000),"Flag: High-Value "&J100,"")
...

Sheet Sales Analysis
A1: Task/Case Study 2 — Part B: Sales Analysis
A2: NovaByte Solutions — source: Cleaned_Sales_Deals (2,500 deals after removing duplicates)
A4: 1. Total Deal Value and Deal Count by Deal Stage and Quarter
A5: Total Deal Value (INR) — all deals regardless of stage outcome
A6: Sum of Deal_Value_INR | B6: Column Labels
A7: Row Labels | B7: Q1-2023 | C7: Q1-2024 | D7: Q1-2025 | E7: Q2-2023 | F7: Q2-2024 | G7: Q3-2023 | H7: Q3-2024 | I7: Q4-2023 | J7: Q4-2024 | K7: Grand Total
A8: Closed Lost | B8: 9141005 | C8: 9689942 | D8: 11235371 | E8: 12418633 | F8: 11860603 | G8: 13566424 | H8: 11346226 | I8: 9339682 | J8: 9138527 | K8: 97736413
A9: Closed Won | B9: 23298342 | C9: 19839336 | D9: 15486634 | E9: 21194799 | F9: 13903057 | G9: 16417272 | H9: 17997739 | I9: 22994816 | J9: 17248504 | K9: 168380499
A10: Negotiation | B10: 12206699 | C10: 8752913 | D10: 11486069 | E10: 13861972 | F10: 10747999 | G10: 11427216 | H10: 13882593 | I10: 11154542 | J10: 11906162 | K10: 105426165
A11: Proposal Sent | B11: 15444405 | C11: 13171347 | D11: 19932319 | E11: 12101534 | F11: 17246961 | G11: 18600069 | H11: 14770864 | I11: 14497360 | J11: 12170242 | K11: 137935101
A12: Prospecting | B12: 6542137 | C12: 12292551 | D12: 8303277 | E12: 11244293 | F12: 7761452 | G12: 4429654 | H12: 8460044 | I12: 7564203 | J12: 6202016 | K12: 72799627
A13: Qualification | B13: 11504094 | C13: 13245808 | D13: 14278340 | E13: 14189296 | F13: 11142002 | G13: 10554962 | H13: 13217207 | I13: 10086169 | J13: 15644643 | K13: 113862521
A14: Grand Total | B14: 78136682 | C14: 76991897 | D14: 80722010 | E14: 85010527 | F14: 72662074 | G14: 74995597 | H14: 79674673 | I14: 75636772 | J14: 72310094 | K14: 696140326
A16: Deal Count by Stage and Quarter
A17: Count of Deal_ID | B17: Column Labels
A18: Row Labels | B18: Q1-2023 | C18: Q1-2024 | D18: Q1-2025 | E18: Q2-2023 | F18: Q2-2024 | G18: Q3-2023 | H18: Q3-2024 | I18: Q4-2023 | J18: Q4-2024 | K18: Grand Total
A19: Closed Lost | B19: 30 | C19: 39 | D19: 46 | E19: 44 | F19: 46 | G19: 44 | H19: 43 | I19: 36 | J19: 33 | K19: 361
A20: Closed Won | B20: 81 | C20: 69 | D20: 63 | E20: 79 | F20: 56 | G20: 60 | H20: 72 | I20: 83 | J20: 61 | K20: 624
A21: Negotiation | B21: 50 | C21: 38 | D21: 41 | E21: 52 | F21: 40 | G21: 42 | H21: 45 | I21: 39 | J21: 46 | K21: 393
A22: Proposal Sent | B22: 56 | C22: 42 | D22: 58 | E22: 44 | F22: 47 | G22: 62 | H22: 50 | I22: 55 | J22: 42 | K22: 456
A23: Prospecting | B23: 26 | C23: 32 | D23: 25 | E23: 42 | F23: 25 | G23: 19 | H23: 30 | I23: 28 | J23: 30 | K23: 257
A24: Qualification | B24: 43 | C24: 54 | D24: 49 | E24: 48 | F24: 42 | G24: 39 | H24: 42 | I24: 40 | J24: 52 | K24: 409
A25: Grand Total | B25: 286 | C25: 274 | D25: 282 | E25: 309 | F25: 256 | G25: 266 | H25: 282 | I25: 281 | J25: 264 | K25: 2500
A27: 2. Win Rate by Sales Rep and by Region
A28: Win Rate = Closed Won / (Closed Won + Closed Lost)
A29: By Sales Rep
A30: Sales_Rep | B30: Closed Won | C30: Closed Lost | D30: Total Closed | E30: Win Rate
A31: Aditya Pillai | B31: =COUNTIFS('Cleaned_Sales_Deals'!$B$2:$B$2501,$A31,'Cleaned_Sales_Deals'!$F$2:$F$2501,"Closed Won") -> 39 | C31: =COUNTIFS('Cleaned_Sales_Deals'!$B$2:$B$2501,$A31,'Cleaned_Sales_Deals'!$F$2:$F$2501,"Closed Lost") -> 24 | D31: =B31+C31 -> 63 | E31: =IF(B31+C31=0,0,B31/(B31+C31)) -> 0.61904762
A32: Amit Pillai | B32: =COUNTIFS('Cleaned_Sales_Deals'!$B$2:$B$2501,$A32,'Cleaned_Sales_Deals'!$F$2:$F$2501,"Closed Won") -> 39 | C32: =COUNTIFS('Cleaned_Sales_Deals'!$B$2:$B$2501,$A32,'Cleaned_Sales_Deals'!$F$2:$F$2501,"Closed Lost") -> 31 | D32: =B32+C32 -> 70 | E32: =IF(B32+C32=0,0,B32/(B32+C32)) -> 0.55714286
A33: Ananya Sharma | B33: =COUNTIFS('Cleaned_Sales_Deals'!$B$2:$B$2501,$A33,'Cleaned_Sales_Deals'!$F$2:$F$2501,"Closed Won") -> 39 | C33: =COUNTIFS('Cleaned_Sales_Deals'!$B$2:$B$2501,$A33,'Cleaned_Sales_Deals'!$F$2:$F$2501,"Closed Lost") -> 22 | D33: =B33+C33 -> 61 | E33: =IF(B33+C33=0,0,B33/(B33+C33)) -> 0.63934426
A34: Arjun Rao | B34: =COUNTIFS('Cleaned_Sales_Deals'!$B$2:$B$2501,$A34,'Cleaned_Sales_Deals'!$F$2:$F$2501,"Closed Won") -> 39 | C34: =COUNTIFS('Cleaned_Sales_Deals'!$B$2:$B$2501,$A34,'Cleaned_Sales_Deals'!$F$2:$F$2501,"Closed Lost") -> 16 | D34: =B34+C34 -> 55 | E34: =IF(B34+C34=0,0,B34/(B34+C34)) -> 0.70909091
A35: Deepika Das | B35: =COUNTIFS('Cleaned_Sales_Deals'!$B$2:$B$2501,$A35,'Cleaned_Sales_Deals'!$F$2:$F$2501,"Closed Won") -> 42 | C35: =COUNTIFS('Cleaned_Sales_Deals'!$B$2:$B$2501,$A35,'Cleaned_Sales_Deals'!$F$2:$F$2501,"Closed Lost") -> 27 | D35: =B35+C35 -> 69 | E35: =IF(B35+C35=0,0,B35/(B35+C35)) -> 0.60869565
A36: Meera Reddy | B36: =COUNTIFS('Cleaned_Sales_Deals'!$B$2:$B$2501,$A36,'Cleaned_Sales_Deals'!$F$2:$F$2501,"Closed Won") -> 34 | C36: =COUNTIFS('Cleaned_Sales_Deals'!$B$2:$B$2501,$A36,'Cleaned_Sales_Deals'!$F$2:$F$2501,"Closed Lost") -> 16 | D36: =B36+C36 -> 50 | E36: =IF(B36+C36=0,0,B36/(B36+C36)) -> 0.68
A37: Neha Pillai | B37: =COUNTIFS('Cleaned_Sales_Deals'!$B$2:$B$2501,$A37,'Cleaned_Sales_Deals'!$F$2:$F$2501,"Closed Won") -> 51 | C37: =COUNTIFS('Cleaned_Sales_Deals'!$B$2:$B$2501,$A37,'Cleaned_Sales_Deals'!$F$2:$F$2501,"Closed Lost") -> 23 | D37: =B37+C37 -> 74 | E37: =IF(B37+C37=0,0,B37/(B37+C37)) -> 0.68918919
A38: Priya Kumar | B38: =COUNTIFS('Cleaned_Sales_Deals'!$B$2:$B$2501,$A38,'Cleaned_Sales_Deals'!$F$2:$F$2501,"Closed Won") -> 32 | C38: =COUNTIFS('Cleaned_Sales_Deals'!$B$2:$B$2501,$A38,'Cleaned_Sales_Deals'!$F$2:$F$2501,"Closed Lost") -> 15 | D38: =B38+C38 -> 47 | E38: =IF(B38+C38=0,0,B38/(B38+C38)) -> 0.68085106
A39: Rahul Patel | B39: =COUNTIFS('Cleaned_Sales_Deals'!$B$2:$B$2501,$A39,'Cleaned_Sales_Deals'!$F$2:$F$2501,"Closed Won") -> 43 | C39: =COUNTIFS('Cleaned_Sales_Deals'!$B$2:$B$2501,$A39,'Cleaned_Sales_Deals'!$F$2:$F$2501,"Closed Lost") -> 30 | D39: =B39+C39 -> 73 | E39: =IF(B39+C39=0,0,B39/(B39+C39)) -> 0.5890411
A40: Riya Das | B40: =COUNTIFS('Cleaned_Sales_Deals'!$B$2:$B$2501,$A40,'Cleaned_Sales_Deals'!$F$2:$F$2501,"Closed Won") -> 49 | C40: =COUNTIFS('Cleaned_Sales_Deals'!$B$2:$B$2501,$A40,'Cleaned_Sales_Deals'!$F$2:$F$2501,"Closed Lost") -> 27 | D40: =B40+C40 -> 76 | E40: =IF(B40+C40=0,0,B40/(B40+C40)) -> 0.64473684
A41: Rohit Mehta | B41: =COUNTIFS('Cleaned_Sales_Deals'!$B$2:$B$2501,$A41,'Cleaned_Sales_Deals'!$F$2:$F$2501,"Closed Won") -> 35 | C41: =COUNTIFS('Cleaned_Sales_Deals'!$B$2:$B$2501,$A41,'Cleaned_Sales_Deals'!$F$2:$F$2501,"Closed Lost") -> 24 | D41: =B41+C41 -> 59 | E41: =IF(B41+C41=0,0,B41/(B41+C41)) -> 0.59322034
A42: Siddharth Gupta | B42: =COUNTIFS('Cleaned_Sales_Deals'!$B$2:$B$2501,$A42,'Cleaned_Sales_Deals'!$F$2:$F$2501,"Closed Won") -> 49 | C42: =COUNTIFS('Cleaned_Sales_Deals'!$B$2:$B$2501,$A42,'Cleaned_Sales_Deals'!$F$2:$F$2501,"Closed Lost") -> 26 | D42: =B42+C42 -> 75 | E42: =IF(B42+C42=0,0,B42/(B42+C42)) -> 0.65333333
... A46: Vikram Patel | B46: =COUNTIFS('Cleaned_Sales_Deals'!$B$2:$B$2501,$A46,'Cleaned_Sales_Deals'!$F$2:$F$2501,"Closed Won") -> 37 | C46: =COUNTIFS('Cleaned_Sales_Deals'!$B$2:$B$2501,$A46,'Cleaned_Sales_Deals'!$F$2:$F$2501,"Closed Lost") -> 26 | D46: =B46+C46 -> 63 | E46: =IF(B46+C46=0,0,B46/(B46+C46)) -> 0.58730159
A48: By Region
A49: Region | B49: Closed Won | C49: Closed Lost | D49: Total Closed | E49: Win Rate
A50: East | B50: =COUNTIFS('Cleaned_Sales_Deals'!$L$2:$L$2501,$A50,'Cleaned_Sales_Deals'!$F$2:$F$2501,"Closed Won") -> 141 | C50: =COUNTIFS('Cleaned_Sales_Deals'!$L$2:$L$2501,$A50,'Cleaned_Sales_Deals'!$F$2:$F$2501,"Closed Lost") -> 89 | D50: =B50+C50 -> 230 | E50: =IF(B50+C50=0,0,B50/(B50+C50)) -> 0.61304348
A51: North | B51: =COUNTIFS('Cleaned_Sales_Deals'!$L$2:$L$2501,$A51,'Cleaned_Sales_Deals'!$F$2:$F$2501,"Closed Won") -> 156 | C51: =COUNTIFS('Cleaned_Sales_Deals'!$L$2:$L$2501,$A51,'Cleaned_Sales_Deals'!$F$2:$F$2501,"Closed Lost") -> 98 | D51: =B51+C51 -> 254 | E51: =IF(B51+C51=0,0,B51/(B51+C51)) -> 0.61417323
A52: South | B52: =COUNTIFS('Cleaned_Sales_Deals'!$L$2:$L$2501,$A52,'Cleaned_Sales_Deals'!$F$2:$F$2501,"Closed Won") -> 166 | C52: =COUNTIFS('Cleaned_Sales_Deals'!$L$2:$L$2501,$A52,'Cleaned_Sales_Deals'!$F$2:$F$2501,"Closed Lost") -> 93 | D52: =B52+C52 -> 259 | E52: =IF(B52+C52=0,0,B52/(B52+C52)) -> 0.64092664
A53: West | B53: =COUNTIFS('Cleaned_Sales_Deals'!$L$2:$L$2501,$A53,'Cleaned_Sales_Deals'!$F$2:$F$2501,"Closed Won") -> 161 | C53: =COUNTIFS('Cleaned_Sales_Deals'!$L$2:$L$2501,$A53,'Cleaned_Sales_Deals'!$F$2:$F$2501,"Closed Lost") -> 81 | D53: =B53+C53 -> 242 | E53: =IF(B53+C53=0,0,B53/(B53+C53)) -> 0.66528926
A57: 3. Average Days to Close by Product and by Lead Source
A58: Calculated over closed deals only (blank Days_to_Close excluded automatically)
A59: By Product
A60: Product | B60: Avg Days to Close | C60: Closed Deal Count
A61: AI Insights Module | B61: =IFERROR(AVERAGEIFS('Cleaned_Sales_Deals'!$J$2:$J$2501,'Cleaned_Sales_Deals'!$D$2:$D$2501,$A61),"") -> 96.086207 | C61: =COUNTIFS('Cleaned_Sales_Deals'!$D$2:$D$2501,$A61,'Cleaned_Sales_Deals'!$J$2:$J$2501,"<>") -> 174
A62: AnalyticsEdge | B62: =IFERROR(AVERAGEIFS('Cleaned_Sales_Deals'!$J$2:$J$2501,'Cleaned_Sales_Deals'!$D$2:$D$2501,$A62),"") -> 95.932584 | C62: =COUNTIFS('Cleaned_Sales_Deals'!$D$2:$D$2501,$A62,'Cleaned_Sales_Deals'!$J$2:$J$2501,"<>") -> 178
A63: CloudShift Platform | B63: =IFERROR(AVERAGEIFS('Cleaned_Sales_Deals'!$J$2:$J$2501,'Cleaned_Sales_Deals'!$D$2:$D$2501,$A63),"") -> 98.548611 | C63: =COUNTIFS('Cleaned_Sales_Deals'!$D$2:$D$2501,$A63,'Cleaned_Sales_Deals'!$J$2:$J$2501,"<>") -> 144
A64: DataVault Pro | B64: =IFERROR(AVERAGEIFS('Cleaned_Sales_Deals'!$J$2:$J$2501,'Cleaned_Sales_Deals'!$D$2:$D$2501,$A64),"") -> 96.044872 | C64: =COUNTIFS('Cleaned_Sales_Deals'!$D$2:$D$2501,$A64,'Cleaned_Sales_Deals'!$J$2:$J$2501,"<>") -> 156
A65: DevOps Accelerator | B65: =IFERROR(AVERAGEIFS('Cleaned_Sales_Deals'!$J$2:$J$2501,'Cleaned_Sales_Deals'!$D$2:$D$2501,$A65),"") -> 97.70122 | C65: =COUNTIFS('Cleaned_Sales_Deals'!$D$2:$D$2501,$A65,'Cleaned_Sales_Deals'!$J$2:$J$2501,"<>") -> 164
A66: SecureNet Suite | B66: =IFERROR(AVERAGEIFS('Cleaned_Sales_Deals'!$J$2:$J$2501,'Cleaned_Sales_Deals'!$D$2:$D$2501,$A66),"") -> 101.88166 | C66: =COUNTIFS('Cleaned_Sales_Deals'!$D$2:$D$2501,$A66,'Cleaned_Sales_Deals'!$J$2:$J$2501,"<>") -> 169
A69: By Lead Source
A70: Lead_Source | B70: Avg Days to Close | C70: Closed Deal Count
A71: Cold Outreach | B71: =IFERROR(AVERAGEIFS('Cleaned_Sales_Deals'!$J$2:$J$2501,'Cleaned_Sales_Deals'!$E$2:$E$2501,$A71),"") -> 90.730769 | C71: =COUNTIFS('Cleaned_Sales_Deals'!$E$2:$E$2501,$A71,'Cleaned_Sales_Deals'!$J$2:$J$2501,"<>") -> 130
A72: Email Campaign | B72: =IFERROR(AVERAGEIFS('Cleaned_Sales_Deals'!$J$2:$J$2501,'Cleaned_Sales_Deals'!$E$2:$E$2501,$A72),"") -> 99.269841 | C72: =COUNTIFS('Cleaned_Sales_Deals'!$E$2:$E$2501,$A72,'Cleaned_Sales_Deals'!$J$2:$J$2501,"<>") -> 126
A73: Google Ads | B73: =IFERROR(AVERAGEIFS('Cleaned_Sales_Deals'!$J$2:$J$2501,'Cleaned_Sales_Deals'!$E$2:$E$2501,$A73),"") -> 93.368 | C73: =COUNTIFS('Cleaned_Sales_Deals'!$E$2:$E$2501,$A73,'Cleaned_Sales_Deals'!$J$2:$J$2501,"<>") -> 125
A74: LinkedIn Campaign | B74: =IFERROR(AVERAGEIFS('Cleaned_Sales_Deals'!$J$2:$J$2501,'Cleaned_Sales_Deals'!$E$2:$E$2501,$A74),"") -> 99.22549 | C74: =COUNTIFS('Cleaned_Sales_Deals'!$E$2:$E$2501,$A74,'Cleaned_Sales_Deals'!$J$2:$J$2501,"<>") -> 102
A75: Organic Search | B75: =IFERROR(AVERAGEIFS('Cleaned_Sales_Deals'!$J$2:$J$2501,'Cleaned_Sales_Deals'!$E$2:$E$2501,$A75),"") -> 100.53043 | C75: =COUNTIFS('Cleaned_Sales_Deals'!$E$2:$E$2501,$A75,'Cleaned_Sales_Deals'!$J$2:$J$2501,"<>") -> 115
A76: Referral | B76: =IFERROR(AVERAGEIFS('Cleaned_Sales_Deals'!$J$2:$J$2501,'Cleaned_Sales_Deals'!$E$2:$E$2501,$A76),"") -> 96.431193 | C76: =COUNTIFS('Cleaned_Sales_Deals'!$E$2:$E$2501,$A76,'Cleaned_Sales_Deals'!$J$2:$J$2501,"<>") -> 109
A77: Trade Show | B77: =IFERROR(AVERAGEIFS('Cleaned_Sales_Deals'!$J$2:$J$2501,'Cleaned_Sales_Deals'!$E$2:$E$2501,$A77),"") -> 105.30769 | C77: =COUNTIFS('Cleaned_Sales_Deals'!$E$2:$E$2501,$A77,'Cleaned_Sales_Deals'!$J$2:$J$2501,"<>") -> 143
A78: Unknown | B78: =IFERROR(AVERAGEIFS('Cleaned_Sales_Deals'!$J$2:$J$2501,'Cleaned_Sales_Deals'!$E$2:$E$2501,$A78),"") -> 110.66667 | C78: =COUNTIFS('Cleaned_Sales_Deals'!$E$2:$E$2501,$A78,'Cleaned_Sales_Deals'!$J$2:$J$2501,"<>") -> 27
A79: Webinar | B79: =IFERROR(AVERAGEIFS('Cleaned_Sales_Deals'!$J$2:$J$2501,'Cleaned_Sales_Deals'!$E$2:$E$2501,$A79),"") -> 92.555556 | C79: =COUNTIFS('Cleaned_Sales_Deals'!$E$2:$E$2501,$A79,'Cleaned_Sales_Deals'!$J$2:$J$2501,"<>") -> 108
A85: 4. Quarterly Revenue Trend — Closed Won Deals Only (Q1-2023 to Q1-2025)
A87: Deal_Stage | B87: Closed Won
A89: Quarter | B89: Closed Won Revenue (INR)
A90: Q1-2023 | B90: 23298342
A91: Q2-2023 | B91: 21194799
A92: Q3-2023 | B92: 16417272
A93: Q4-2023 | B93: 22994816
A94: Q1-2024 | B94: 19839336
A95: Q2-2024 | B95: 13903057
A96: Q3-2024 | B96: 17997739
A97: Q4-2024 | B97: 17248504
A98: Q1-2025 | B98: 15486634

Sheet Finance Analysis
A1: Task/Case Study 2 — Part C: Finance Analysis
A2: NovaByte Solutions — source: Cleaned_Finance_Expenses (1,000 expense records after removing duplicates)
A4: 1. Total Expenses by Department and Category (INR)
A5: Sum of Amount_INR | B5: Column Labels
A6: Row Labels | B6: Cloud Infrastructure | C6: Consulting Fees | D6: Hardware | E6: Maintenance | F6: Marketing Spend | G6: Office Supplies | H6: Recruitment | I6: Salaries | J6: Software Licenses | K6: Training | L6: Travel | M6: Uncategorized | N6: Utilities | O6: Grand Total
A7: Engineering | B7: 5795040 | C7: 1128531 | D7: 3993637 | E7: 924960 | F7: 3446437 | G7: 1300724 | H7: 2355469 | I7: 6370023 | J7: 2513074 | K7: 4206292 | L7: 4135341 | M7: 1255698 | N7: 2590417 | O7: 40015643
A8: Finance | B8: 3646108 | C8: 2209761 | D8: 6637640 | E8: 2277656 | F8: 2847110 | G8: 3964591 | H8: 1771627 | I8: 1313989 | J8: 2349527 | K8: 4061504 | L8: 3983167 | M8: 23074 | N8: 3384454 | O8: 38470208
A9: HR | B9: 4408964 | C9: 5374467 | D9: 7274449 | E9: 2421840 | F9: 3771312 | G9: 7827174 | H9: 2240911 | I9: 1804719 | J9: 1671108 | K9: 6664228 | L9: 3721454 | M9: 628123 | N9: 2867421 | O9: 50676170
A10: Marketing | B10: 7342425 | C10: 1718519 | D10: 9532434 | E10: 2628554 | F10: 2509466 | G10: 2124498 | H10: 2872365 | I10: 2990876 | J10: -1252981 | K10: 3159703 | L10: 2596005 | M10: 1411532 | N10: 2266604 | O10: 39900000
A11: Operations | B11: 1847947 | C11: 5774464 | D11: 4033017 | E11: 3546763 | F11: 9444775 | G11: 2253099 | H11: 5714184 | I11: 945965 | J11: 2739089 | K11: 2271507 | L11: 4032223 | M11: 1090934 | N11: 5834226 | O11: 49528193
A12: Sales | B12: 976653 | C12: 2578908 | D12: 2610012 | E12: 1445061 | F12: 4720848 | G12: 1531770 | H12: 2700212 | I12: 3760367 | J12: 1050435 | K12: 2724040 | L12: 3147054 | M12: 1846065 | N12: 2651718 | O12: 31743143
A13: Support | B13: 2537853 | C13: 4497678 | D13: 1838690 | E13: 7485990 | F13: 5863267 | G13: 2463145 | H13: 2560451 | I13: 3640812 | J13: 3557445 | K13: 2444307 | L13: 7563451 | M13: 328626 | N13: 2046375 | O13: 46828090
A14: Unspecified | B14: 919940 | C14: 620797 | D14: 981466 | E14: 242230 | F14: 435069 | G14: 305519 | H14: 568914 | I14: 1777305 | J14: 229898 | K14: 5333298 | L14: 2554546 | O14: 13968982
A15: Grand Total | B15: 27474930 | C15: 23903125 | D15: 36901345 | E15: 20973054 | F15: 33038284 | G15: 21770520 | H15: 20784133 | I15: 22604056 | J15: 12857595 | K15: 30864879 | L15: 31733241 | M15: 6584052 | N15: 21641215 | O15: 311130429
A18: 2. Budget Variance (Actual vs Allocated) by Department
A19: Variance = Actual - Allocated (signed Amount_INR used, so refunds/credits reduce net spend). Positive = over budget. See Summary sheet for a note on the source Variance_INR column's sign convention.
A20: Row Labels | B20: Total Actual (INR) | C20: Total Allocated (INR) | D20: Variance (INR) | E20: Variance % | F20: Status
A21: Engineering | B21: 40015643 | C21: 48530293 | D21: =B21-C21 -> -8514650.3 | E21: =IF(C21=0,"",D21/C21) -> -0.17545021 | F21: =IF(D21>0,"Over Budget","Under Budget") -> Under Budget
A22: Finance | B22: 38470208 | C22: 41478706 | D22: =B22-C22 -> -3008498.4 | E22: =IF(C22=0,"",D22/C22) -> -0.072531153 | F22: =IF(D22>0,"Over Budget","Under Budget") -> Under Budget
A23: HR | B23: 50676170 | C23: 51893822 | D23: =B23-C23 -> -1217652.5 | E23: =IF(C23=0,"",D23/C23) -> -0.023464305 | F23: =IF(D23>0,"Over Budget","Under Budget") -> Under Budget
A24: Marketing | B24: 39900000 | C24: 50187718 | D24: =B24-C24 -> -10287718 | E24: =IF(C24=0,"",D24/C24) -> -0.20498477 | F24: =IF(D24>0,"Over Budget","Under Budget") -> Under Budget
A25: Operations | B25: 49528193 | C25: 52465663 | D25: =B25-C25 -> -2937469.6 | E25: =IF(C25=0,"",D25/C25) -> -0.05598842 | F25: =IF(D25>0,"Over Budget","Under Budget") -> Under Budget
A26: Sales | B26: 31743143 | C26: 34940189 | D26: =B26-C26 -> -3197046.4 | E26: =IF(C26=0,"",D26/C26) -> -0.091500546 | F26: =IF(D26>0,"Over Budget","Under Budget") -> Under Budget
A27: Support | B27: 46828090 | C27: 47761845 | D27: =B27-C27 -> -933755.38 | E27: =IF(C27=0,"",D27/C27) -> -0.019550237 | F27: =IF(D27>0,"Over Budget","Under Budget") -> Under Budget
A28: Unspecified | B28: 13968982 | C28: 15563379 | D28: =B28-C28 -> -1594396.5 | E28: =IF(C28=0,"",D28/C28) -> -0.1024454 | F28: =IF(D28>0,"Over Budget","Under Budget") -> Under Budget
A31: 3. Top 5 Vendors by Total Spend
A32: Vendor | B32: Total Spend (INR) | C32: Count of Expense_ID
A33: Wipro | B33: 29086598 | C33: 76
A34: Zoom | B34: 26635414 | C34: 61
A35: TCS | B35: 23793501 | C35: 69
A36: AWS | B36: 22876465 | C36: 63
A37: Google Cloud | B37: 21667738 | C37: 58
A40: 4. Rejected or Pending Expenses Above INR 200,000
A41: 181 expense records match this criteria (also flagged live in Cleaned_Finance_Expenses, column O).
A42: Expense_ID | B42: Category | C42: Vendor | D42: Approval Status | E42: Expense Date | F42: Sum of Amount (INR)
A43: EXP-00208 | B43: Salaries | C43: Freshdesk | D43: Pending | E43: 45105 | F43: 4846353
A44: EXP-00936 | B44: Travel | C44: Jira | D44: Pending | E44: 45467 | F44: 4800245
A45: EXP-00105 | B45: Training | C45: Oracle | D45: Rejected | E45: 45012 | F45: 4688784
A46: EXP-00717 | B46: Office Supplies | C46: Internal | D46: Pending | E46: 45464 | F46: 3606815
A47: EXP-00876 | B47: Recruitment | C47: Wipro | D47: Pending | E47: 45154 | F47: 3110100
A48: EXP-00412 | B48: Hardware | C48: Adobe | D48: Rejected | E48: 45484 | F48: 2978304
A49: EXP-00397 | B49: Cloud Infrastructure | C49: HubSpot | D49: Pending | E49: 45655 | F49: 2583687
A50: EXP-00618 | B50: Marketing Spend | C50: Zoom | D50: Rejected | E50: 45569 | F50: 1730163
A51: EXP-00524 | B51: Marketing Spend | C51: Oracle | D51: Pending | E51: 44981 | F51: 1009569
A52: EXP-00289 | B52: Hardware | C52: SAP | D52: Pending | E52: 45585 | F52: 498758
A53: EXP-00251 | B53: Hardware | C53: TCS | D53: Pending | E53: 45361 | F53: 498331
A54: EXP-00015 | B54: Cloud Infrastructure | C54: HubSpot | D54: Rejected | E54: 45541 | F54: 497608
... A223: EXP-00233 | B223: Consulting Fees | C223: Google Cloud | D223: Pending | E223: 45719 | F223: 201346
